Workbook

Sheet file_processing_summary
A1: file_name | B1: file_path | C1: rows_raw | D1: rows_cleaned | E1: columns_raw | F1: columns_final | G1: status
A2: savedrecs_1.xls | B2: C:\Users\Luís Pinto Coelho\Desktop\Dissertação\StudyScreening_Meta-Analysis\data\web_of_science\raw_data\savedrecs_1.xls | C2: 1000 | D2: 1000 | E2: 72 | F2: 25 | G2: ok
A3: savedrecs_2.xls | B3: C:\Users\Luís Pinto Coelho\Desktop\Dissertação\StudyScreening_Meta-Analysis\data\web_of_science\raw_data\savedrecs_2.xls | C3: 1000 | D3: 1000 | E3: 72 | F3: 25 | G3: ok
A4: savedrecs_3.xls | B4: C:\Users\Luís Pinto Coelho\Desktop\Dissertação\StudyScreening_Meta-Analysis\data\web_of_science\raw_data\savedrecs_3.xls | C4: 417 | D4: 417 | E4: 72 | F4: 25 | G4: ok

Sheet input_manifest
A1: file_name | B1: file_path | C1: suffix | D1: size_bytes | E1: modified_time_iso | F1: sha256
A2: savedrecs_1.xls | B2: C:\Users\Luís Pinto Coelho\Desktop\Dissertação\StudyScreening_Meta-Analysis\data\web_of_science\raw_data\savedrecs_1.xls | C2: .xls | D2: 3935744 | E2: 2025-11-07T20:00:34 | F2: 7eb144d274468473421e6e50c00bad5c7bfdee340b9a449acb83ba7a1a5b1cc3
A3: savedrecs_2.xls | B3: C:\Users\Luís Pinto Coelho\Desktop\Dissertação\StudyScreening_Meta-Analysis\data\web_of_science\raw_data\savedrecs_2.xls | C3: .xls | D3: 4025344 | E3: 2025-11-07T20:00:58 | F3: 38d21a0d8d853ac52ece49015ddb184cd9a47805a79dba5d16225e9f73427313
A4: savedrecs_3.xls | B4: C:\Users\Luís Pinto Coelho\Desktop\Dissertação\StudyScreening_Meta-Analysis\data\web_of_science\raw_data\savedrecs_3.xls | C4: .xls | D4: 1800192 | E4: 2025-11-07T20:01:34 | F4: 9ec980e22522d28fe3398a1d6a968b28613fae7b29042b271d37955b4aca9cab

Sheet screening_report
A1: Initial Screening report
A3: Resumo geral
A4: Total de registos | B4: 2417
A5: Classificados | B5: 2417
A6: Por classificar | B6: 0
A7: Included (Label = 1) | B7: 994
A8: Excluded (Label = 0) | B8: 1423
A9: Included (%) | B9: 0.41125362
A10: Excluded (%) | B10: 0.58874638
A12: Distribuição por critério (excluídos)
A13: Critério | B13: N
A14: 1 – Estudo empírico | B14: 350
A15: 2 – Incide sobre trigo | B15: 634
A16: 3 – Stress térmico | B16: 386
A17: 4 – Condição de controlo | B17: 1
A18: 5 – Rendimento ou qualidade do grão | B18: 52
A20: Razões de exclusão — Ordem descdente
A21: Reason to Exclude | B21: N
A22: 2 – Incide sobre trigo | B22: 634
A23: 3 – Stress térmico | B23: 386
A24: 1 – Estudo empírico | B24: 350
A25: 5 – Rendimento ou qualidade do grão | B25: 52
A26: 4 – Condição de controlo | B26: 1

Sheet wos_full_text
A1: record_id | B1: source_record_id | C1: master_id | D1: source | E1: source_priority | F1: run_id | G1: source_path | H1: source_row_index | I1: date_imported | J1: Authors | K1: Publication Year | L1: Title | M1: Abstract | N1: Author Keywords | O1: Source Title | P1: Volume | Q1: Issue | R1: Begin Page | S1: End Page | T1: Article Number | U1: E-mail Address | V1: DOI | W1: DOI Link | X1: pdf_downloaded | Y1: pdf_download_status | Z1: pdf_file_name | AA1: pdf_source_url | AB1: pdf_local_path | AC1: pdf_http_status | AD1: pdf_checked_at | AE1: Label | AF1: Reason to Exclude | AG1: Comment
A2: 3 | B2: WOS_savedrecs_1_r000005 | D2: WoS | E2: 1 | F2: 2026-02-26_005404 | G2: C:\Users\Luís Pinto Coelho\Desktop\Dissertação\StudyScreening_Meta-Analysis\data\web_of_science\raw_data\savedrecs_1.xls | H2: 5 | I2: 2026-02-26 | J2: Choudhary, M; Yan, GJ; Siddique, KHM; Cowling, WA | K2: 2022 | L2: Heat Stress during Meiosis Has Lasting Impacts on Plant Growth and Reproduction in Wheat (Triticum aestivum L.) | M2: Meiosis is the least explored stage for thermotolerance in wheat. We evaluated the impact of 5 d of moderate transient daily heat stress during meiosis in the main stem spike on physiological and grain yield traits in 30 diverse wheat cultivars which vary widely in heat tolerance and sensitivity. We found that a moderate heat stress event during meiosis in the main stem spike had lasting impacts on plant growth and reproduction in heat-sensitive, but not heat-tolerant, wheat cultivars. Heat-tolerant cultivars maintained grain yield, grain number and individual grain weight in the main stem spike and also total plant grain yield and biomass in the heat stress treatment relative to the control. Heat-sensitive cultivars responded to heat stress by producing fewer and smaller grains per spikelet on the main stem, fewer tillers, lower biomass and lower total plant grain yield in the high temperature treatment relative to the control. Heat-sensitive cultivars produced higher flag leaf chlorophyll content in the high temperature treatment relative to the control than heat-tolerant cultivars during the first 3 d of heat treatment. There was small reduction in pollen viability from 98% to 96% following heat stress during meiosis which was unrelated to heat tolerance or sensitivity. Moderate transient heat stress during meiosis did not greatly reduce the production of viable male gametes, but had long-lasting negative impacts on fertilization and subsequent seed production in heat-sensitive cultivars. | N2: wheat (Triticum aestivum); heat stress tolerance; meiosis; grain number; grain weight | O2: AGRONOMY-BASEL | P2: 12 | Q2: 5 | T2: 987 | U2: mukesh.choudhary@research.uwa.edu.au; guijun.yan@uwa.edu.au; kadambot.siddique@uwa.edu.au; wallace.cowling@uwa.edu.au | V2: 10.3390/agronomy12050987 | W2: https://doi.org/10.3390/agronomy12050987 | X2: 0 | Y2: paywalled | Z2: 3__Heat_Stress_during_Meiosis_Has_Lasting_Impacts_on_Plant_Growth_and_Reproduction_in_Wheat_(Triticum_aestivum_L.).pdf | AA2: https://www.mdpi.com/2073-4395/12/5/987 | AC2: 403 | AD2: 2026-03-15 11:24:28 | AE2: =IFERROR(IF(ISBLANK(INDEX(wos_screening_view_full_text!$O:$O, MATCH($A2, wos_screening_view_full_text!$B:$B, 0))), "", INDEX(wos_screening_view_full_text!$O:$O, MATCH($A2, wos_screening_view_full_text!$B:$B, 0))), "") | AF2: =IFERROR(IF(ISBLANK(INDEX(wos_screening_view_full_text!$P:$P, MATCH($A2, wos_screening_view_full_text!$B:$B, 0))), "", INDEX(wos_screening_view_full_text!$P:$P, MATCH($A2, wos_screening_view_full_text!$B:$B, 0))), "") | AG2: =IFERROR(IF(ISBLANK(INDEX(wos_screening_view_full_text!$Q:$Q, MATCH($A2, wos_screening_view_full_text!$B:$B, 0))), "", INDEX(wos_screening_view_full_text!$Q:$Q, MATCH($A2, wos_screening_view_full_text!$B:$B, 0))), "")
A3: 6 | B3: WOS_savedrecs_1_r000011 | D3: WoS | E3: 1 | F3: 2026-02-26_005404 | G3: C:\Users\Luís Pinto Coelho\Desktop\Dissertação\StudyScreening_Meta-Analysis\data\web_of_science\raw_data\savedrecs_1.xls | H3: 11 | I3: 2026-02-26 | J3: Corrêa, AAP; da Silva, FM; Moresco, ER; Cristeli, DS; Souza, JD; Unêda-Trevisoli, SH | K3: 2025 | L3: Multivariate approach for identifying wheat Triticum aestivum L. tolerant to heat and drought stress | M3: Breeding wheat for production in the Brazilian Cerrado region should aim at developing productive genotypes adapted to heat and drought conditions; therefore, this study evaluated the tolerance of wheat cultivars to heat/thermal and drought stress. To meet this objective, 30 wheat cultivars were cultivated in 3 greenhouse environments, namely control, drought, and heat, applying stress from the booting stage to the end of anthesis. The following parameters were evaluated: cycle, plant height, spike number per plant, spike length, spike weight, spikelet number per spike, percentage of fertile spikelets, number of grains per spike, and grain weight per spike. Principal component analysis and cluster analysis were performed by the Ward and K-means methods. Principal component analysis showed that the correlations between the productivity traits and the principal components were more affected by drought than by the control and heat environments. The cluster analyses formed five clusters for the control and heat environments and seven clusters for the drought environment. Grain productivity was highlighted in the heat environment for 'BRS 210', 'BR18 Terena', 'IPR Catuara TM', 'CD 154', 'BR 220', 'MGS Alian & ccedil;a', 'IAC 350', 'IAC Tucunar & eacute;', 'BR 24', 'IAC 5 Maringa', 'UFVT1 Pioneiro', and 'CD 151 4' with a positive relationship in principal component analysis. Considering spikelet number per spike in the drought environment, cultivars 'BRS 208', 'IAC 350', 'Supera', 'BRS 210', 'IPR 85', 'IPR Catuara TM', 'Anahuac 73', 'BR 24', 'IAC 5 Maringa', and 'UFVT1 Pioneiro' were highlighted. In the drought environment, most of the productivity-related traits exhibited components with negative relationships among cultivars and the evaluated traits, confirming their response to the induced stress. | N3: Triticum aestivum; thermal stress; water stress; Cerrado; genotype x environment interactions; Python | O3: ACTA SCIENTIARUM-AGRONOMY | P3: 47 | T3: e70982 | U3: jardel.souza@unesp.br | V3: 10.4025/actasciagron.v47i1.70982 | W3: https://doi.org/10.4025/actasciagron.v47i1.70982 | X3: 1 | Y3: downloaded | Z3: 6__Multivariate_approach_for_identifying_wheat_Triticum_aestivum_L._tolerant_to_heat_and_drought_stress.pdf | AA3: https://periodicos.uem.br/ojs/index.php/ActaSciAgron/article/download/70982/751375159540 | AB3: pdf_files/6__Multivariate_approach_for_identifying_wheat_Triticum_aestivum_L._tolerant_to_heat_and_drought_stress.pdf | AC3: 200 | AD3: 2026-03-15 11:24:33 | AE3: =IFERROR(IF(ISBLANK(INDEX(wos_screening_view_full_text!$O:$O, MATCH($A3, wos_screening_view_full_text!$B:$B, 0))), "", INDEX(wos_screening_view_full_text!$O:$O, MATCH($A3, wos_screening_view_full_text!$B:$B, 0))), "") | AF3: =IFERROR(IF(ISBLANK(INDEX(wos_screening_view_full_text!$P:$P, MATCH($A3, wos_screening_view_full_text!$B:$B, 0))), "", INDEX(wos_screening_view_full_text!$P:$P, MATCH($A3, wos_screening_view_full_text!$B:$B, 0))), "") | AG3: =IFERROR(IF(ISBLANK(INDEX(wos_screening_view_full_text!$Q:$Q, MATCH($A3, wos_screening_view_full_text!$B:$B, 0))), "", INDEX(wos_screening_view_full_text!$Q:$Q, MATCH($A3, wos_screening_view_full_text!$B:$B, 0))), "")
A4: 7 | B4: WOS_savedrecs_1_r000012 | D4: WoS | E4: 1 | F4: 2026-02-26_005404 | G4: C:\Users\Luís Pinto Coelho\Desktop\Dissertação\StudyScreening_Meta-Analysis\data\web_of_science\raw_data\savedrecs_1.xls | H4: 12 | I4: 2026-02-26 | J4: Mahdavi, S; Arzani, A; Maibody, SAMM; Kadivar, M | K4: 2022 | L4: Grain and flour quality of wheat genotypes grown under heat stress | M4: Heat stress during the grain-filling period is the main abiotic stress factor limiting grain yield and quality in wheat (Triticum aestivum L.). In this study, 64 wheat genotypes were exposed to heat stress during reproduction caused by delayed sowing in two growing seasons. Grain yield, 1000 grain weight (GW), grain hardness (GH), and grain-quality related traits were investigated. Heat stress caused a significant decrease in GW through reducing starch content (SC) and a non-compensating rise in protein content (PC), and thereby resulted in lower yield. In addition, significant increases in flour water absorption (WA), Zeleny sedimentation volume (ZT), ash content (AC), lipid content (LC), loaf volume (LV), wet gluten content (WG), dry gluten content (DG), gluten index (GI), and amylopectin content (APC) were found following heat stress. In contrast, decreases in grain moisture content (MC) and amylose content (AMC) induced by heat stress were observed. The heat-tolerant genotypes were superior in grain yield, GW, SC, AMC, and MC. While the sensitive genotypes contained higher PC, LV, GI and AMP. A group of wheat genotypes characterized with a higher yield, AMC, GW, and SC as well as lower PC, WA, GH, ZT, and LV; and was found to be the most heat tolerant by principal component analysis. Lighter weight and smaller grains produce a smaller starchy endosperm with lower quality (less amylose) and higher grain protein content in heat stress compared to normal conditions. Heat stress caused by delayed sowing improves some of the baking-quality related traits. (c) 2022 The Authors. Published by Elsevier B.V. on behalf of King Saud University. This is an open access article under the CC BY-NC-ND license (http://creativecommons.org/licenses/by-nc-nd/4.0/). | N4: Wheat; Global warming; Flour quality; Thermal stress | O4: SAUDI JOURNAL OF BIOLOGICAL SCIENCES | P4: 29 | Q4: 10 | T4: 103417 | U4: soraya.mahdavi@ag.iut.ac.ir; a_arzani@iut.ac.ir; maibody@iut.ac.ir; kadivar@iut.ac.ir | V4: 10.1016/j.sjbs.2022.103417 | W4: https://doi.org/10.1016/j.sjbs.2022.103417 | X4: 0 | Y4: manual_check | Z4: 7__Grain_and_flour_quality_of_wheat_genotypes_grown_under_heat_stress.pdf | AA4: https://linkinghub.elsevier.com/retrieve/pii/S1319562X22003333 | AC4: 200 | AD4: 2026-03-15 11:24:35 | AE4: =IFERROR(IF(ISBLANK(INDEX(wos_screening_view_full_text!$O:$O, MATCH($A4, wos_screening_view_full_text!$B:$B, 0))), "", INDEX(wos_screening_view_full_text!$O:$O, MATCH($A4, wos_screening_view_full_text!$B:$B, 0))), "") | AF4: =IFERROR(IF(ISBLANK(INDEX(wos_screening_view_full_text!$P:$P, MATCH($A4, wos_screening_view_full_text!$B:$B, 0))), "", INDEX(wos_screening_view_full_text!$P:$P, MATCH($A4, wos_screening_view_full_text!$B:$B, 0))), "") | AG4: =IFERROR(IF(ISBLANK(INDEX(wos_screening_view_full_text!$Q:$Q, MATCH($A4, wos_screening_view_full_text!$B:$B, 0))), "", INDEX(wos_screening_view_full_text!$Q:$Q, MATCH($A4, wos_screening_view_full_text!$B:$B, 0))), "")
A5: 8 | B5: WOS_savedrecs_1_r000013 | D5: WoS | E5: 1 | F5: 2026-02-26_005404 | G5: C:\Users\Luís Pinto Coelho\Desktop\Dissertação\StudyScreening_Meta-Analysis\data\web_of_science\raw_data\savedrecs_1.xls | H5: 13 | I5: 2026-02-26 | J5: Mohanty, N | K5: 2003 | L5: Photosynthetic characteristics and enzymatic antioxidant capacity of flag leaf and the grain yield in two cultivars of Triticum aestivum (L.) exposed to warmer growth conditions | M5: Using late sowing practice, the reproductive growth (anthesis and kernel filling) phase of two wheat cultivars, HD1553 and HD2307 was exposed to warmer growth conditions, and the effect on grain yield was examined. The grain weight declined in late-sown plants of both cultivars, but the number of grains per spike decreased drastically in HD1553 plants. In this cultivar exposure to warmer temperature during reproductive phase led to 67% fewer grains per spike. Examination of photosynthetic and enzymatic antioxidant capacity in flag leaves of late-sown plants revealed a marked reduction in chlorophyll and carotenoid pigmentation in addition to a decline in the activity of H2O2 metabolising enzymes in HD1553 cultivar. The photo-oxidative pigment loss due to warmer growth conditions in late-shown HD1553 plants could lead to a reduction in flag leaf photosynthesis and contribute to poor grain yield. | N5: wheat cultivars; heat-tolerance of flag leaf functions; H2O2. metabolising enzymes; flag leaf senescence; reproductive growth and grain yield | O5: JOURNAL OF PLANT PHYSIOLOGY | P5: 160 | Q5: 1 | R5: 71 | S5: 74 | V5: 10.1078/0176-1617-00847 | W5: https://doi.org/10.1078/0176-1617-00847 | X5: 0 | Y5: manual_check | Z5: 8__Photosynthetic_characteristics_and_enzymatic_antioxidant_capacity_of_flag_leaf_and_the_grain_yield_in_two_cultivars_of_Triticum_aestivum_(L..pdf | AA5: https://linkinghub.elsevier.com/retrieve/pii/S017616170470379X | AC5: 200 | AD5: 2026-03-15 11:24:36 | AE5: =IFERROR(IF(ISBLANK(INDEX(wos_screening_view_full_text!$O:$O, MATCH($A5, wos_screening_view_full_text!$B:$B, 0))), "", INDEX(wos_screening_view_full_text!$O:$O, MATCH($A5, wos_screening_view_full_text!$B:$B, 0))), "") | AF5: =IFERROR(IF(ISBLANK(INDEX(wos_screening_view_full_text!$P:$P, MATCH($A5, wos_screening_view_full_text!$B:$B, 0))), "", INDEX(wos_screening_view_full_text!$P:$P, MATCH($A5, wos_screening_view_full_text!$B:$B, 0))), "") | AG5: =IFERROR(IF(ISBLANK(INDEX(wos_screening_view_full_text!$Q:$Q, MATCH($A5, wos_screening_view_full_text!$B:$B, 0))), "", INDEX(wos_screening_view_full_text!$Q:$Q, MATCH($A5, wos_screening_view_full_text!$B:$B, 0))), "")
A6: 11 | B6: WOS_savedrecs_1_r000019 | D6: WoS | E6: 1 | F6: 2026-02-26_005404 | G6: C:\Users\Luís Pinto Coelho\Desktop\Dissertação\StudyScreening_Meta-Analysis\data\web_of_science\raw_data\savedrecs_1.xls | H6: 19 | I6: 2026-02-26 | J6: Cao, XY; Mondal, S; Cheng, DG; Wang, CG; Liu, AF; Song, JM; Li, HS; Zhao, ZD; Liu, JJ | K6: 2015 | L6: Evaluation of agronomic and physiological traits associated with high temperature stress tolerance in the winter wheat cultivars | M6: Post-anthesis high temperature stress is a major concern for the winter wheat producing areas in east China, especially in Shandong province. Fourteen agronomic and physiological traits were studied in 58 Chinese wheat accessions under high-temperature conditions in 2012 and 2013. High temperature stress led to reduction in grain yield and other yield component traits. Significant variations were observed for grain yield per plant (GYPP), grain weight per spike (GWS), thousand kernel weight (TKW), grain number of the main-spike, spikelet number and biological yield per plant. Among the physiological traits measured, chlorophyll content and normalized difference vegetation index showed significant variation under high temperature stress. The results indicate that heat susceptibility index estimated for TKW, GYPP, GWS and flag leaf senescence scale (FLSS) could be used as selection criteria for identifying heat tolerant genotypes for the Shandong province. The results also suggest that FLSS is a good, quick visual indicator of staygreen for field selection for heat tolerance. After harvest, TKW can be measured as final indicator of heat tolerance. The varieties Gaoyou 9415, Hemai 13, Jimai 22, Kexin 9, Shannong 8355, Taishan 23, Yannong 5286 and Zimai 7 were heat tolerant and potential germplasm for heat tolerance breeding in Shandong province and other parts of China. The results could be useful for breeding climate resilient varieties for China or other countries in the world suffering high temperature stresses during grain filling period. | N6: Winter bread wheat; High-temperature; Agronomic traits; Physiological traits; Heat tolerance | O6: ACTA PHYSIOLOGIAE PLANTARUM | P6: 37 | Q6: 4 | T6: 90 | U6: cxytvs@163.com; wheat9561@sina.com | V6: 10.1007/s11738-015-1835-6 | W6: https://doi.org/10.1007/s11738-015-1835-6 | X6: 1 | Y6: downloaded | Z6: 11__Evaluation_of_agronomic_and_physiological_traits_associated_with_high_temperature_stress_tolerance_in_the_winter_wheat_cultivars.pdf | AA6: https://link.springer.com/content/pdf/10.1007/s11738-015-1835-6.pdf | AB6: pdf_files/11__Evaluation_of_agronomic_and_physiological_traits_associated_with_high_temperature_stress_tolerance_in_the_winter_wheat_cultivars.pdf | AC6: 200 | AD6: 2026-03-15 11:24:40 | AE6: =IFERROR(IF(ISBLANK(INDEX(wos_screening_view_full_text!$O:$O, MATCH($A6, wos_screening_view_full_text!$B:$B, 0))), "", INDEX(wos_screening_view_full_text!$O:$O, MATCH($A6, wos_screening_view_full_text!$B:$B, 0))), "") | AF6: =IFERROR(IF(ISBLANK(INDEX(wos_screening_view_full_text!$P:$P, MATCH($A6, wos_screening_view_full_text!$B:$B, 0))), "", INDEX(wos_screening_view_full_text!$P:$P, MATCH($A6, wos_screening_view_full_text!$B:$B, 0))), "") | AG6: =IFERROR(IF(ISBLANK(INDEX(wos_screening_view_full_text!$Q:$Q, MATCH($A6, wos_screening_view_full_text!$B:$B, 0))), "", INDEX(wos_screening_view_full_text!$Q:$Q, MATCH($A6, wos_screening_view_full_text!$B:$B, 0))), "")
A7: 13 | B7: WOS_savedrecs_1_r000023 | D7: WoS | E7: 1 | F7: 2026-02-26_005404 | G7: C:\Users\Luís Pinto Coelho\Desktop\Dissertação\StudyScreening_Meta-Analysis\data\web_of_science\raw_data\savedrecs_1.xls | H7: 23 | I7: 2026-02-26 | J7: Mirosavljevic, M; Mikic, S; Spika, AK; Zupunski, V; Zhou, R; Abdelhakim, L; Ottosen, CO | K7: 2021 | L7: The effect of heat stress on some main spike traits in 12 wheat cultivars at anthesis and mid-grain filling stage | M7: High temperature decreases winter wheat grain yield by reducing the grain number and grain weight. The effect of heat stress on spike grain distribution and weight of individual grains within spike and spikelets was less studied. Our aim is to identify influence of high temperatures during different phenological stages on spike grain distribution and weight and to explore genotypic variation of the studied wheat cultivars. Within this study, controlled experiment was conducted with 12 different winter wheat cultivars under heat stress at anthesis and mid-grain filling stage. The results showed that spike grain weight, thousand-grain weight and grain number per spike decreased moderately in treatments with individual heat stress at anthesis and mid-grain filling period, respectively, which decreased severely in the multiple heat stressed plants at both stages compared with the control treatment. Heat stress decreased number of spikelets with grains. Grain weight at the G1, G2 and G3 positions had positive relationship with spike grain weight. Among the studied Serbian wheat cultivars Suboticanka and Renesansa were identified as the most heat tolerant and sensitive, respectively. Heat tolerance of the studied cultivars should be based on the cultivar capacity to retain higher grain weight, and to maintain production of distal spikelet grains. | N7: cereal; drought; extreme heat; flowering; global warming; Triticum aestivum L. | O7: PLANT SOIL AND ENVIRONMENT | P7: 67 | Q7: 2 | R7: 71 | S7: 76 | U7: milan.mirosavljevic@nsseme.com | V7: 10.17221/457/2020-pse | W7: https://doi.org/10.17221/457/2020-pse | X7: 1 | Y7: downloaded | Z7: 13__The_effect_of_heat_stress_on_some_main_spike_traits_in_12_wheat_cultivars_at_anthesis_and_mid-grain_filling_stage.pdf | AA7: http://pse.agriculturejournals.cz/pdfs/pse/2021/02/02.pdf | AB7: pdf_files/13__The_effect_of_heat_stress_on_some_main_spike_traits_in_12_wheat_cultivars_at_anthesis_and_mid-grain_filling_stage.pdf | AC7: 200 | AD7: 2026-03-15 11:24:43 | AE7: =IFERROR(IF(ISBLANK(INDEX(wos_screening_view_full_text!$O:$O, MATCH($A7, wos_screening_view_full_text!$B:$B, 0))), "", INDEX(wos_screening_view_full_text!$O:$O, MATCH($A7, wos_screening_view_full_text!$B:$B, 0))), "") | AF7: =IFERROR(IF(ISBLANK(INDEX(wos_screening_view_full_text!$P:$P, MATCH($A7, wos_screening_view_full_text!$B:$B, 0))), "", INDEX(wos_screening_view_full_text!$P:$P, MATCH($A7, wos_screening_view_full_text!$B:$B, 0))), "") | AG7: =IFERROR(IF(ISBLANK(INDEX(wos_screening_view_full_text!$Q:$Q, MATCH($A7, wos_screening_view_full_text!$B:$B, 0))), "", INDEX(wos_screening_view_full_text!$Q:$Q, MATCH($A7, wos_screening_view_full_text!$B:$B, 0))), "")
A8: 15 | B8: WOS_savedrecs_1_r000026 | D8: WoS | E8: 1 | F8: 2026-02-26_005404 | G8: C:\Users\Luís Pinto Coelho\Desktop\Dissertação\StudyScreening_Meta-Analysis\data\web_of_science\raw_data\savedrecs_1.xls | H8: 26 | I8: 2026-02-26 | J8: Vedi, A; Raghuvanshi, D; Tripathi, A; Pandey, GC | K8: 2024 | L8: Characterization of Traits Associated with Grain Yield Under Terminal Heat Stress in Bread Wheat (Triticum aestivum L.) on the Basis of Heat Susceptibility Index | M8: High temperature affects various morpho-physiological and agronomical traits in wheat crops. High-temperature stress can cause poor seed growth, reduction in grain filling duration and grain number, root growth and yield reduction. For the identification of heat tolerant genotype, fifteen wheat cultivars were evaluated under timely and late sown conditions based on grain yield in 2018-2019 crop seasons by precise phenotyping approach for this study. Heat susceptibility index (HSI) value recorded for grain filling duration and canopy temperature ranged from 0.57 to 1.35 with a mean value of 1.00 and 0.58-1.29 with a mean value of 1.005, respectively. Grain no./spike and grain weight/spike HSI values ranged from 0.28 to 1.60 (mean value 1.004) and 0.81-1.21 (mean value 0.99), respectively, with thousand-grain weight values ranging from 0.64 to 1.18 (mean value 0.98). Two (WH730 and HUW468) genotypes showed tolerance to heat in all traits, and five genotypes (K7903, RAJ4079, Hindi62, PBW723 and HD3086) showed tolerance in either one trait or none depicting them as sensitive to high temperature. | N8: Heat stress; Heat susceptibility index; Grain yield; Wheat | O8: NATIONAL ACADEMY SCIENCE LETTERS-INDIA | P8: 47 | Q8: 2 | R8: 173 | S8: 175 | U8: aarushivedi@gmail.com | V8: 10.1007/s40009-023-01331-x | W8: https://doi.org/10.1007/s40009-023-01331-x | X8: 1 | Y8: downloaded | Z8: 15__Characterization_of_Traits_Associated_with_Grain_Yield_Under_Terminal_Heat_Stress_in_Bread_Wheat_(Triticum_aestivum_L.)_on_the_Basis_of_Heat.pdf | AA8: https://link.springer.com/content/pdf/10.1007/s40009-023-01331-x.pdf | AB8: pdf_files/15__Characterization_of_Traits_Associated_with_Grain_Yield_Under_Terminal_Heat_Stress_in_Bread_Wheat_(Triticum_aestivum_L.)_on_the_Basis_of_Heat.pdf | AC8: 200 | AD8: 2026-03-15 11:24:46 | AE8: =IFERROR(IF(ISBLANK(INDEX(wos_screening_view_full_text!$O:$O, MATCH($A8, wos_screening_view_full_text!$B:$B, 0))), "", INDEX(wos_screening_view_full_text!$O:$O, MATCH($A8, wos_screening_view_full_text!$B:$B, 0))), "") | AF8: =IFERROR(IF(ISBLANK(INDEX(wos_screening_view_full_text!$P:$P, MATCH($A8, wos_screening_view_full_text!$B:$B, 0))), "", INDEX(wos_screening_view_full_text!$P:$P, MATCH($A8, wos_screening_view_full_text!$B:$B, 0))), "") | AG8: =IFERROR(IF(ISBLANK(INDEX(wos_screening_view_full_text!$Q:$Q, MATCH($A8, wos_screening_view_full_text!$B:$B, 0))), "", INDEX(wos_screening_view_full_text!$Q:$Q, MATCH($A8, wos_screening_view_full_text!$B:$B, 0))), "")
A9: 17 | B9: WOS_savedrecs_1_r000028 | D9: WoS | E9: 1 | F9: 2026-02-26_005404 | G9: C:\Users\Luís Pinto Coelho\Desktop\Dissertação\StudyScreening_Meta-Analysis\data\web_of_science\raw_data\savedrecs_1.xls | H9: 28 | I9: 2026-02-26 | J9: SHPILER, L; BLUM, A | K9: 1990 | L9: HEAT TOLERANCE FOR YIELD AND ITS COMPONENTS IN DIFFERENT WHEAT CULTIVARS | M9: Twenty one diverse, standard and experimental cultivars of common spring wheat (Triticum aestivum L.) were tested for the effect of heat stress on phenology, yield and its components by growing the materials for 2 years under full irrigation during the hot summer (offseason), and the cool winter (normal) conditions. Heat tolerance was estimated for each variable by the 'heat susceptibility index' (S) which scales the reduction in cultivar performance from cool to hot conditions relative to the respective mean reduction over all cultivars. Genotypes differed significantly in S for yield and its components. The ranking of cultivars in S over the 2 years was consistent for yield, kernels per spike and kernel weight, but not for spike number. Of the three yield components, the greatest genotypic variation in S was expressed for kernels per spike. However, S for yield could not be simply attributed to S in a unique component across all cultivars. On the other hand, a general linear model regression of summer yield on its components revealed that the most important yield component affecting yield variation among cultivars under heat stress was kernel number per spike. Kernel number per spike was positively associated across cultivars with longer duration and greater stability of thermal time requirement from emergence to 'double ridge'. It is therefore concluded that kernel number per spike under heat stress is a reasonable estimate of heat tolerance in yield of wheat and that this tolerance is operative already during the first 2 to 3 weeks of growth. | N9: TRITICUM-AESTIVUM; WHEAT; HEAT TOLERANCE; PHENOLOGY; YIELD COMPONENTS; SELECTION | O9: EUPHYTICA | P9: 51 | Q9: 3 | R9: 257 | S9: 263 | V9: 10.1007/bf00039727 | W9: https://doi.org/10.1007/bf00039727 | X9: 1 | Y9: downloaded | Z9: 17__HEAT_TOLERANCE_FOR_YIELD_AND_ITS_COMPONENTS_IN_DIFFERENT_WHEAT_CULTIVARS.pdf | AA9: https://link.springer.com/content/pdf/10.1007/BF00039727.pdf | AB9: pdf_files/17__HEAT_TOLERANCE_FOR_YIELD_AND_ITS_COMPONENTS_IN_DIFFERENT_WHEAT_CULTIVARS.pdf | AC9: 200 | AD9: 2026-03-15 11:24:48 | AE9: =IFERROR(IF(ISBLANK(INDEX(wos_screening_view_full_text!$O:$O, MATCH($A9, wos_screening_view_full_text!$B:$B, 0))), "", INDEX(wos_screening_view_full_text!$O:$O, MATCH($A9, wos_screening_view_full_text!$B:$B, 0))), "") | AF9: =IFERROR(IF(ISBLANK(INDEX(wos_screening_view_full_text!$P:$P, MATCH($A9, wos_screening_view_full_text!$B:$B, 0))), "", INDEX(wos_screening_view_full_text!$P:$P, MATCH($A9, wos_screening_view_full_text!$B:$B, 0))), "") | AG9: =IFERROR(IF(ISBLANK(INDEX(wos_screening_view_full_text!$Q:$Q, MATCH($A9, wos_screening_view_full_text!$B:$B, 0))), "", INDEX(wos_screening_view_full_text!$Q:$Q, MATCH($A9, wos_screening_view_full_text!$B:$B, 0))), "")
A10: 18 | B10: WOS_savedrecs_1_r000029 | D10: WoS | E10: 1 | F10: 2026-02-26_005404 | G10: C:\Users\Luís Pinto Coelho\Desktop\Dissertação\StudyScreening_Meta-Analysis\data\web_of_science\raw_data\savedrecs_1.xls | H10: 29 | I10: 2026-02-26 | J10: Fu, JM; Bowden, RL; Jagadish, SVK; Prasad, PVV | K10: 2023 | L10: Genetic variation for terminal heat stress tolerance in winter wheat | M10: In many regions worldwide wheat (Triticum aestivum L.) plants experience terminal high temperature stress during the grain filling stage, which is a leading cause for single seed weight decrease and consequently for grain yield reduction. An approach to mitigate high temperature damage is to develop tolerant cultivars using the conventional breeding approach which involves identifying tolerant lines and then incorporating the tolerant traits in commercial varieties. In this study, we evaluated the terminal heat stress tolerance of 304 diverse elite winter wheat lines from wheat breeding programs in the US, Australia, and Serbia in controlled environmental conditions. Chlorophyll content and yield traits were measured and calculated as the percentage of non-stress control. The results showed that there was significant genetic variation for chlorophyll retention and seed weight under heat stress conditions. The positive correlation between the percent of chlorophyll content and the percent of single seed weight was significant. Two possible mechanisms of heat tolerance during grain filling were proposed. One represented by wheat line OK05723W might be mainly through the current photosynthesis since the high percentage of single seed weight was accompanied with high percentages of chlorophyll content and high shoot dry weight, and the other represented by wheat Line TX04M410164 might be mainly through the relocation of reserves since the high percentage of single seed weight was accompanied with low percentages of chlorophyll content and low shoot dry weight under heat stress. The tolerant genotypes identified in this study should be useful for breeding programs after further validation. | N10: heat stress; wheat; chlorophyll; yield components; controlled environment | O10: FRONTIERS IN PLANT SCIENCE | P10: 14 | T10: 1132108 | U10: jianming@ksu.edu | V10: 10.3389/fpls.2023.1132108 | W10: https://doi.org/10.3389/fpls.2023.1132108 | X10: 1 | Y10: downloaded | Z10: 18__Genetic_variation_for_terminal_heat_stress_tolerance_in_winter_wheat.pdf | AA10: https://public-pages-files-2025.frontiersin.org/journals/plant-science/articles/10.3389/fpls.2023.1132108/pdf | AB10: pdf_files/18__Genetic_variation_for_terminal_heat_stress_tolerance_in_winter_wheat.pdf | AC10: 200 | AD10: 2026-03-15 11:24:52 | AE10: =IFERROR(IF(ISBLANK(INDEX(wos_screening_view_full_text!$O:$O, MATCH($A10, wos_screening_view_full_text!$B:$B, 0))), "", INDEX(wos_screening_view_full_text!$O:$O, MATCH($A10, wos_screening_view_full_text!$B:$B, 0))), "") | AF10: =IFERROR(IF(ISBLANK(INDEX(wos_screening_view_full_text!$P:$P, MATCH($A10, wos_screening_view_full_text!$B:$B, 0))), "", INDEX(wos_screening_view_full_text!$P:$P, MATCH($A10, wos_screening_view_full_text!$B:$B, 0))), "") | AG10: =IFERROR(IF(ISBLANK(INDEX(wos_screening_view_full_text!$Q:$Q, MATCH($A10, wos_screening_view_full_text!$B:$B, 0))), "", INDEX(wos_screening_view_full_text!$Q:$Q, MATCH($A10, wos_screening_view_full_text!$B:$B, 0))), "")
A11: 19 | B11: WOS_savedrecs_1_r000030 | D11: WoS | E11: 1 | F11: 2026-02-26_005404 | G11: C:\Users\Luís Pinto Coelho\Desktop\Dissertação\StudyScreening_Meta-Analysis\data\web_of_science\raw_data\savedrecs_1.xls | H11: 30 | I11: 2026-02-26 | J11: Sharma, RC; Tiwary, AK; Ortiz-Ferrara, G | K11: 2008 | L11: Reduction in kernel weight as a potential indirect selection criterion for wheat grain yield under terminal heat stress | M11: Heat is an important abiotic stress during wheat (Triticum aestivum L.) grain-filling in South Asia. A study was undertaken to determine effectiveness of selection for reduction in 1000-kernel weight (TKWR) under heat stress to increase grain yield. Selection was made for low and high TKWR and selected progenies were evaluated in timely and late seeded trials at two locations in Nepal in 2003. One thousand kernel weight (TKW), biomass yield, grain yield, harvest index (HI), grain-filling duration (GFD) and area under spot blotch progress curve per day (AUDPC/day) were examined. The low and high TKWR groups did not differ significantly for TKW, biomass yield, grain yield, HI, days to heading, GFD and AUDPC/day under timely seeding. However, low TKWR lines showed higher TKW, biomass yield, grain yield, HI, and GFD and lower AUDPC/day than the lines with high TKWR under late seeding. Realized heritability estimates for TKWR ranged from 0.68 to 0.85. The findings show that selection for low TKWR could be used as an indirect selection criterion to identify high grain yielding lines under terminal heat stress. | N11: grain yield; heat stress; heritability; kernel weight; seeding date; selection; Triticum aestivum; wheat | O11: PLANT BREEDING | P11: 127 | Q11: 3 | R11: 241 | S11: 248 | U11: rsharma@ecomail.com.np | V11: 10.1111/j.1439-0523.2007.01460.x | W11: https://doi.org/10.1111/j.1439-0523.2007.01460.x | X11: 0 | Y11: paywalled | Z11: 19__Reduction_in_kernel_weight_as_a_potential_indirect_selection_criterion_for_wheat_grain_yield_under_terminal_heat_stress.pdf | AA11: https://onlinelibrary.wiley.com/doi/10.1111/j.1439-0523.2007.01460.x | AC11: 403 | AD11: 2026-03-15 11:24:53 | AE11: =IFERROR(IF(ISBLANK(INDEX(wos_screening_view_full_text!$O:$O, MATCH($A11, wos_screening_view_full_text!$B:$B, 0))), "", INDEX(wos_screening_view_full_text!$O:$O, MATCH($A11, wos_screening_view_full_text!$B:$B, 0))), "") | AF11: =IFERROR(IF(ISBLANK(INDEX(wos_screening_view_full_text!$P:$P, MATCH($A11, wos_screening_view_full_text!$B:$B, 0))), "", INDEX(wos_screening_view_full_text!$P:$P, MATCH($A11, wos_screening_view_full_text!$B:$B, 0))), "") | AG11: =IFERROR(IF(ISBLANK(INDEX(wos_screening_view_full_text!$Q:$Q, MATCH($A11, wos_screening_view_full_text!$B:$B, 0))), "", INDEX(wos_screening_view_full_text!$Q:$Q, MATCH($A11, wos_screening_view_full_text!$B:$B, 0))), "")
A12: 23 | B12: WOS_savedrecs_1_r000035 | D12: WoS | E12: 1 | F12: 2026-02-26_005404 | G12: C:\Users\Luís Pinto Coelho\Desktop\Dissertação\StudyScreening_Meta-Analysis\data\web_of_science\raw_data\savedrecs_1.xls | H12: 35 | I12: 2026-02-26 | J12: Mahdavi, S; Arzani, A; Maibody, SAMM; Mehrabi, AA | K12: 2021 | L12: Photosynthetic and yield performance of wheat (Triticum aestivum L.) under sowing in hot environment | M12: Heat stress during the post-flowering and grain development stages is a key abiotic stress influencing grain yield in wheat (Triticum aestivum L.). In this study, 64 wheat genotypes, in their terminal growth stage, were subjected to two field temperatures caused by delayed sowing in two consecutive growing seasons. Results of photosynthetic gas exchange, chlorophyll fluorescence, yield attributes, and grain yield investigations were subjected to combined analysis of variance, which revealed significant differences in the 1000 grain weight (GW), grain filling duration (GFD), grain yield, gas exchange parameters, and maximum quantum efficiency PSII photochemistry (Fv/Fm) among the genotypes (G) between the normal and heat stress conditions (E) and G x E interactions. Heat stress accelerated reproductive phases and shortened GFD leading to lower GW and grain yield. Exposure to heat stress resulted in significant decreases in net CO2 assimilation rate (P-N), stomatal conductance (gs), transpiration rate (E), iWUE, WUE, Fv/Fm ratio, and yield, while it increased sub-stomatal CO2 concentration (C-i). Moreover, grain yield was found to be strongly correlated with C-i, Fv/Fm, and P-N. Path coefficient analysis and stepwise multiple regression revealed that greater improvements will be achieved in C-i and Fv/Fm by increasing yield and P-N performance when wheat is bred for tolerance to heat stress than those achieved by breeders under normal growing conditions. | N12: Global warming; Thermal stress; Photosynthesis; Chlorophyll fluorescent; Common wheat | O12: ACTA PHYSIOLOGIAE PLANTARUM | P12: 43 | Q12: 7 | T12: 106 | U12: a_arzani@iut.ac.ir | V12: 10.1007/s11738-021-03278-2 | W12: https://doi.org/10.1007/s11738-021-03278-2 | X12: 1 | Y12: downloaded | Z12: 23__Photosynthetic_and_yield_performance_of_wheat_(Triticum_aestivum_L.)_under_sowing_in_hot_environment.pdf | AA12: https://link.springer.com/content/pdf/10.1007/s11738-021-03278-2.pdf | AB12: pdf_files/23__Photosynthetic_and_yield_performance_of_wheat_(Triticum_aestivum_L.)_under_sowing_in_hot_environment.pdf | AC12: 200 | AD12: 2026-03-15 11:24:56 | AE12: =IFERROR(IF(ISBLANK(INDEX(wos_screening_view_full_text!$O:$O, MATCH($A12, wos_screening_view_full_text!$B:$B, 0))), "", INDEX(wos_screening_view_full_text!$O:$O, MATCH($A12, wos_screening_view_full_text!$B:$B, 0))), "") | AF12: =IFERROR(IF(ISBLANK(INDEX(wos_screening_view_full_text!$P:$P, MATCH($A12, wos_screening_view_full_text!$B:$B, 0))), "", INDEX(wos_screening_view_full_text!$P:$P, MATCH($A12, wos_screening_view_full_text!$B:$B, 0))), "") | AG12: =IFERROR(IF(ISBLANK(INDEX(wos_screening_view_full_text!$Q:$Q, MATCH($A12, wos_screening_view_full_text!$B:$B, 0))), "", INDEX(wos_screening_view_full_text!$Q:$Q, MATCH($A12, wos_screening_view_full_text!$B:$B, 0))), "")
A13: 24 | B13: WOS_savedrecs_1_r000036 | D13: WoS | E13: 1 | F13: 2026-02-26_005404 | G13: C:\Users\Luís Pinto Coelho\Desktop\Dissertação\StudyScreening_Meta-Analysis\data\web_of_science\raw_data\savedrecs_1.xls | H13: 36 | I13: 2026-02-26 | J13: Schmidt, J; Tricker, PJ; Eckermann, P; Kalambettu, P; Garcia, M; Fleury, D | K13: 2020 | L13: Novel Alleles for Combined Drought and Heat Stress Tolerance in Wheat | M13: Drought and heat waves commonly co-occur in many wheat-growing regions causing significant crop losses. The identification of stress associated quantitative trait loci, particularly those for yield, is problematic due to their association with plant phenology and the high genetic x environment interaction. Here we studied a panel of 315 diverse, spring type accessions of bread wheat (Triticum aestivum) in pots in a semi-controlled environment under combined drought and heat stress over 2 years. Importantly, we treated individual plants according to their flowering time. We found 134 out of the 145 identified loci for grain weight that were not associated with either plant phenology or plant height. The majority of loci uncovered here were novel, with favorable alleles widespread in Asian and African landraces providing opportunities for their incorporation into modern varieties through breeding. Using residual heterozygosity in lines from a nested association mapping population, we were able to rapidly develop near-isogenic lines for important target loci. One target locus on chromosome 6A contributed to higher grain weight, harvest index, thousand kernel weight, and grain number under drought and heat stress in field conditions consistent with allelic effects demonstrated in the genome-wide association study. | N13: genome-wide association; quantitative trait loci; near-isogenic lines; Triticum; abiotic; genetic diversity | O13: FRONTIERS IN PLANT SCIENCE | P13: 10 | T13: 1800 | U13: melissa.garcia@adelaida.edu.au | V13: 10.3389/fpls.2019.01800 | W13: https://doi.org/10.3389/fpls.2019.01800 | X13: 1 | Y13: downloaded | Z13: 24__Novel_Alleles_for_Combined_Drought_and_Heat_Stress_Tolerance_in_Wheat.pdf | AA13: https://public-pages-files-2025.frontiersin.org/journals/plant-science/articles/10.3389/fpls.2019.01800/pdf | AB13: pdf_files/24__Novel_Alleles_for_Combined_Drought_and_Heat_Stress_Tolerance_in_Wheat.pdf | AC13: 200 | AD13: 2026-03-15 11:24:59 | AE13: =IFERROR(IF(ISBLANK(INDEX(wos_screening_view_full_text!$O:$O, MATCH($A13, wos_screening_view_full_text!$B:$B, 0))), "", INDEX(wos_screening_view_full_text!$O:$O, MATCH($A13, wos_screening_view_full_text!$B:$B, 0))), "") | AF13: =IFERROR(IF(ISBLANK(INDEX(wos_screening_view_full_text!$P:$P, MATCH($A13, wos_screening_view_full_text!$B:$B, 0))), "", INDEX(wos_screening_view_full_text!$P:$P, MATCH($A13, wos_screening_view_full_text!$B:$B, 0))), "") | AG13: =IFERROR(IF(ISBLANK(INDEX(wos_screening_view_full_text!$Q:$Q, MATCH($A13, wos_screening_view_full_text!$B:$B, 0))), "", INDEX(wos_screening_view_full_text!$Q:$Q, MATCH($A13, wos_screening_view_full_text!$B:$B, 0))), "")
A14: 26 | B14: WOS_savedrecs_1_r000039 | D14: WoS | E14: 1 | F14: 2026-02-26_005404 | G14: C:\Users\Luís Pinto Coelho\Desktop\Dissertação\StudyScreening_Meta-Analysis\data\web_of_science\raw_data\savedrecs_1.xls | H14: 39 | I14: 2026-02-26 | J14: Tahir, ISA; Nakata, N; Ali, AM; Mustafa, HM; Saad, ASI; Takata, K; Ishikawa, N; Abdalla, OS | K14: 2006 | L14: Genotypic and temperature effects on wheat grain yield and quality in a hot irrigated environment | M14: High temperature influences both grain yield and end-use quality of wheat. The objectives of this study were to evaluate the performance of selected wheat genotypes under heat stress and to examine the effects of high temperatures during grain filling on grain yield and end-use quality parameters. Fifteen bread wheat genotypes in 2000/2001 and 18 eenotypes in 2002/2003 were evaluated under the optimum and late-sowing conditions of the irrigated hot environment of the Gezira Research Farm, Wad Medam, Sudan. The genotypes comprised released varieties and elite lines from the Sudanese wheat improvement programme. Data collected included grain yield, grain weight and grain end-use quality including protein content, protein composition, SDS sedimentation values (SDSS) and gluten strength as determined by mixograph analyses. High temperatures significantly decreased grain yield by decreasing grain weight. Although genotypes exhibited variation in magnitude of response, results indicated that high temperature during grain filling increased both soluble and insoluble protein contents, SDSS, mixograph peak height (MPH) and the descending slope at 2 min past peak (MDS). In contrast, mixograph peak time (MPT) and the curve width at 2 min past peak (MCW) were significantly decreased. Flour protein correlated positively with SDSS, MPH and MDS and negatively with MCW. MPT correlated negatively with MDS and positively with MCW. Results indicate that high temperature increased both soluble and insoluble protein contents, SDSS and MPH, and hence the gluten strength, but decreased flour mixing time and tolerance and hence the dough elasticity. Variation observed among genotypes suggests that grain end-use quality could be improved under high temperature conditions utilizing the available variability; however, it might require evaluation under various growing conditions. | N14: Triticum aestivum; high temperature; grain quality; late sowing; mixograph parameters | O14: PLANT BREEDING | P14: 125 | Q14: 4 | R14: 323 | S14: 330 | U14: izzatahir@yahoo.com | V14: 10.1111/j.1439-0523.2006.01236.x | W14: https://doi.org/10.1111/j.1439-0523.2006.01236.x | X14: 0 | Y14: paywalled | Z14: 26__Genotypic_and_temperature_effects_on_wheat_grain_yield_and_quality_in_a_hot_irrigated_environment.pdf | AA14: https://onlinelibrary.wiley.com/doi/10.1111/j.1439-0523.2006.01236.x | AC14: 403 | AD14: 2026-03-15 11:25:00 | AE14: =IFERROR(IF(ISBLANK(INDEX(wos_screening_view_full_text!$O:$O, MATCH($A14, wos_screening_view_full_text!$B:$B, 0))), "", INDEX(wos_screening_view_full_text!$O:$O, MATCH($A14, wos_screening_view_full_text!$B:$B, 0))), "") | AF14: =IFERROR(IF(ISBLANK(INDEX(wos_screening_view_full_text!$P:$P, MATCH($A14, wos_screening_view_full_text!$B:$B, 0))), "", INDEX(wos_screening_view_full_text!$P:$P, MATCH($A14, wos_screening_view_full_text!$B:$B, 0))), "") | AG14: =IFERROR(IF(ISBLANK(INDEX(wos_screening_view_full_text!$Q:$Q, MATCH($A14, wos_screening_view_full_text!$B:$B, 0))), "", INDEX(wos_screening_view_full_text!$Q:$Q, MATCH($A14, wos_screening_view_full_text!$B:$B, 0))), "")
A15: 27 | B15: WOS_savedrecs_1_r000040 | D15: WoS | E15: 1 | F15: 2026-02-26_005404 | G15: C:\Users\Luís Pinto Coelho\Desktop\Dissertação\StudyScreening_Meta-Analysis\data\web_of_science\raw_data\savedrecs_1.xls | H15: 40 | I15: 2026-02-26 | J15: Narayanan, S; Prasad, PVV; Fritz, AK; Boyle, DL; Gill, BS | K15: 2015 | L15: Impact of High Night-Time and High Daytime Temperature Stress on Winter Wheat | M15: High temperature is a major environmental factor that limits wheat (Triticum aestivum L.) productivity. Climate models predict greater increases in night-time temperature than in daytime temperature. The objective of this research was to compare the effects of high daytime and high night-time temperatures during anthesis on physiological (chlorophyll fluorescence, chlorophyll concentration, leaf level photosynthesis, and membrane damage), biochemical (reactive oxygen species (ROS) concentration and antioxidant capacity in leaves), growth and yield traits of wheat genotypes. Winter wheat genotypes (Ventnor and Karl 92) were grown at optimum temperatures (25/15 degrees C, maximum/minimum) until the onset of anthesis. Thereafter, plants were exposed to high night-time (HN, 25/24 degrees C), high daytime (HD, 35/15 degrees C), high daytime and night-time (HDN, 35/24 degrees C) or optimum temperatures for 7days. Compared with optimum temperature, HN, HD and HDN increased ROS concentration and membrane damage and decreased antioxidant capacity, photochemical efficiency, leaf level photosynthesis, seed set, grain number and grain yield per spike. Impact of HN and HD was similar on all traits. Greater impact on seed set, grain number and grain yield per spike was observed at HDN compared with HN and HD. These results suggest that HN and HD during anthesis cause damage of a similar magnitude to winter wheat. | N15: grain yield; high daytime and night-time temperature; high daytime temperature; high night-time temperature; photosynthesis; wheat | O15: JOURNAL OF AGRONOMY AND CROP SCIENCE | P15: 201 | Q15: 3 | R15: 206 | S15: 218 | U15: vara@ksu.edu | V15: 10.1111/jac.12101 | W15: https://doi.org/10.1111/jac.12101 | X15: 0 | Y15: paywalled | Z15: 27__Impact_of_High_Night-Time_and_High_Daytime_Temperature_Stress_on_Winter_Wheat.pdf | AA15: https://onlinelibrary.wiley.com/doi/10.1111/jac.12101 | AC15: 403 | AD15: 2026-03-15 11:25:02 | AE15: =IFERROR(IF(ISBLANK(INDEX(wos_screening_view_full_text!$O:$O, MATCH($A15, wos_screening_view_full_text!$B:$B, 0))), "", INDEX(wos_screening_view_full_text!$O:$O, MATCH($A15, wos_screening_view_full_text!$B:$B, 0))), "") | AF15: =IFERROR(IF(ISBLANK(INDEX(wos_screening_view_full_text!$P:$P, MATCH($A15, wos_screening_view_full_text!$B:$B, 0))), "", INDEX(wos_screening_view_full_text!$P:$P, MATCH($A15, wos_screening_view_full_text!$B:$B, 0))), "") | AG15: =IFERROR(IF(ISBLANK(INDEX(wos_screening_view_full_text!$Q:$Q, MATCH($A15, wos_screening_view_full_text!$B:$B, 0))), "", INDEX(wos_screening_view_full_text!$Q:$Q, MATCH($A15, wos_screening_view_full_text!$B:$B, 0))), "")
A16: 29 | B16: WOS_savedrecs_1_r000043 | D16: WoS | E16: 1 | F16: 2026-02-26_005404 | G16: C:\Users\Luís Pinto Coelho\Desktop\Dissertação\StudyScreening_Meta-Analysis\data\web_of_science\raw_data\savedrecs_1.xls | H16: 43 | I16: 2026-02-26 | J16: Zhang, XX; Högy, P; Wu, XN; Schmid, I; Wang, XL; Schulze, WX; Jiang, D; Fangmeier, A | K16: 2018 | L16: Physiological and Proteomic Evidence for the Interactive Effects of Post-Anthesis Heat Stress and Elevated CO2 on Wheat | M16: Elevated CO2 promotes leaf photosynthesis and improves crop grain yield. However, as a major anthropogenic greenhouse gas, CO2 contributes to more frequent and severe heat stress, which threatens crop productivity. The combined effects of elevated CO2 and heat stress are complex, and the underlying mechanisms are poorly understood. In the present study, the effects of elevated CO2 and high-temperature on foliar physiological traits and the proteome of spring wheat grown under two CO2 concentrations (380 and 550 mu mol mol(-1)) and two temperature conditions (ambient and post-anthesis heat stress) are examined. Elevated CO2 increases leaf photosynthetic traits, biomass, and grain yield, while heat stress depresses photosynthesis and yield. Temperature-induced impacts on chlorophyll content and grain yield are not significantly different under the two CO2 concentrations. Analysis of the leaf proteome reveals that proteins involved in photosynthesis as well as antioxidant and protein synthesis pathways are significantly downregulated-due to the combination of elevated CO2 and heat stress. Correspondingly, plants treated with elevated CO2 and heat stress exhibit decreased green leaf area, photosynthetic rate, antioxidant enzyme activities, and 1000-kernel weight. The present study demonstrates that future post-anthesis heat episodes will diminish the positive effects of elevated CO2 and negatively impact wheat production. | N16: elevated CO2; grain yield; heat stress; proteomics; wheat (Triticum aestivum L.) | O16: PROTEOMICS | P16: 18 | Q16: 23 | T16: 1800262 | U16: Petra.Hoegy@uni-hohenheim.de; jiangd@njau.edu.cn | V16: 10.1002/pmic.201800262 | W16: https://doi.org/10.1002/pmic.201800262 | X16: 0 | Y16: paywalled | Z16: 29__Physiological_and_Proteomic_Evidence_for_the_Interactive_Effects_of_Post-Anthesis_Heat_Stress_and_Elevated_CO2_on_Wheat.pdf | AA16: https://analyticalsciencejournals.onlinelibrary.wiley.com/doi/10.1002/pmic.201800262 | AC16: 403 | AD16: 2026-03-15 11:25:03 | AE16: =IFERROR(IF(ISBLANK(INDEX(wos_screening_view_full_text!$O:$O, MATCH($A16, wos_screening_view_full_text!$B:$B, 0))), "", INDEX(wos_screening_view_full_text!$O:$O, MATCH($A16, wos_screening_view_full_text!$B:$B, 0))), "") | AF16: =IFERROR(IF(ISBLANK(INDEX(wos_screening_view_full_text!$P:$P, MATCH($A16, wos_screening_view_full_text!$B:$B, 0))), "", INDEX(wos_screening_view_full_text!$P:$P, MATCH($A16, wos_screening_view_full_text!$B:$B, 0))), "") | AG16: =IFERROR(IF(ISBLANK(INDEX(wos_screening_view_full_text!$Q:$Q, MATCH($A16, wos_screening_view_full_text!$B:$B, 0))), "", INDEX(wos_screening_view_full_text!$Q:$Q, MATCH($A16, wos_screening_view_full_text!$B:$B, 0))), "")
A17: 31 | B17: WOS_savedrecs_1_r000045 | D17: WoS | E17: 1 | F17: 2026-02-26_005404 | G17: C:\Users\Luís Pinto Coelho\Desktop\Dissertação\StudyScreening_Meta-Analysis\data\web_of_science\raw_data\savedrecs_1.xls | H17: 45 | I17: 2026-02-26 | J17: Jagadeesha, YK; Navathe, S; Krishnappa, G; Ambati, D; Baviskar, V; Biradar, S; Magar, N; Mishra, CN; Mamrutha, HM; Govindan, V; Singh, GP; Singh, G | K17: 2024 | L17: Multi-Environment Analysis of Nutritional and Grain Quality Traits in Relation to Grain Yield Under Drought and Terminal Heat Stress in Bread Wheat and Durum Wheat | M17: Heat and drought are two important constraints to global wheat productivity; understanding the genotypic responses for quality parameters under harsh production conditions (drought and heat) is very important for developing nutrient-dense wheat varieties. A set of 15 modern bread wheat (Triticum aestivum L. subsp. aestivum) and durum wheat (Triticum turgidum subsp. durum) cultivars were tested in nine environments, including three different production conditions (normal, heat and drought) during 2020-21. Genotype stability performance for yield, nutrition and quality parameters is assessed using multienvironment trials through AMMI and GGE Biplot analysis. We discovered intriguing stress dynamics in grain zinc content (Zn) and grain iron content (Fe). Under heat stress, zinc concentration increases but decreases under drought stress, while iron does the opposite. Selecting zinc, starch and kernel weight under terminal heat stress can boost yield. Protein content and yield are inversely related, making it difficult for breeders to optimise both traits. G x E interactions and stability indices across all environments have found genotypes with high-yielding stable genotypes, G12 (MP1358) (42.09 ppm) and G5 (HI1544) (42.41 ppm) have high Fe content. G12 (MP1358) (14.98%) ranked highest in protein concentration. Meanwhile, for Zn content, G11 (MACS 4058) (45.23 ppm) and G15 (WH730) (42.44 ppm) were top performers across environments. G7 (HI 1636) and G12 (MP1358) stand out as a win-win genotype for their high potential and stability in yield, protein, Zn and Fe content. Our study shows the complex relationships and possible suggestions for targeted breeding programmes under heat and drought stress conditions to improve wheat grain quality and micronutrient profiles without yield loss. | N17: drought; grain quality; heat; nutritional security | O17: JOURNAL OF AGRONOMY AND CROP SCIENCE | P17: 210 | Q17: 5 | T17: e12763 | U17: yashavanthak@aripune.org; sudhir.agro123@gmail.com | V17: 10.1111/jac.12763 | W17: https://doi.org/10.1111/jac.12763 | X17: 0 | Y17: paywalled | Z17: 31__Multi-Environment_Analysis_of_Nutritional_and_Grain_Quality_Traits_in_Relation_to_Grain_Yield_Under_Drought_and_Terminal_Heat_Stress_in_Brea.pdf | AA17: https://onlinelibrary.wiley.com/doi/10.1111/jac.12763 | AC17: 403 | AD17: 2026-03-15 11:25:05 | AE17: =IFERROR(IF(ISBLANK(INDEX(wos_screening_view_full_text!$O:$O, MATCH($A17, wos_screening_view_full_text!$B:$B, 0))), "", INDEX(wos_screening_view_full_text!$O:$O, MATCH($A17, wos_screening_view_full_text!$B:$B, 0))), "") | AF17: =IFERROR(IF(ISBLANK(INDEX(wos_screening_view_full_text!$P:$P, MATCH($A17, wos_screening_view_full_text!$B:$B, 0))), "", INDEX(wos_screening_view_full_text!$P:$P, MATCH($A17, wos_screening_view_full_text!$B:$B, 0))), "") | AG17: =IFERROR(IF(ISBLANK(INDEX(wos_screening_view_full_text!$Q:$Q, MATCH($A17, wos_screening_view_full_text!$B:$B, 0))), "", INDEX(wos_screening_view_full_text!$Q:$Q, MATCH($A17, wos_screening_view_full_text!$B:$B, 0))), "")
A18: 33 | B18: WOS_savedrecs_1_r000047 | D18: WoS | E18: 1 | F18: 2026-02-26_005404 | G18: C:\Users\Luís Pinto Coelho\Desktop\Dissertação\StudyScreening_Meta-Analysis\data\web_of_science\raw_data\savedrecs_1.xls | H18: 47 | I18: 2026-02-26 | J18: Juraev, DT; Amanov, OA; Dilmurodov, SD; Meyliev, AX; Boysunov; Buronov, A; Aminova, DX; Turaeva, SM | K18: 2024 | L18: BREAD WHEAT RESPONSE TO HEAT STRESS CONDITIONS FOR PRODUCTIVITY IN THE SOUTHERN REGIONS OF UZBEKISTAN | M18: Climate change and enhanced air temperatures adversely affect the wheat's (Triticum aestivum L.) morphological, physiological, biochemical, and molecular properties and grain yield. Therefore, developing high-yielding and resistant bread wheat cultivars to abiotic factors is vital, along with their primary source under varied environmental conditions. In the presented study, monitoring the influence of high temperatures (30 degrees & Scy; and above) continuously during the grain maturation period, especially in grain filling, on grain quality and productivity has undergone thorough research in the southern parts of Uzbekistan. These Southern regions mainly grow winter bread wheat cultivars. In determining the heat resistance of winter wheat cultivars typically planted in the Republic and selecting the best ones, the experiments and observations materialized with optimum and late-sowing conditions. The study determined the temperature during the growth period and daily temperatures during the grain-filling period. The research was able to evaluate the influence of air temperatures on 1000-grain weight, grain nature, and protein and gluten content and compare the results under optimum and late periods. | N18: Bread wheat (T. aestivum L.); cultivars; climate change; high temperature; heat resistance; growth phases; grain-filling period; grain yield and quality | O18: SABRAO JOURNAL OF BREEDING AND GENETICS | P18: 56 | Q18: 5 | R18: 1834 | S18: 1844 | U18: jurayevdiyor9@gmail.com; di.yor@mail.ru; s.dilmurodov@mail.ru; akmal_8417@mail.ru; nurzod.boysunov@mail.ru; buronova_1985@mail.ru; dildoraminova8@gmail.com; saidaicps@gmail.com | V18: 10.54910/sabrao2024.56.5.8 | W18: https://doi.org/10.54910/sabrao2024.56.5.8 | X18: 1 | Y18: downloaded | Z18: 33__BREAD_WHEAT_RESPONSE_TO_HEAT_STRESS_CONDITIONS_FOR_PRODUCTIVITY_IN_THE_SOUTHERN_REGIONS_OF_UZBEKISTAN.pdf | AA18: https://sabraojournal.org/wp-content/uploads/2024/10/SABRAO-J-Breed-Genet-56-5-1834-1844-MS24-44.pdf | AB18: pdf_files/33__BREAD_WHEAT_RESPONSE_TO_HEAT_STRESS_CONDITIONS_FOR_PRODUCTIVITY_IN_THE_SOUTHERN_REGIONS_OF_UZBEKISTAN.pdf | AC18: 200 | AD18: 2026-03-15 11:25:09 | AE18: =IFERROR(IF(ISBLANK(INDEX(wos_screening_view_full_text!$O:$O, MATCH($A18, wos_screening_view_full_text!$B:$B, 0))), "", INDEX(wos_screening_view_full_text!$O:$O, MATCH($A18, wos_screening_view_full_text!$B:$B, 0))), "") | AF18: =IFERROR(IF(ISBLANK(INDEX(wos_screening_view_full_text!$P:$P, MATCH($A18, wos_screening_view_full_text!$B:$B, 0))), "", INDEX(wos_screening_view_full_text!$P:$P, MATCH($A18, wos_screening_view_full_text!$B:$B, 0))), "") | AG18: =IFERROR(IF(ISBLANK(INDEX(wos_screening_view_full_text!$Q:$Q, MATCH($A18, wos_screening_view_full_text!$B:$B, 0))), "", INDEX(wos_screening_view_full_text!$Q:$Q, MATCH($A18, wos_screening_view_full_text!$B:$B, 0))), "")
A19: 37 | B19: WOS_savedrecs_1_r000051 | D19: WoS | E19: 1 | F19: 2026-02-26_005404 | G19: C:\Users\Luís Pinto Coelho\Desktop\Dissertação\StudyScreening_Meta-Analysis\data\web_of_science\raw_data\savedrecs_1.xls | H19: 51 | I19: 2026-02-26 | J19: Nandini, GA; Chitranshi, A; Gampa, M; Goswami, S; Dalal, M; Kumar, S; Tyagi, A; Kumar, RR | K19: 2024 | L19: Unraveling the effect of drought and heat stresses on grain quality of wheat ( Triticum aestivum ) | M19: Drought stress (DS) and heat stress (HS) have adverse effects on wheat ( Triticum aestivum L.) growth, serving as the primary constraints that significantly limit grain yield. Present study was carried out during 2020-21 and 2021-22 at the research farm of ICAR-Indian Agricultural Research Institute, New Delhi to evaluate the effects of drought and heat stress on grain quality parameters of 4 contrasting wheat genotypes. Several physiological and biochemical parameters were analyzed in wheat cv. C306 (thermotolerant), HD3271 (thermosusceptible), H11500 (drought tolerant) and HD3226 (drought susceptible) under DS and HS. Our study found that disintegration of chlorophyll pigments was higher in wheat cv. HD3226 (43%) under combined stress. Grain weight per spike was reduced by 30% in C306 and 47.3% in HD 3271 under combined drought and heat stress treatment. All cultivars showed reduction in starch, amylose, amylopectin, AGPase and Soluble starch synthase activity under DS and HS. Additionally, a significant increase in total soluble protein and free amino acid content were observed in all genotypes under combined stress. Chlorophyll content and grain weight per spike were positively correlated with the starch, amylose, amylopectin, soluble starch synthase and AGPase activity, while negatively related to the total soluble protein and free amino acid content. The tolerant genotypes maintained higher chlorophyll content, grain weight per spike, starch, amylose, amylopectin, soluble starch synthase and AGPase activity could be used for breeding, for the adaptation to drought and heat under climate change. | N19: Combined stress; Drought stress; Heat stress; Starch; Starch synthase; Wheat | O19: INDIAN JOURNAL OF AGRICULTURAL SCIENCES | P19: 94 | Q19: 5 | R19: 489 | S19: 494 | U19: ranjeetranjaniari@gmail.com | V19: 10.56093/ijas.v94i5.142783 | W19: https://doi.org/10.56093/ijas.v94i5.142783 | X19: 1 | Y19: downloaded | Z19: 37__Unraveling_the_effect_of_drought_and_heat_stresses_on_grain_quality_of_wheat_(_Triticum_aestivum_).pdf | AA19: http://epubs.icar.org.in/index.php/IJAgS/article/download/142783/54524 | AB19: pdf_files/37__Unraveling_the_effect_of_drought_and_heat_stresses_on_grain_quality_of_wheat_(_Triticum_aestivum_).pdf | AC19: 200 | AD19: 2026-03-15 11:25:17 | AE19: =IFERROR(IF(ISBLANK(INDEX(wos_screening_view_full_text!$O:$O, MATCH($A19, wos_screening_view_full_text!$B:$B, 0))), "", INDEX(wos_screening_view_full_text!$O:$O, MATCH($A19, wos_screening_view_full_text!$B:$B, 0))), "") | AF19: =IFERROR(IF(ISBLANK(INDEX(wos_screening_view_full_text!$P:$P, MATCH($A19, wos_screening_view_full_text!$B:$B, 0))), "", INDEX(wos_screening_view_full_text!$P:$P, MATCH($A19, wos_screening_view_full_text!$B:$B, 0))), "") | AG19: =IFERROR(IF(ISBLANK(INDEX(wos_screening_view_full_text!$Q:$Q, MATCH($A19, wos_screening_view_full_text!$B:$B, 0))), "", INDEX(wos_screening_view_full_text!$Q:$Q, MATCH($A19, wos_screening_view_full_text!$B:$B, 0))), "")
A20: 43 | B20: WOS_savedrecs_1_r000058 | D20: WoS | E20: 1 | F20: 2026-02-26_005404 | G20: C:\Users\Luís Pinto Coelho\Desktop\Dissertação\StudyScreening_Meta-Analysis\data\web_of_science\raw_data\savedrecs_1.xls | H20: 58 | I20: 2026-02-26 | J20: Lekhana, MV; Meena, RK; Anirudh, TV; Barman, M; Kumar, A; Reddy, MSS; Sharma, AK; Bahuguna, RN; Singh, SK | K20: 2025 | L20: Effect of terminal heat stress on stay-green and senescence process could explain genetic variation in grain yield and nutritional profile in wheat (Triticum aestivum L.) | M20: Wheat is a staple food crop for the majority of the world's population. Heat stress affects reproductive development, seed-set and seed weight, eventually reducing yield and total biomass in wheat. Stay-green contributes to seed weight by allowing more assimilate partitioning to grain. Conversely, senescence is essential for the recycling of nutrients to developing grain. We have studied a set of 26 high-yielding wheat genotypes to study the effect of terminal heat stress on the stay-green and senescence process to explain genetic variation and trade-off associated between grain yield and grain nutrients under field conditions. Our results revealed that heat stress accelerated the senescence process and significantly reduced average grain filling duration by 8 days. The negative effect of heat stress on spikelet fertility and seed weight resulted in reduced grain yield (25%). On the contrary, a positive influence of heat was observed on grain protein (6-21%), grain minerals, and reduced C:N ratio. Interestingly, genotype (HTWYT42) with a longer stay-green period, showed higher yield under heat stress, whereas genotype (HTWYT43) showed early onset but a slower pace of senescence accumulating more grain protein, minerals and lower C:N ratio under heat stress. This study demonstrates a strong trade-off between grain yield and nutrition. However, maintaining an optimum balance between stay-green and a slower rate of senescence could be crucial to minimizing this trade-off, and achieving both higher yield and improve grain nutrition. Furthermore, understanding the mechanisms underlying slower senescence in source tissues could be essential for developing wheat genotypes with enhanced grain nutrient content. | N20: Heat stress; Grain yield; Grain quality; Senescence; Stay-green; Wheat | O20: PLANT GROWTH REGULATION | U20: r.bahuguna15@gmail.com; satish.singh@rpcau.ac.in | V20: 10.1007/s10725-025-01345-z | W20: https://doi.org/10.1007/s10725-025-01345-z | X20: 1 | Y20: downloaded | Z20: 43__Effect_of_terminal_heat_stress_on_stay-green_and_senescence_process_could_explain_genetic_variation_in_grain_yield_and_nutritional_profile_i.pdf | AA20: https://link.springer.com/content/pdf/10.1007/s10725-025-01345-z.pdf | AB20: pdf_files/43__Effect_of_terminal_heat_stress_on_stay-green_and_senescence_process_could_explain_genetic_variation_in_grain_yield_and_nutritional_profile_i.pdf | AC20: 200 | AD20: 2026-03-15 11:25:21 | AE20: =IFERROR(IF(ISBLANK(INDEX(wos_screening_view_full_text!$O:$O, MATCH($A20, wos_screening_view_full_text!$B:$B, 0))), "", INDEX(wos_screening_view_full_text!$O:$O, MATCH($A20, wos_screening_view_full_text!$B:$B, 0))), "") | AF20: =IFERROR(IF(ISBLANK(INDEX(wos_screening_view_full_text!$P:$P, MATCH($A20, wos_screening_view_full_text!$B:$B, 0))), "", INDEX(wos_screening_view_full_text!$P:$P, MATCH($A20, wos_screening_view_full_text!$B:$B, 0))), "") | AG20: =IFERROR(IF(ISBLANK(INDEX(wos_screening_view_full_text!$Q:$Q, MATCH($A20, wos_screening_view_full_text!$B:$B, 0))), "", INDEX(wos_screening_view_full_text!$Q:$Q, MATCH($A20, wos_screening_view_full_text!$B:$B, 0))), "")
A21: 44 | B21: WOS_savedrecs_1_r000059 | D21: WoS | E21: 1 | F21: 2026-02-26_005404 | G21: C:\Users\Luís Pinto Coelho\Desktop\Dissertação\StudyScreening_Meta-Analysis\data\web_of_science\raw_data\savedrecs_1.xls | H21: 59 | I21: 2026-02-26 | J21: Bergkamp, B; Impa, SM; Asebedo, AR; Fritz, AK; Jagadish, SVK | K21: 2018 | L21: Prominent winter wheat varieties response to post-flowering heat stress under controlled chambers and field based heat tents | M21: Post-flowering heat stress shortens grain filling duration and limits resource allocation to grains leading to lower productivity in wheat. Wheat grown in Kansas and US Great Plains, often experiences temperatures of 30 degrees C during grain filling, leading to lower productivity. Thus, characterizing Kansas prominent and newly released varieties for post-flowering heat stress will define the gap in heat tolerance that will need to be addressed through breeding. In the present study, seven Kansas varieties were phenotyped for heat tolerance under a controlled chamber study and two field experiments. To impose heat stress in the controlled chambers, plants grown at 25 degrees C were transferred to high day temperature (35 degrees C) chambers, 10 days after first sign of anthesis. Under field conditions, custom built heat tents were placed over the plots ten days after 50% flowering and remained until maturity. Plants grown under heat stress exhibited early senescence indicating a shorter grain filling period compared to control. Early maturing varieties recorded higher percent reduction in grain yield under heat stress. Post-flowering heat stress induced significant reduction in thousand kernel weight, grain number, harvest index and grain yield over control. Percent reduction in yield ranged from 6 to 51% under severe heat stress exposure in controlled environments and 2-27% with heat stress exposure using field based tents. Among the varieties tested SY Monument and Larry performed well under both conditions suggesting that they are relatively better suited for locations that face consistent heat stress exposure during the post-flowering stage. Our findings highlight the need to explore wider genetic diversity including wild wheat to infuse greater heat stress resilience into ongoing wheat breeding programs. | N21: Grain filling; Grain yield; Heat stress; Spike temperature; Winter wheat | O21: FIELD CROPS RESEARCH | P21: 222 | R21: 143 | S21: 152 | U21: kjagadish@ksu.edu | V21: 10.1016/j.fcr.2018.03.009 | W21: https://doi.org/10.1016/j.fcr.2018.03.009 | X21: 0 | Y21: manual_check | Z21: 44__Prominent_winter_wheat_varieties_response_to_post-flowering_heat_stress_under_controlled_chambers_and_field_based_heat_tents.pdf | AA21: https://linkinghub.elsevier.com/retrieve/pii/S0378429017315630 | AC21: 200 | AD21: 2026-03-15 11:25:22 | AE21: =IFERROR(IF(ISBLANK(INDEX(wos_screening_view_full_text!$O:$O, MATCH($A21, wos_screening_view_full_text!$B:$B, 0))), "", INDEX(wos_screening_view_full_text!$O:$O, MATCH($A21, wos_screening_view_full_text!$B:$B, 0))), "") | AF21: =IFERROR(IF(ISBLANK(INDEX(wos_screening_view_full_text!$P:$P, MATCH($A21, wos_screening_view_full_text!$B:$B, 0))), "", INDEX(wos_screening_view_full_text!$P:$P, MATCH($A21, wos_screening_view_full_text!$B:$B, 0))), "") | AG21: =IFERROR(IF(ISBLANK(INDEX(wos_screening_view_full_text!$Q:$Q, MATCH($A21, wos_screening_view_full_text!$B:$B, 0))), "", INDEX(wos_screening_view_full_text!$Q:$Q, MATCH($A21, wos_screening_view_full_text!$B:$B, 0))), "")
A22: 46 | B22: WOS_savedrecs_1_r000061 | D22: WoS | E22: 1 | F22: 2026-02-26_005404 | G22: C:\Users\Luís Pinto Coelho\Desktop\Dissertação\StudyScreening_Meta-Analysis\data\web_of_science\raw_data\savedrecs_1.xls | H22: 61 | I22: 2026-02-26 | J22: Tanaka, H; Gorafi, YSA; Fujita, M; Sasaki, H; Tahir, ISA; Tsujimoto, H | K22: 2021 | L22: Expression of seed storage proteins responsible for maintaining kernel traits and wheat flour quality in common wheat under heat stress conditions | M22: Heat stress during grain filling has been documented to decrease wheat grain yield and quality in arid regions worldwide. We studied the effect of heat stress on wheat flour quality in heat tolerant cultivars to define the effects of heat stress on flour quality and to identify germplasm combining traits for heat tolerance and good flour quality. We studied the kernel phenotypic traits, the expression of seed storage proteins (SSPs), and the resulting flour quality under heat and normal conditions. Under heat stress, all cultivars yielded narrowshaped seeds, and increased protein contents as compared to the control plants grown under normal conditions. The specific sedimentation values used to estimate the gluten quality varied between cultivars. We identified cultivars that could maintain good flour quality under heat stress conditions: 'Imam', which possessed the Glu-D1d allele responsible for the suitable bread-making; 'Bohaine', which displayed high expression level of SSPs; and 'Condor', which possessed slight variations in the ratio of each SSP under heat stress conditions. Combining the desirable traits from these cultivars could yield a wheat cultivar with heat tolerance and good flour quality. | N22: Triticum aestivum L.; heat stress; kernel traits; wheat flour quality; seed storage protein | O22: BREEDING SCIENCE | P22: 71 | Q22: 2 | R22: 184 | S22: 192 | U22: htanaka@tottori-u.ac.jp | V22: 10.1270/jsbbs.20080 | W22: https://doi.org/10.1270/jsbbs.20080 | X22: 1 | Y22: downloaded | Z22: 46__Expression_of_seed_storage_proteins_responsible_for_maintaining_kernel_traits_and_wheat_flour_quality_in_common_wheat_under_heat_stress_cond.pdf | AA22: https://www.jstage.jst.go.jp/article/jsbbs/71/2/71_20080/_pdf | AB22: pdf_files/46__Expression_of_seed_storage_proteins_responsible_for_maintaining_kernel_traits_and_wheat_flour_quality_in_common_wheat_under_heat_stress_cond.pdf | AC22: 200 | AD22: 2026-03-15 11:25:37 | AE22: =IFERROR(IF(ISBLANK(INDEX(wos_screening_view_full_text!$O:$O, MATCH($A22, wos_screening_view_full_text!$B:$B, 0))), "", INDEX(wos_screening_view_full_text!$O:$O, MATCH($A22, wos_screening_view_full_text!$B:$B, 0))), "") | AF22: =IFERROR(IF(ISBLANK(INDEX(wos_screening_view_full_text!$P:$P, MATCH($A22, wos_screening_view_full_text!$B:$B, 0))), "", INDEX(wos_screening_view_full_text!$P:$P, MATCH($A22, wos_screening_view_full_text!$B:$B, 0))), "") | AG22: =IFERROR(IF(ISBLANK(INDEX(wos_screening_view_full_text!$Q:$Q, MATCH($A22, wos_screening_view_full_text!$B:$B, 0))), "", INDEX(wos_screening_view_full_text!$Q:$Q, MATCH($A22, wos_screening_view_full_text!$B:$B, 0))), "")
A23: 47 | B23: WOS_savedrecs_1_r000062 | D23: WoS | E23: 1 | F23: 2026-02-26_005404 | G23: C:\Users\Luís Pinto Coelho\Desktop\Dissertação\StudyScreening_Meta-Analysis\data\web_of_science\raw_data\savedrecs_1.xls | H23: 62 | I23: 2026-02-26 | J23: Molero, G; Reynolds, MP | K23: 2020 | L23: Spike photosynthesis measured at high throughput indicates genetic variation independent of flag leaf photosynthesis | M23: Future increases in yield potential will rely largely on improved photosynthesis. Whereas emphasis has traditionally been given to measuring leaf photosynthesis, wheat spikes have an important role in filling grains since they can intercept up to a third of incident light. In the present study, 196 genetically diverse spring wheat lines were evaluated for spike photosynthesis (SP) under temperate (yield potential) and heat stressed, irrigated conditions. Two different methods to estimate SP were used: (i) gas exchange measurements of SP rate and (ii) integrative measurements using a SP inhibition treatment (consisting of a permeable textile covering the spikes). Rate of SP was measured directly in 45 selected genotypes under yield potential conditions using a custom-made illuminating chamber. In these lines, a variation of 2.8-fold for spike photosynthetic rate is reported for the first time with good heritability estimates. Correlations between SP rate and yield, thousand grain weight, number of grains per spike and radiation use efficiency are reported across different panels. Genotypic variation in SP was independent from flag leaf photosynthesis suggesting that any strategy aiming to increase canopy photosynthesis should also consider SP. The SP inhibition treatments were applied on the 196 lines in both environments to estimate SP contribution to grain weight per spike, which was 30-40 % under both heat stressed and yield potential conditions averaged across lines. Positive correlations with grain yield were observed for spike photosynthesis contribution across all of the panels under heat stress and when combining heat and yield potential environments (P < 0.001, r = 0.401). These results indicate a highly significant genotypic variation of spike photosynthetic rate and spike photosynthesis contribution to grain yield among wheat lines and highlight its importance under irrigated and heat stressed conditions. | N23: Genetic variation; Heat; Phenotyping; Spike photosynthesis; Wheat; Breeding | O23: FIELD CROPS RESEARCH | P23: 255 | T23: 107866 | U23: g.molero@cgiar.org; m.reynolds@cgiar.org | V23: 10.1016/j.fcr.2020.107866 | W23: https://doi.org/10.1016/j.fcr.2020.107866 | X23: 0 | Y23: manual_check | Z23: 47__Spike_photosynthesis_measured_at_high_throughput_indicates_genetic_variation_independent_of_flag_leaf_photosynthesis.pdf | AA23: https://linkinghub.elsevier.com/retrieve/pii/S0378429019313632 | AC23: 200 | AD23: 2026-03-15 11:25:39 | AE23: =IFERROR(IF(ISBLANK(INDEX(wos_screening_view_full_text!$O:$O, MATCH($A23, wos_screening_view_full_text!$B:$B, 0))), "", INDEX(wos_screening_view_full_text!$O:$O, MATCH($A23, wos_screening_view_full_text!$B:$B, 0))), "") | AF23: =IFERROR(IF(ISBLANK(INDEX(wos_screening_view_full_text!$P:$P, MATCH($A23, wos_screening_view_full_text!$B:$B, 0))), "", INDEX(wos_screening_view_full_text!$P:$P, MATCH($A23, wos_screening_view_full_text!$B:$B, 0))), "") | AG23: =IFERROR(IF(ISBLANK(INDEX(wos_screening_view_full_text!$Q:$Q, MATCH($A23, wos_screening_view_full_text!$B:$B, 0))), "", INDEX(wos_screening_view_full_text!$Q:$Q, MATCH($A23, wos_screening_view_full_text!$B:$B, 0))), "")
A24: 48 | B24: WOS_savedrecs_1_r000063 | D24: WoS | E24: 1 | F24: 2026-02-26_005404 | G24: C:\Users\Luís Pinto Coelho\Desktop\Dissertação\StudyScreening_Meta-Analysis\data\web_of_science\raw_data\savedrecs_1.xls | H24: 63 | I24: 2026-02-26 | J24: Kaur, V; Behl, RK | K24: 2010 | L24: Grain Yield in Wheat as Affected by Short Periods of High Temperature, Drought and their Interaction during Pre- and Post-anthesis Stages | M24: Drought and high temperature are especially considered as key stress factors with high potential impact on crop yield. The aim of this study was to investigate the effect of short periods of high temperature, drought and their combination at different growth stages of plant under controlled conditions. The effects of high temperature and drought on grain yield were additive. However, high temperature increased the degree of water stress and the combined effects of drought and high temperature were much more severe than those of each individual treatment. High temperature and drought applied at post-anthesis shortened duration of maturation, grain filling duration and reduced grain yield, mean grain weight, grain number and thousand-grain weight. | N24: wheat; grain weight; grain number; high temperature; drought; grain yield; test weight | O24: CEREAL RESEARCH COMMUNICATIONS | P24: 38 | Q24: 4 | R24: 514 | S24: 520 | U24: drvikender@yahoo.in | V24: 10.1556/crc.38.2010.4.8 | W24: https://doi.org/10.1556/crc.38.2010.4.8 | X24: 0 | Y24: manual_check | Z24: 48__Grain_Yield_in_Wheat_as_Affected_by_Short_Periods_of_High_Temperature,_Drought_and_their_Interaction_during_Pre-_and_Post-anthesis_Stages.pdf | AA24: https://akjournals.com/doi/abs/10.1556/CRC.38.2010.4.8 | AC24: 202 | AD24: 2026-03-15 11:25:41 | AE24: =IFERROR(IF(ISBLANK(INDEX(wos_screening_view_full_text!$O:$O, MATCH($A24, wos_screening_view_full_text!$B:$B, 0))), "", INDEX(wos_screening_view_full_text!$O:$O, MATCH($A24, wos_screening_view_full_text!$B:$B, 0))), "") | AF24: =IFERROR(IF(ISBLANK(INDEX(wos_screening_view_full_text!$P:$P, MATCH($A24, wos_screening_view_full_text!$B:$B, 0))), "", INDEX(wos_screening_view_full_text!$P:$P, MATCH($A24, wos_screening_view_full_text!$B:$B, 0))), "") | AG24: =IFERROR(IF(ISBLANK(INDEX(wos_screening_view_full_text!$Q:$Q, MATCH($A24, wos_screening_view_full_text!$B:$B, 0))), "", INDEX(wos_screening_view_full_text!$Q:$Q, MATCH($A24, wos_screening_view_full_text!$B:$B, 0))), "")
A25: 49 | B25: WOS_savedrecs_1_r000065 | D25: WoS | E25: 1 | F25: 2026-02-26_005404 | G25: C:\Users\Luís Pinto Coelho\Desktop\Dissertação\StudyScreening_Meta-Analysis\data\web_of_science\raw_data\savedrecs_1.xls | H25: 65 | I25: 2026-02-26 | J25: Soba, D; González-Torralba, J; Ancín, M; Menéndez, S; Aranjuelo, I | K25: 2024 | L25: Changes in end-use quality parameters of two bread wheat cultivars under water stress and heatwave conditions | M25: The baking industry requires a high level of uniformity in flour quality to meet its demands. Cereal production and nutritional traits are tightly conditioned by genotype and environmental factors. In the current study, the impact of temperature and rainfall on yield and end-use quality of two bread wheat (Triticum aestivum L.) cultivars (Camargo and Marcopolo) was analysed under field conditions. To do that a 2-year experiment (2018-2019) was carried out in three contrasting agro-climatic environments in Navarra (northern Spain). The results revealed that year (Y) (linked with temperature and precipitation) was the main factor controlling most crop agronomic performance parameters. Further, genotype (G), G x E, G x Y and the triple interaction had significant effects in the studied grain quality parameters, suggesting a well-differentiated response to different environments between both cultivars. More specifically, Marcopolo was more affected by drought, decreasing grain yield and starch but increasing quality parameters (protein, gluten and N content and dough extensibility (alveograph L) and dough baking strength (alveograph W). On the other hand, only heatwave affected protein and N and gluten content in the Camargo cultivar. Nitrogen content in grain was selected as a potential smallscale rapid parameter to predict quality traits due to its high correlation with protein and gluten content and alveograph W with correlations higher than r = 0.85. Finally, the C isotopic discrimination (Delta 13C) and N isotope composition (delta 15N) determinations showed that while Delta 13C was the best trait predicting grain yield, delta 15N was significantly correlated with some important end-use quality parameters. In summary, the current study underscores the fact that alongside a direct impact on crop yield, heat and water stress are target factors conditioning wheat grain quality traits. | N25: Bread wheat; Drought stress; Heat stress; End-use quality; Dough rheological properties | O25: EUROPEAN JOURNAL OF AGRONOMY | P25: 161 | T25: 127385 | U25: iker.aranjuelo@csic.es | V25: 10.1016/j.eja.2024.127385 | W25: https://doi.org/10.1016/j.eja.2024.127385 | X25: 0 | Y25: manual_check | Z25: 49__Changes_in_end-use_quality_parameters_of_two_bread_wheat_cultivars_under_water_stress_and_heatwave_conditions.pdf | AA25: https://linkinghub.elsevier.com/retrieve/pii/S116103012400306X | AC25: 200 | AD25: 2026-03-15 11:25:42 | AE25: =IFERROR(IF(ISBLANK(INDEX(wos_screening_view_full_text!$O:$O, MATCH($A25, wos_screening_view_full_text!$B:$B, 0))), "", INDEX(wos_screening_view_full_text!$O:$O, MATCH($A25, wos_screening_view_full_text!$B:$B, 0))), "") | AF25: =IFERROR(IF(ISBLANK(INDEX(wos_screening_view_full_text!$P:$P, MATCH($A25, wos_screening_view_full_text!$B:$B, 0))), "", INDEX(wos_screening_view_full_text!$P:$P, MATCH($A25, wos_screening_view_full_text!$B:$B, 0))), "") | AG25: =IFERROR(IF(ISBLANK(INDEX(wos_screening_view_full_text!$Q:$Q, MATCH($A25, wos_screening_view_full_text!$B:$B, 0))), "", INDEX(wos_screening_view_full_text!$Q:$Q, MATCH($A25, wos_screening_view_full_text!$B:$B, 0))), "")
A26: 50 | B26: WOS_savedrecs_1_r000066 | D26: WoS | E26: 1 | F26: 2026-02-26_005404 | G26: C:\Users\Luís Pinto Coelho\Desktop\Dissertação\StudyScreening_Meta-Analysis\data\web_of_science\raw_data\savedrecs_1.xls | H26: 66 | I26: 2026-02-26 | J26: Kumar, R; Azad, CS; Chattopadhyay, T; Bhati, PK; Gangwar, OP; Kumar, S; Prasad, P; Baranwal, D | K26: 2024 | L26: Identification of terminal heat-tolerant and foliar disease-resistant fortified genotypes in wheat (Triticum aestivum L.) | M26: Terminal heat stress and foliar diseases like rusts and spot blotch are the major concerns for sustainable wheat production in South Asia. Eastern Indo-Gangetic plains witness the crucial role of heat stress during grain-filling duration (GFD) and occurrence of rust diseases and spot blotch in wheat. One hundred promising wheat genotypes were selected from five international wheat yield trials and evaluated at three sites in India for yield components and disease resistance. To identify potential donors, these lines were further screened under timely sown (normal sown) and late sown (heat stress) conditions. Analysis of variation in the studied traits revealed significant differences among all the genotypes in both environments. Grain yield showed a positive and significant correlation with NDVI, chlorophyll index, flag leaf length, flag leaf area, tiller per plant, number of grains per spike, peduncle length and 1000 grain weight (TGW) in both environments. Grain zinc and iron content was substantially increased under late sown condition. As per heat susceptibility index of GFD, TGW, NDVI and grain yield per plot, 10 tested entries were found heat tolerant. Ten promising entries with low disease score were listed as spot blotch donors. Markers linked with seven rust resistance genes, three spot blotch genes and two markers linked with quality-related traits, namely yellow pigment (Psy-A1) and polyphenol oxidase activity (Ppo-1A) and rust pathotypes, were also used to identify the presence of individual genes. Promising entries 46 (CWYT-613; GID 7631433) and 58 (41ESWYT-137; GID 8240588), common for both tested conditions, were identified and promoted under the breeding programme. | N26: Biofortification; Puccinia; Rust; Spot blotch; Donor stock | O26: CEREAL RESEARCH COMMUNICATIONS | P26: 52 | Q26: 4 | R26: 1799 | S26: 1818 | U26: deepak0247@bausabour.ac.in | V26: 10.1007/s42976-024-00505-7 | W26: https://doi.org/10.1007/s42976-024-00505-7 | X26: 1 | Y26: downloaded | Z26: 50__Identification_of_terminal_heat-tolerant_and_foliar_disease-resistant_fortified_genotypes_in_wheat_(Triticum_aestivum_L.).pdf | AA26: https://link.springer.com/content/pdf/10.1007/s42976-024-00505-7.pdf | AB26: pdf_files/50__Identification_of_terminal_heat-tolerant_and_foliar_disease-resistant_fortified_genotypes_in_wheat_(Triticum_aestivum_L.).pdf | AC26: 200 | AD26: 2026-03-15 11:25:45 | AE26: =IFERROR(IF(ISBLANK(INDEX(wos_screening_view_full_text!$O:$O, MATCH($A26, wos_screening_view_full_text!$B:$B, 0))), "", INDEX(wos_screening_view_full_text!$O:$O, MATCH($A26, wos_screening_view_full_text!$B:$B, 0))), "") | AF26: =IFERROR(IF(ISBLANK(INDEX(wos_screening_view_full_text!$P:$P, MATCH($A26, wos_screening_view_full_text!$B:$B, 0))), "", INDEX(wos_screening_view_full_text!$P:$P, MATCH($A26, wos_screening_view_full_text!$B:$B, 0))), "") | AG26: =IFERROR(IF(ISBLANK(INDEX(wos_screening_view_full_text!$Q:$Q, MATCH($A26, wos_screening_view_full_text!$B:$B, 0))), "", INDEX(wos_screening_view_full_text!$Q:$Q, MATCH($A26, wos_screening_view_full_text!$B:$B, 0))), "")
A27: 52 | B27: WOS_savedrecs_1_r000068 | D27: WoS | E27: 1 | F27: 2026-02-26_005404 | G27: C:\Users\Luís Pinto Coelho\Desktop\Dissertação\StudyScreening_Meta-Analysis\data\web_of_science\raw_data\savedrecs_1.xls | H27: 68 | I27: 2026-02-26 | J27: Cabral, C; Ravnskov, S; Tringovska, I; Wollenweber, B | K27: 2016 | L27: Arbuscular mycorrhizal fungi modify nutrient allocation and composition in wheat (Triticum aestivum L.) subjected to heat-stress | M27: To evaluate the role of the AM symbiosis on nutrient allocation in Triticum aestivum L. cv. 1110 at different growth stages before and after heat-stress at anthesis. Measurements of plant biomass and grain yield at anthesis, grain-filling and maturity; determination of macro- and micronutrient concentrations in aboveground biomass; evaluation of AM fungal structures in roots and assessment of light-use efficiency of plants. AM increased grain number in wheat under heat-stress, and altered nutrient allocation and tiller nutrient composition. Heat increased number of arbuscules in wheat root, whereas number of vesicles and total colonization were unaffected. Heat increased photosystem II yield and the electron transfer rate, whereas non-photochemical quenching decreased during the first 2 days of heat-stress. Nutrient allocation and -composition in wheat grown under heat-stress were altered by AM symbiosis, which lowered the K/Ca ratio, whereas it was increased by heat-stress. The increased carbon availability in spikes at this developmental stage, related to the C sink strength of the AM symbiosis and its influence on source-sink relationships in the host-plant, resulted in increased number of grains in heat-stressed AM plants. | N27: Arbuscular mycorrhiza; Grain number; Nutrient allocation; Light-use efficiency | O27: PLANT AND SOIL | P27: 408 | Q27: 1-2 | R27: 385 | S27: 399 | U27: sabine.ravnskov@agro.au.dk | V27: 10.1007/s11104-016-2942-x | W27: https://doi.org/10.1007/s11104-016-2942-x | X27: 1 | Y27: downloaded | Z27: 52__Arbuscular_mycorrhizal_fungi_modify_nutrient_allocation_and_composition_in_wheat_(Triticum_aestivum_L.)_subjected_to_heat-stress.pdf | AA27: https://link.springer.com/content/pdf/10.1007/s11104-016-2942-x.pdf | AB27: pdf_files/52__Arbuscular_mycorrhizal_fungi_modify_nutrient_allocation_and_composition_in_wheat_(Triticum_aestivum_L.)_subjected_to_heat-stress.pdf | AC27: 200 | AD27: 2026-03-15 11:25:47 | AE27: =IFERROR(IF(ISBLANK(INDEX(wos_screening_view_full_text!$O:$O, MATCH($A27, wos_screening_view_full_text!$B:$B, 0))), "", INDEX(wos_screening_view_full_text!$O:$O, MATCH($A27, wos_screening_view_full_text!$B:$B, 0))), "") | AF27: =IFERROR(IF(ISBLANK(INDEX(wos_screening_view_full_text!$P:$P, MATCH($A27, wos_screening_view_full_text!$B:$B, 0))), "", INDEX(wos_screening_view_full_text!$P:$P, MATCH($A27, wos_screening_view_full_text!$B:$B, 0))), "") | AG27: =IFERROR(IF(ISBLANK(INDEX(wos_screening_view_full_text!$Q:$Q, MATCH($A27, wos_screening_view_full_text!$B:$B, 0))), "", INDEX(wos_screening_view_full_text!$Q:$Q, MATCH($A27, wos_screening_view_full_text!$B:$B, 0))), "")
A28: 54 | B28: WOS_savedrecs_1_r000073 | D28: WoS | E28: 1 | F28: 2026-02-26_005404 | G28: C:\Users\Luís Pinto Coelho\Desktop\Dissertação\StudyScreening_Meta-Analysis\data\web_of_science\raw_data\savedrecs_1.xls | H28: 73 | I28: 2026-02-26 | J28: Rivelli, GM; Calderini, DF; Abeledo, LG; Miralles, DJ; Rondanini, DP | K28: 2024 | L28: Yield and quality traits of wheat and rapeseed in response to source-sink ratio and heat stress in post-flowering | M28: The probability of occurrence of high temperatures and cloudiness events increases during the post-flowering period of temperate crops in the southern cone of South America. Several studies have evaluated the effect of high temperature or shading on wheat and rapeseed, but little is known about the impact of the combined effect of both stresses on the yield and grain quality of these crops during the post-flowering phase. This study aims to analyze the sensitivity and stability of wheat and rapeseed grain yield and quality in response to shading, high temperature and the combined stresses during post-flowering in two contrasting environments. Field experiments were carried out using the same wheat and rapeseed genotypes in environments with high (Valdivia, Chile) and medium (Buenos Aires, Argentina) yield potential. The treatments consisted of i) control, ii) shading stress, iii) heat stress and iv) combined shading and heat stress during the central hours of day. Portable chambers were placed on the plots at 7-10 days from anthesis in wheat and 14 days from the beginning of flowering in rapeseed, throughout 10 days. Grain yield was significantly reduced for the combined stress in wheat (-46%) and rapeseed (-39%) in Buenos Aires, but there were no differences between treatments in any crop in Valdivia. Combined stress in rapeseed produced a trade-off between grain number (-40%) and grain thousand weight (+43%) in Valdivia, while grain thousand weight was penalized (-25%) in Buenos Aires. For wheat there were no differences in grain protein in both locations, while for rapeseed protein increased due to the combined stress in Buenos Aires (+15%), no effects were recorded for grain oil in either location. Our results showed a high stability of grain weight in rapeseed to single and combined environmental stresses, with better environmental conditions during grain filling. | N28: Brassica napus L .; Heat shock; Shading; Protein; Oil; Triticum aestivum L. | O28: EUROPEAN JOURNAL OF AGRONOMY | P28: 152 | T28: 127028 | U28: grivelli@agro.uba.ar | V28: 10.1016/j.eja.2023.127028 | W28: https://doi.org/10.1016/j.eja.2023.127028 | X28: 0 | Y28: manual_check | Z28: 54__Yield_and_quality_traits_of_wheat_and_rapeseed_in_response_to_source-sink_ratio_and_heat_stress_in_post-flowering.pdf | AA28: https://linkinghub.elsevier.com/retrieve/pii/S1161030123002964 | AC28: 200 | AD28: 2026-03-15 11:25:49 | AE28: =IFERROR(IF(ISBLANK(INDEX(wos_screening_view_full_text!$O:$O, MATCH($A28, wos_screening_view_full_text!$B:$B, 0))), "", INDEX(wos_screening_view_full_text!$O:$O, MATCH($A28, wos_screening_view_full_text!$B:$B, 0))), "") | AF28: =IFERROR(IF(ISBLANK(INDEX(wos_screening_view_full_text!$P:$P, MATCH($A28, wos_screening_view_full_text!$B:$B, 0))), "", INDEX(wos_screening_view_full_text!$P:$P, MATCH($A28, wos_screening_view_full_text!$B:$B, 0))), "") | AG28: =IFERROR(IF(ISBLANK(INDEX(wos_screening_view_full_text!$Q:$Q, MATCH($A28, wos_screening_view_full_text!$B:$B, 0))), "", INDEX(wos_screening_view_full_text!$Q:$Q, MATCH($A28, wos_screening_view_full_text!$B:$B, 0))), "")
A29: 55 | B29: WOS_savedrecs_1_r000074 | D29: WoS | E29: 1 | F29: 2026-02-26_005404 | G29: C:\Users\Luís Pinto Coelho\Desktop\Dissertação\StudyScreening_Meta-Analysis\data\web_of_science\raw_data\savedrecs_1.xls | H29: 74 | I29: 2026-02-26 | J29: De Melo, DLD; Correa, AAP; Moresco, ER; da Silva, FM; Val, BHP; Di Mauro, AO; Uneda-Trevisoli, SH | K29: 2017 | L29: Heat stress: Impacts on fertility, productivity, and protein content of wheat cultivars | M29: The aim of this study was to analyze the effects of high temperatures on ear fertility, yield components and protein content of wheat cultivars. Therefore, 96 genotypes were subjected to two environments in a greenhouse: control and heat stress. Each environment had two replicates, totalling 192 plots. The evaluations were: number of ear per plant, number of ear per pot, ear weight, number of grains per ear, number of sterile spikelet's, number of viable grains, grain weight and protein content. Principal component analysis (PCA) and genetic and phenotypic correlations were performed. The results showed a significant drop in productivity of the genotypes subjected to heat stress as well as significant increase in the number of sterile spikelet's. The PCA allowed the selection of nine promising genotypes for cultivation in environments with high temperatures with basis on these traits, especially the cultivars CD 104, CD 122 and TBIO Itaipu. | N29: Triticum aestivum; Thermal stress; Breeding; Tolerance; High temperature | O29: GENETICS AND MOLECULAR RESEARCH | P29: 16 | Q29: 4 | T29: 16039847 | U29: aretiss@yahoo.com.br | V29: 10.4238/gmr16039847 | W29: https://doi.org/10.4238/gmr16039847 | X29: 0 | Y29: not_found | Z29: 55__Heat_stress_Impacts_on_fertility,_productivity,_and_protein_content_of_wheat_cultivars.pdf | AA29: https://www.funpecrp.com.br/gmr/articles/year2017/vol16-4/pdf/heat-stress-impacts-on-fertility-productivity-and-protein-content-of-wheat-cultivars.pdf | AC29: 404 | AD29: 2026-03-15 11:25:51 | AE29: =IFERROR(IF(ISBLANK(INDEX(wos_screening_view_full_text!$O:$O, MATCH($A29, wos_screening_view_full_text!$B:$B, 0))), "", INDEX(wos_screening_view_full_text!$O:$O, MATCH($A29, wos_screening_view_full_text!$B:$B, 0))), "") | AF29: =IFERROR(IF(ISBLANK(INDEX(wos_screening_view_full_text!$P:$P, MATCH($A29, wos_screening_view_full_text!$B:$B, 0))), "", INDEX(wos_screening_view_full_text!$P:$P, MATCH($A29, wos_screening_view_full_text!$B:$B, 0))), "") | AG29: =IFERROR(IF(ISBLANK(INDEX(wos_screening_view_full_text!$Q:$Q, MATCH($A29, wos_screening_view_full_text!$B:$B, 0))), "", INDEX(wos_screening_view_full_text!$Q:$Q, MATCH($A29, wos_screening_view_full_text!$B:$B, 0))), "")
A30: 57 | B30: WOS_savedrecs_1_r000079 | D30: WoS | E30: 1 | F30: 2026-02-26_005404 | G30: C:\Users\Luís Pinto Coelho\Desktop\Dissertação\StudyScreening_Meta-Analysis\data\web_of_science\raw_data\savedrecs_1.xls | H30: 79 | I30: 2026-02-26 | J30: Mosavian, SN; Eisvand, HR; Akbari, N; Moshatati, A; Ismaili, A | K30: 2021 | L30: Do nitrogen and zinc application alleviate the adverse effect of heat stress on wheat (Triticum aestivum L.)? | M30: Late-season heat stress (LSH) is a limiting factor for wheat production. Besides, low zinc and poor protein diet usually is a problem in low-income countries. The primary calorie source in such countries is prepared from bread. This study aims to mitigate heat stress by zinc and nitrogen application and improve zinc and protein content in wheat grain. We did the field experiments as a split-split-plot based on a randomized complete block design with four replications to assess zinc and nitrogen's possible mitigation effect on LSH and protein and zinc enrichment of wheat grain during two years. Factors included LSH by delay in planting date (optimum, late, and very late) as the main plot, nitrogen (0, 75, 150, and 225 kg ha(-1)) in subplots, and zinc (0, 10, and 20 kg ha(-1)) as sub-subplots. We measured yield, yield components, physiological traits, zinc, and protein contents in the grain. Results showed that the highest relative water content and cell-membrane thermal stability were attained at the optimum planting date, 150 kg N ha(-1) and 20 kg Zn ha(-1). The maximum chlorophyll a and carotenoids contents in wheat cells were recorded in the optimum planting date, 225 kg N ha-1, and 20 kg Zn ha(-1). Heat stress reduced the grain yield. In the second year of the experiment, the grain number per unit area was more than that of the first year; however, the highest grain yield was achieved in the first year owing to the higher mean grain weight. Nitrogen application decreased the adverse effects of heat stress on grain yield by increasing the grain number. Zinc application diminished the adverse effects of heat stress by increasing the mean grain weight. The adverse impact of the LSH on grain yield was more than that of biological yield. Heat stress reduced the hectolitre weight and zinc content of the grain. Meanwhile, it increased grain protein. In general, under LSH, the application of 225 kg N ha(-1)and 20 kg Zn ha(-1) can reduce the adverse effects of heat on the grain quality and quantity. | N30: biofortification; cell-membrane thermal stability; fertilizers; planting date | O30: NOTULAE BOTANICAE HORTI AGROBOTANICI CLUJ-NAPOCA | P30: 49 | Q30: 2 | T30: 12252 | U30: nader_mosavian@yahoo.com; eisvand.hr@lu.ac.ir; nr1332@hotmail.com; A.moshatati@asnrukh.ac.ir; ismaili.a@lu.ac.ir | V30: 10.15835/nbha49212252 | W30: https://doi.org/10.15835/nbha49212252 | X30: 1 | Y30: downloaded | Z30: 57__Do_nitrogen_and_zinc_application_alleviate_the_adverse_effect_of_heat_stress_on_wheat_(Triticum_aestivum_L.).pdf | AA30: https://www.notulaebotanicae.ro/index.php/nbha/article/download/12252/9175 | AB30: pdf_files/57__Do_nitrogen_and_zinc_application_alleviate_the_adverse_effect_of_heat_stress_on_wheat_(Triticum_aestivum_L.).pdf | AC30: 200 | AD30: 2026-03-15 11:25:55 | AE30: =IFERROR(IF(ISBLANK(INDEX(wos_screening_view_full_text!$O:$O, MATCH($A30, wos_screening_view_full_text!$B:$B, 0))), "", INDEX(wos_screening_view_full_text!$O:$O, MATCH($A30, wos_screening_view_full_text!$B:$B, 0))), "") | AF30: =IFERROR(IF(ISBLANK(INDEX(wos_screening_view_full_text!$P:$P, MATCH($A30, wos_screening_view_full_text!$B:$B, 0))), "", INDEX(wos_screening_view_full_text!$P:$P, MATCH($A30, wos_screening_view_full_text!$B:$B, 0))), "") | AG30: =IFERROR(IF(ISBLANK(INDEX(wos_screening_view_full_text!$Q:$Q, MATCH($A30, wos_screening_view_full_text!$B:$B, 0))), "", INDEX(wos_screening_view_full_text!$Q:$Q, MATCH($A30, wos_screening_view_full_text!$B:$B, 0))), "")
A31: 58 | B31: WOS_savedrecs_1_r000080 | D31: WoS | E31: 1 | F31: 2026-02-26_005404 | G31: C:\Users\Luís Pinto Coelho\Desktop\Dissertação\StudyScreening_Meta-Analysis\data\web_of_science\raw_data\savedrecs_1.xls | H31: 80 | I31: 2026-02-26 | J31: Leithold, B; Muller, G; Weber, WE; Westermann, T | K31: 1997 | L31: Investigations on heat tolerance of spring wheat varieties of different origin under growth chamber conditions | M31: Winter wheat has replaced spring wheat to a large extent under the climatic conditions of Western and Central Europe. But spring wheat genotypes are still important under the warm climate in large parts of Africa and Central America, since spring wheat needs no vernalization. To reach optimal yield, genotypes must be well adapted to heat stress. In this study 11 spring wheat varieties of Egypt, Sudan, CIMMYT and Germany were exposed to high temperatures at ear emergence and beginning of anthesis. There were reductions in kernel yield and kernel number of the main ear for all genotypes, but the differences in reduction were remarkable. The German variety 'Naxos' was best adapted. Some varieties showed an increased number of florets per spikelet under heat treatment, but this does not prohibit a reduction in kernel number per spikelet. | N31: Triticum aestivum; floret number; grain yield; high temperature tolerance; kernel number | O31: JOURNAL OF AGRONOMY AND CROP SCIENCE-ZEITSCHRIFT FUR ACKER UND PFLANZENBAU | P31: 179 | Q31: 2 | R31: 115 | S31: 122 | V31: 10.1111/j.1439-037x.1997.tb00506.x | W31: https://doi.org/10.1111/j.1439-037x.1997.tb00506.x | X31: 0 | Y31: paywalled | Z31: 58__Investigations_on_heat_tolerance_of_spring_wheat_varieties_of_different_origin_under_growth_chamber_conditions.pdf | AA31: https://onlinelibrary.wiley.com/doi/10.1111/j.1439-037X.1997.tb00506.x | AC31: 403 | AD31: 2026-03-15 11:25:56 | AE31: =IFERROR(IF(ISBLANK(INDEX(wos_screening_view_full_text!$O:$O, MATCH($A31, wos_screening_view_full_text!$B:$B, 0))), "", INDEX(wos_screening_view_full_text!$O:$O, MATCH($A31, wos_screening_view_full_text!$B:$B, 0))), "") | AF31: =IFERROR(IF(ISBLANK(INDEX(wos_screening_view_full_text!$P:$P, MATCH($A31, wos_screening_view_full_text!$B:$B, 0))), "", INDEX(wos_screening_view_full_text!$P:$P, MATCH($A31, wos_screening_view_full_text!$B:$B, 0))), "") | AG31: =IFERROR(IF(ISBLANK(INDEX(wos_screening_view_full_text!$Q:$Q, MATCH($A31, wos_screening_view_full_text!$B:$B, 0))), "", INDEX(wos_screening_view_full_text!$Q:$Q, MATCH($A31, wos_screening_view_full_text!$B:$B, 0))), "")
A32: 62 | B32: WOS_savedrecs_1_r000084 | D32: WoS | E32: 1 | F32: 2026-02-26_005404 | G32: C:\Users\Luís Pinto Coelho\Desktop\Dissertação\StudyScreening_Meta-Analysis\data\web_of_science\raw_data\savedrecs_1.xls | H32: 84 | I32: 2026-02-26 | J32: Abeysingha, DN; Ozga, JA; Strydhorst, S; Doyle, P; Iqbal, M; Yang, RC; Reinecke, DM | K32: 2021 | L32: The effect of auxins on amelioration of heat stress-induced wheat (Triticum aestivum L.) grain loss | M32: High temperature stress during the reproductive growth stage of wheat (Triticum aestivum L.) can cause extensive yield losses. As the plant hormone auxin is a key regulator of reproductive development, we studied the effect of auxins on grain yield in five wheat lines exposed to moderate heat stress (34-35 degrees C) for 6 h per day for 6 days during early flowering (booting stage to anthesis). 'CDC Go', a semi-dwarf (Rht-B1b) cultivar, responded to auxin application (1 mu M) by producing higher grain number and yield under control and heat stress conditions. The effect of five different auxins on grain yield in 'CDC Go' was dependent on spike developmental stage at application and position within the spike, with 4-Cl-IAA at 1 mu M being the most effective auxin treatment. The presence of Rht dwarfing mutant alleles of Rht-B1 and Rht-D1 alone did not increase auxin-induced grain yield when tested in lines isogenic for these alleles. In the field, 4-Cl-IAA (1 mu M) increased grain yield by 6%-8% only in 'CDC Go', one of six hard red spring wheat cultivars tested over two growing seasons in the western Canadian prairies. When 4-Cl-IAA application increased grain yield and number, the grain protein content was not affected; when it maintained grain yield in plants with lower biomass, grain protein content was reduced. Our field results suggested that both genotype and environment affect auxin-induced enhancement of wheat grain yield. We recommend testing target environments with heat stress as a focus of a breeding programme along with further testing of auxin as a crop enhancement tool. | N32: 4-Cl-IAA; abiotic stress; grain yield; high temperature stress; reproductive growth | O32: JOURNAL OF AGRONOMY AND CROP SCIENCE | P32: 207 | Q32: 6 | R32: 970 | S32: 983 | U32: jocelyn.ozga@ualberta.ca | V32: 10.1111/jac.12555 | W32: https://doi.org/10.1111/jac.12555 | X32: 0 | Y32: paywalled | Z32: 62__The_effect_of_auxins_on_amelioration_of_heat_stress-induced_wheat_(Triticum_aestivum_L.)_grain_loss.pdf | AA32: https://onlinelibrary.wiley.com/doi/10.1111/jac.12555 | AC32: 403 | AD32: 2026-03-15 11:25:58 | AE32: =IFERROR(IF(ISBLANK(INDEX(wos_screening_view_full_text!$O:$O, MATCH($A32, wos_screening_view_full_text!$B:$B, 0))), "", INDEX(wos_screening_view_full_text!$O:$O, MATCH($A32, wos_screening_view_full_text!$B:$B, 0))), "") | AF32: =IFERROR(IF(ISBLANK(INDEX(wos_screening_view_full_text!$P:$P, MATCH($A32, wos_screening_view_full_text!$B:$B, 0))), "", INDEX(wos_screening_view_full_text!$P:$P, MATCH($A32, wos_screening_view_full_text!$B:$B, 0))), "") | AG32: =IFERROR(IF(ISBLANK(INDEX(wos_screening_view_full_text!$Q:$Q, MATCH($A32, wos_screening_view_full_text!$B:$B, 0))), "", INDEX(wos_screening_view_full_text!$Q:$Q, MATCH($A32, wos_screening_view_full_text!$B:$B, 0))), "")
A33: 64 | B33: WOS_savedrecs_1_r000087 | D33: WoS | E33: 1 | F33: 2026-02-26_005404 | G33: C:\Users\Luís Pinto Coelho\Desktop\Dissertação\StudyScreening_Meta-Analysis\data\web_of_science\raw_data\savedrecs_1.xls | H33: 87 | I33: 2026-02-26 | J33: Alghabari, F; Ihsan, MZ; Khaliq, A; Hussain, S; Daur, I; Fahad, S; Nasim, W | K33: 2016 | L33: Gibberellin-sensitive Rht alleles confer tolerance to heat and drought stresses in wheat at booting stage | M33: The present study compared six near-isogenic lines from different backgrounds, varying in Rht (reduced height) alleles for gibberellin (GA) response, for heat and drought tolerance. Various temperature (day/night: 20/12 degrees C to 39/31 degrees C), and irrigation (100% field capacity and no irrigation) treatments were imposed at booting stage. Results depicted a 50% reduction in grain yield at 36.7 degrees C with irrigation and at 31.2 degrees C without irrigation. Number of grains per spike was severely reduced over 26 degrees C for water-stressed plants while irrigated plants did not show any significant reduction up to 34 degrees C. Ear numbers per pot and spikelets per spike were unaffected by irrigation till 33 degrees C. In Mercia, grain nitrogen, sulphur, and Hagberg falling number (HFN) were significantly higher for severe dwarfs (Rht-D1c and Rht-12), however, in Maris Widgeon, rht (tall) recorded higher nitrogen and sulphur concentration while Rht-B1b presented the maximum sedimentation of sodium dodecyl sulphate (SDS). The SDS was higher in Maris Widgeon while HFN were superior in Mercia. Conclusively, the present study demonstrated that heat and drought stresses severely reduced the grain yield while improved grain quality traits. The GA-insensitive semi dwarf Rht-B1b was the most promising genotype for grain yield and HFN under combined drought and heat stresses. (C) 2016 Elsevier Ltd. All rights reserved. | N33: Drought; Gibberellin; Grain yield and quality; Heat stress | O33: JOURNAL OF CEREAL SCIENCE | P33: 70 | R33: 72 | S33: 78 | U33: falghabari@gmail.com; shussain@webmail.hzau.edu.cn | V33: 10.1016/j.jcs.2016.05.016 | W33: https://doi.org/10.1016/j.jcs.2016.05.016 | X33: 0 | Y33: manual_check | Z33: 64__Gibberellin-sensitive_Rht_alleles_confer_tolerance_to_heat_and_drought_stresses_in_wheat_at_booting_stage.pdf | AA33: https://linkinghub.elsevier.com/retrieve/pii/S0733521016300789 | AC33: 200 | AD33: 2026-03-15 11:25:59 | AE33: =IFERROR(IF(ISBLANK(INDEX(wos_screening_view_full_text!$O:$O, MATCH($A33, wos_screening_view_full_text!$B:$B, 0))), "", INDEX(wos_screening_view_full_text!$O:$O, MATCH($A33, wos_screening_view_full_text!$B:$B, 0))), "") | AF33: =IFERROR(IF(ISBLANK(INDEX(wos_screening_view_full_text!$P:$P, MATCH($A33, wos_screening_view_full_text!$B:$B, 0))), "", INDEX(wos_screening_view_full_text!$P:$P, MATCH($A33, wos_screening_view_full_text!$B:$B, 0))), "") | AG33: =IFERROR(IF(ISBLANK(INDEX(wos_screening_view_full_text!$Q:$Q, MATCH($A33, wos_screening_view_full_text!$B:$B, 0))), "", INDEX(wos_screening_view_full_text!$Q:$Q, MATCH($A33, wos_screening_view_full_text!$B:$B, 0))), "")
A34: 65 | B34: WOS_savedrecs_1_r000088 | D34: WoS | E34: 1 | F34: 2026-02-26_005404 | G34: C:\Users\Luís Pinto Coelho\Desktop\Dissertação\StudyScreening_Meta-Analysis\data\web_of_science\raw_data\savedrecs_1.xls | H34: 88 | I34: 2026-02-26 | J34: Banowetz, GM; Ammar, K; Chen, DD | K34: 1999 | L34: Postanthesis temperatures influence cytokinin accumulation and wheat kernel weight | M34: High temperatures during reproductive development alter kernel development and reduce yield and quality in wheat (Triticum aestivum L.). Understanding how temperature alters kernel formation will help the development of genetic approaches to enhance heat tolerance in this cereal, A relationship between kernel development and postanthesis cytokinin accumulation is well documented, but the effect of temperature on this relationship is not known. This study quantified the effects of a postanthesis temperature treatment (7 d at 35/25 degrees C day/night) on kernel development and cytokinin accumulation in a soft white winter wheat (c.v. Stephens). Kernels from control plants maintained at 25/15 degrees C accumulated zeatin, dihydrozeatin and their corresponding 9-ribosides from 1 to 4 d postanthesis, Postanthesis kernel cytokinin accumulation was reduced by 50-80% by the temperature treatment. Kernel cytokinin content in control plants declined to baseline by 5 d postanthesis and remained at that level. Kernels from treated plants had a secondary peak of cytokinin accumulation 6-8 d after anthesis, This treatment significantly reduced kernel weight. The magnitude of the effect on kernel number was smaller than on kernel weight, but was statistically significant. Reduced kernel weight was accompanied by reduced cytokinin accumulation. Exogenous cytokinins did not mitigate the temperature effects on kernel weight, but at the highest concentrations, did reduce the effect on kernel number. | N34: Triticum aestivum; endosperm; zeatin; zeatin riboside | O34: PLANT CELL AND ENVIRONMENT | P34: 22 | Q34: 3 | R34: 309 | S34: 316 | V34: 10.1046/j.1365-3040.1999.00411.x | W34: https://doi.org/10.1046/j.1365-3040.1999.00411.x | X34: 0 | Y34: paywalled | Z34: 65__Postanthesis_temperatures_influence_cytokinin_accumulation_and_wheat_kernel_weight.pdf | AA34: https://onlinelibrary.wiley.com/doi/10.1046/j.1365-3040.1999.00411.x | AC34: 403 | AD34: 2026-03-15 11:26:01 | AE34: =IFERROR(IF(ISBLANK(INDEX(wos_screening_view_full_text!$O:$O, MATCH($A34, wos_screening_view_full_text!$B:$B, 0))), "", INDEX(wos_screening_view_full_text!$O:$O, MATCH($A34, wos_screening_view_full_text!$B:$B, 0))), "") | AF34: =IFERROR(IF(ISBLANK(INDEX(wos_screening_view_full_text!$P:$P, MATCH($A34, wos_screening_view_full_text!$B:$B, 0))), "", INDEX(wos_screening_view_full_text!$P:$P, MATCH($A34, wos_screening_view_full_text!$B:$B, 0))), "") | AG34: =IFERROR(IF(ISBLANK(INDEX(wos_screening_view_full_text!$Q:$Q, MATCH($A34, wos_screening_view_full_text!$B:$B, 0))), "", INDEX(wos_screening_view_full_text!$Q:$Q, MATCH($A34, wos_screening_view_full_text!$B:$B, 0))), "")
A35: 66 | B35: WOS_savedrecs_1_r000089 | D35: WoS | E35: 1 | F35: 2026-02-26_005404 | G35: C:\Users\Luís Pinto Coelho\Desktop\Dissertação\StudyScreening_Meta-Analysis\data\web_of_science\raw_data\savedrecs_1.xls | H35: 89 | I35: 2026-02-26 | J35: Hlavácová, M; Klem, K; Smutná, P; Skarpa, P; Hlavinka, P; Novotná, K; Rapantová, B; Trnka, M | K35: 2017 | L35: Effect of heat stress at anthesis on yield formation in winter wheat | M35: Heat stress around anthesis is considered to have an increasing impact on wheat yield under the ongoing climate change. However, the effect of high temperatures and their duration on formation of individual yield parameters is still little understood. Within this study, the effect of high temperatures applied during anthesis for 3 and 7 days on yield formation parameters was analysed. The study was conducted in growth chambers under four temperature regimes (daily temperature maxima 26, 32, 35 and 38 degrees C). In the periods preceding and following heat stress regimes the plants were cultivated under ambient weather conditions. The number of grains per spike was reduced under temperatures >= 35 degrees C in cv. Bohemia and >= 38 degrees C in cv. Tobak. This resulted in a similar response of spike productivity. Thousand grain weight showed no response to temperature regime in cv. Tobak, whereas in cv. Bohemia, a peak response to temperature with maximum at 35 degrees C was observed. The duration of heat stress had only little effect on most yield formation parameters. | N35: high temperature stress; grains number per spike; spike productivity; phytotron; Triticum aestivum L. | O35: PLANT SOIL AND ENVIRONMENT | P35: 63 | Q35: 3 | R35: 139 | S35: 144 | U35: Marci.Hlava.22@gmail.com | V35: 10.17221/73/2017-pse | W35: https://doi.org/10.17221/73/2017-pse | X35: 1 | Y35: downloaded | Z35: 66__Effect_of_heat_stress_at_anthesis_on_yield_formation_in_winter_wheat.pdf | AA35: http://pse.agriculturejournals.cz/pdfs/pse/2017/03/07.pdf | AB35: pdf_files/66__Effect_of_heat_stress_at_anthesis_on_yield_formation_in_winter_wheat.pdf | AC35: 200 | AD35: 2026-03-15 11:26:04 | AE35: =IFERROR(IF(ISBLANK(INDEX(wos_screening_view_full_text!$O:$O, MATCH($A35, wos_screening_view_full_text!$B:$B, 0))), "", INDEX(wos_screening_view_full_text!$O:$O, MATCH($A35, wos_screening_view_full_text!$B:$B, 0))), "") | AF35: =IFERROR(IF(ISBLANK(INDEX(wos_screening_view_full_text!$P:$P, MATCH($A35, wos_screening_view_full_text!$B:$B, 0))), "", INDEX(wos_screening_view_full_text!$P:$P, MATCH($A35, wos_screening_view_full_text!$B:$B, 0))), "") | AG35: =IFERROR(IF(ISBLANK(INDEX(wos_screening_view_full_text!$Q:$Q, MATCH($A35, wos_screening_view_full_text!$B:$B, 0))), "", INDEX(wos_screening_view_full_text!$Q:$Q, MATCH($A35, wos_screening_view_full_text!$B:$B, 0))), "")
A36: 68 | B36: WOS_savedrecs_1_r000092 | D36: WoS | E36: 1 | F36: 2026-02-26_005404 | G36: C:\Users\Luís Pinto Coelho\Desktop\Dissertação\StudyScreening_Meta-Analysis\data\web_of_science\raw_data\savedrecs_1.xls | H36: 92 | I36: 2026-02-26 | J36: Farooq, M; Rizwan, M; Nawaz, A; Rehman, A; Ahmad, R | K36: 2017 | L36: Application of natural plant extracts improves the tolerance against combined terminal heat and drought stresses in bread wheat | M36: Drought and heat are among the main abiotic stresses causing severe damage to the cereal productivity when occur at reproductive stages. In this study, ten wheat cultivars were screened for combined heat and drought tolerance imposed at booting, heading, anthesis and post-anthesis stages, and role of the foliage applied plant extracts was evaluated in improving the performance of differentially responding wheat cultivars under terminal heat and drought stresses. During both years, wheat crop was raised under ambient temperature and 70% water holding capacity (WHC) till leaf boot stage. The plant extracts (3% each) of sorghum, brassica, sunflower and moringa were foliage applied at booting, anthesis and post-anthesis stage; and after one week of application of these plant extracts, combined heat and drought was imposed at each respective stage. Heat and drought stresses were imposed at each respective stage by placing pots in glass canopies with temperature of 4 +/- 2 degrees C above than the ambient temperature in combination with drought stress (35% WHC) until maturity. Combination of drought and heat stresses significantly reduced the performance of tested wheat cultivars; however, stress at the booting and heading stages was more damaging than the anthesis and post-anthesis stages. Cultivars Mairaj-2008 and Chakwal-50 remained green with extended duration for grain filling, resulting in the maintenance of number of grains per spike and 100-grain weight under stress conditions and thus had better grain yield and water-use efficiency. However, in cultivars Fsd-2008, and Shafaq-2006, the combined imposition of drought and heat accelerated the grain filling rate with decrease in grain filling duration, grain weight and grain yield. Foliar application of all the plant extracts improved the wheat performance under terminal heat and drought stress; however, brassica extract was the most effective. This improvement in grain yield, water-use efficiency and transpiration efficiency due to foliage applied plant extracts, under terminal heat and drought stress, was owing to better stay-green character and accumulation of more soluble phenolics, which imparted stress tolerance as indicated by relatively stable grain weight and grain number. In crux, growing of stay-green wheat cultivars with better grain filling and foliage application of plant extracts may help improving the performance of bread wheat under combined heat and drought stresses. | N36: allelopathy; climate change; grain weight; secondary metabolites | O36: JOURNAL OF AGRONOMY AND CROP SCIENCE | P36: 203 | Q36: 6 | R36: 528 | S36: 538 | U36: farooqcp@gmail.com | V36: 10.1111/jac.12214 | W36: https://doi.org/10.1111/jac.12214 | X36: 0 | Y36: paywalled | Z36: 68__Application_of_natural_plant_extracts_improves_the_tolerance_against_combined_terminal_heat_and_drought_stresses_in_bread_wheat.pdf | AA36: https://onlinelibrary.wiley.com/doi/10.1111/jac.12214 | AC36: 403 | AD36: 2026-03-15 11:26:06 | AE36: =IFERROR(IF(ISBLANK(INDEX(wos_screening_view_full_text!$O:$O, MATCH($A36, wos_screening_view_full_text!$B:$B, 0))), "", INDEX(wos_screening_view_full_text!$O:$O, MATCH($A36, wos_screening_view_full_text!$B:$B, 0))), "") | AF36: =IFERROR(IF(ISBLANK(INDEX(wos_screening_view_full_text!$P:$P, MATCH($A36, wos_screening_view_full_text!$B:$B, 0))), "", INDEX(wos_screening_view_full_text!$P:$P, MATCH($A36, wos_screening_view_full_text!$B:$B, 0))), "") | AG36: =IFERROR(IF(ISBLANK(INDEX(wos_screening_view_full_text!$Q:$Q, MATCH($A36, wos_screening_view_full_text!$B:$B, 0))), "", INDEX(wos_screening_view_full_text!$Q:$Q, MATCH($A36, wos_screening_view_full_text!$B:$B, 0))), "")
A37: 69 | B37: WOS_savedrecs_1_r000094 | D37: WoS | E37: 1 | F37: 2026-02-26_005404 | G37: C:\Users\Luís Pinto Coelho\Desktop\Dissertação\StudyScreening_Meta-Analysis\data\web_of_science\raw_data\savedrecs_1.xls | H37: 94 | I37: 2026-02-26 | J37: Djanaguiraman, M; Narayanan, S; Erdayani, E; Prasad, PVV | K37: 2020 | L37: Effects of high temperature stress during anthesis and grain filling periods on photosynthesis, lipids and grain yield in wheat | M37: Background Short episodes of high temperature (HT) stress during reproductive stages of development cause significant yield losses in wheat (Triticum aestivumL.). Two independent experiments were conducted to quantify the effects of HT during anthesis and grain filling periods on photosynthesis, leaf lipidome, and yield traits in wheat. In experiment I, wheat genotype Seri82 was exposed to optimum temperature (OT; 22/14 degrees C; day/night) or HT (32/22 degrees C) for 14 d during anthesis stage. In experiment II, the plants were exposed to OT or HT for 14 d during the grain filling stage. During the HT stress, chlorophyll index, thylakoid membrane damage, stomatal conductance, photosynthetic rate and leaf lipid composition were measured. At maturity, grain yield and its components were quantified. Results HT stress during anthesis or grain filling stage decreased photosynthetic rate (17 and 25%, respectively) and grain yield plant(- 1)(29 and 44%, respectively), and increased thylakoid membrane damage (61 and 68%, respectively) compared to their respective control (OT). HT stress during anthesis or grain filling stage increased the molar percentage of less unsaturated lipid species [36:5- monogalactosyldiacylglycerol (MGDG) and digalactosyldiacylglycerol (DGDG)]. However, at grain filling stage, HT stress decreased the molar percentage of more unsaturated lipid species (36:6- MGDG and DGDG). There was a significant positive relationship between photosynthetic rate and grain yield plant(- 1), and a negative relationship between thylakoid membrane damage and photosynthetic rate. Conclusions The study suggests that maintaining thylakoid membrane stability, and seed-set per cent and individual grain weight under HT stress can improve the photosynthetic rate and grain yield, respectively. | N37: Grain number; High temperature; Individual grain weight; Lipids; Photosynthesis; Wheat | O37: BMC PLANT BIOLOGY | P37: 20 | Q37: 1 | T37: 268 | U37: vara@ksu.edu | V37: 10.1186/s12870-020-02479-0 | W37: https://doi.org/10.1186/s12870-020-02479-0 | X37: 1 | Y37: downloaded | Z37: 69__Effects_of_high_temperature_stress_during_anthesis_and_grain_filling_periods_on_photosynthesis,_lipids_and_grain_yield_in_wheat.pdf | AA37: https://link.springer.com/content/pdf/10.1186/s12870-020-02479-0.pdf | AB37: pdf_files/69__Effects_of_high_temperature_stress_during_anthesis_and_grain_filling_periods_on_photosynthesis,_lipids_and_grain_yield_in_wheat.pdf | AC37: 200 | AD37: 2026-03-15 11:26:08 | AE37: =IFERROR(IF(ISBLANK(INDEX(wos_screening_view_full_text!$O:$O, MATCH($A37, wos_screening_view_full_text!$B:$B, 0))), "", INDEX(wos_screening_view_full_text!$O:$O, MATCH($A37, wos_screening_view_full_text!$B:$B, 0))), "") | AF37: =IFERROR(IF(ISBLANK(INDEX(wos_screening_view_full_text!$P:$P, MATCH($A37, wos_screening_view_full_text!$B:$B, 0))), "", INDEX(wos_screening_view_full_text!$P:$P, MATCH($A37, wos_screening_view_full_text!$B:$B, 0))), "") | AG37: =IFERROR(IF(ISBLANK(INDEX(wos_screening_view_full_text!$Q:$Q, MATCH($A37, wos_screening_view_full_text!$B:$B, 0))), "", INDEX(wos_screening_view_full_text!$Q:$Q, MATCH($A37, wos_screening_view_full_text!$B:$B, 0))), "")
A38: 70 | B38: WOS_savedrecs_1_r000095 | D38: WoS | E38: 1 | F38: 2026-02-26_005404 | G38: C:\Users\Luís Pinto Coelho\Desktop\Dissertação\StudyScreening_Meta-Analysis\data\web_of_science\raw_data\savedrecs_1.xls | H38: 95 | I38: 2026-02-26 | J38: Bagherikia, S; Soughi, H; Khodarahmi, M; Naghipour, F | K38: 2025 | L38: The Effect of Sowing Dates on Grain Yield and Quality in Spring Wheat (Triticum aestivum L.) | M38: The impact of sowing dates on wheat (Triticum aestivum L.) quality and yield was investigated comprehensively across two locations during the growing seasons from 2020 to 2022. The study revealed contrasting effects of temperature on grain protein content and glutenin composition. The increase in temperature during the grain-filling period, caused by delayed sowing dates, led to an increase in grain protein content and wet gluten, while concurrently decreasing SDS and Zeleny sedimentation volumes, indicative of reduced gluten strength. This opposing trend underscores the complex relationship between temperature and wheat grain quality, influenced by the synthesis and polymerization of glutenin proteins critical for dough elasticity and baking performance. Furthermore, a negative relationship between ambient temperature and grain yield was observed across locations and years, highlighting the detrimental impact of heat stress on wheat productivity. Early sowing dates, which extended the grain-filling period under cooler conditions, favored higher grain yield and superior gluten quality, characterized by higher SDS and Zeleny values. In contrast, delayed sowing dates, exposing wheat to higher temperatures during grain filling, resulted in increased grain protein content and wet gluten but compromised gluten strength. The findings underscore the importance of optimizing sowing dates and developing heat-resilient wheat varieties to mitigate the adverse effects of climate change on wheat production. | N38: grain filling; grain quality; heat stress; protein; sowing dates | O38: FOOD SCIENCE & NUTRITION | P38: 13 | Q38: 5 | T38: e70035 | U38: s.bagherikia@areeo.ac.ir | V38: 10.1002/fsn3.70035 | W38: https://doi.org/10.1002/fsn3.70035 | X38: 0 | Y38: paywalled | Z38: 70__The_Effect_of_Sowing_Dates_on_Grain_Yield_and_Quality_in_Spring_Wheat_(Triticum_aestivum_L.).pdf | AA38: https://onlinelibrary.wiley.com/doi/10.1002/fsn3.70035 | AC38: 403 | AD38: 2026-03-15 11:26:10 | AE38: =IFERROR(IF(ISBLANK(INDEX(wos_screening_view_full_text!$O:$O, MATCH($A38, wos_screening_view_full_text!$B:$B, 0))), "", INDEX(wos_screening_view_full_text!$O:$O, MATCH($A38, wos_screening_view_full_text!$B:$B, 0))), "") | AF38: =IFERROR(IF(ISBLANK(INDEX(wos_screening_view_full_text!$P:$P, MATCH($A38, wos_screening_view_full_text!$B:$B, 0))), "", INDEX(wos_screening_view_full_text!$P:$P, MATCH($A38, wos_screening_view_full_text!$B:$B, 0))), "") | AG38: =IFERROR(IF(ISBLANK(INDEX(wos_screening_view_full_text!$Q:$Q, MATCH($A38, wos_screening_view_full_text!$B:$B, 0))), "", INDEX(wos_screening_view_full_text!$Q:$Q, MATCH($A38, wos_screening_view_full_text!$B:$B, 0))), "")
A39: 74 | B39: WOS_savedrecs_1_r000099 | D39: WoS | E39: 1 | F39: 2026-02-26_005404 | G39: C:\Users\Luís Pinto Coelho\Desktop\Dissertação\StudyScreening_Meta-Analysis\data\web_of_science\raw_data\savedrecs_1.xls | H39: 99 | I39: 2026-02-26 | J39: Raza, A; Din, WU; Waleed, A; Jabbar, A; Alharby, HF; Al-Solami, HM; Alabdallah, NM; Rehman, HU | K39: 2023 | L39: Magnesium fertilization reduces high-temperature damages during anthesis in spring wheat (Triticum aestivum L.) by affecting pollen viability and seed weight | M39: Terminal heat during reproductive stages of wheat (Triticum aestivum L.) limits the productivity of the crop. Magnesium (Mg) is an essential macronutrient that is involved in many physiological and biochemical processes to affect photosynthesis and seed weight. The present study comparatively evaluated Mg applied to soil (80 kg MgSO4 center dot 7H(2)O ha(-1)) and to plant foliage (4% w/v) in improving wheat performance under terminal heat. Wheat crop was grown in two sets of treatments until the booting stage, and then one set of plants was shifted to a glasshouse (+/- 5 degrees C) at the booting stage to grow until maturity in comparison to control plants kept under ambient warehouse condition. Heat stress reduced the pollen viability while foliar- and soil-applied Mg improved it by 3% and 6% under heat stress, respectively, compared to the control without Mg treatment. The 100-seed weight, spike length, and biological yield reduced by 39%, 19%, and 50% under heat stress; however, foliar and soil application increased 100-seed weight by 45% and 40%, spike length by 8% and 5%, and biological yield by 35% and 25% under heat stress, respectively. Soil Mg showed maximum SPAD chlorophyll values; however, response was statistically similar to that of foliar Mg as compared to the control without Mg supply. Membrane stability decreased (4%) due to heat stress while foliar and soil treatments improved membrane stability by 8% and 5% compared to that of the control, respectively. Thus, Mg application through soil or plant foliage can be an effective way to reduce negative impacts of terminal heat in wheat by improving pollen viability at anthesis and 100-seed weight that was attributed to increased chlorophyll contents during anthesis. | N39: Terminal heat stress; Magnesium; Pollen viability; Water-soluble carbohydrates; Seed weight; Stay green | O39: ENVIRONMENTAL SCIENCE AND POLLUTION RESEARCH | P39: 30 | Q39: 56 | R39: 118280 | S39: 118290 | U39: halharby@kau.edu.sa; hmalsolami@kau.edu.sa; nmalabdallah@iau.edu.sa; hafeezcp@gmail.com | V39: 10.1007/s11356-023-29911-w | W39: https://doi.org/10.1007/s11356-023-29911-w | X39: 1 | Y39: downloaded | Z39: 74__Magnesium_fertilization_reduces_high-temperature_damages_during_anthesis_in_spring_wheat_(Triticum_aestivum_L.)_by_affecting_pollen_viabilit.pdf | AA39: https://link.springer.com/content/pdf/10.1007/s11356-023-29911-w.pdf | AB39: pdf_files/74__Magnesium_fertilization_reduces_high-temperature_damages_during_anthesis_in_spring_wheat_(Triticum_aestivum_L.)_by_affecting_pollen_viabilit.pdf | AC39: 200 | AD39: 2026-03-15 11:26:15 | AE39: =IFERROR(IF(ISBLANK(INDEX(wos_screening_view_full_text!$O:$O, MATCH($A39, wos_screening_view_full_text!$B:$B, 0))), "", INDEX(wos_screening_view_full_text!$O:$O, MATCH($A39, wos_screening_view_full_text!$B:$B, 0))), "") | AF39: =IFERROR(IF(ISBLANK(INDEX(wos_screening_view_full_text!$P:$P, MATCH($A39, wos_screening_view_full_text!$B:$B, 0))), "", INDEX(wos_screening_view_full_text!$P:$P, MATCH($A39, wos_screening_view_full_text!$B:$B, 0))), "") | AG39: =IFERROR(IF(ISBLANK(INDEX(wos_screening_view_full_text!$Q:$Q, MATCH($A39, wos_screening_view_full_text!$B:$B, 0))), "", INDEX(wos_screening_view_full_text!$Q:$Q, MATCH($A39, wos_screening_view_full_text!$B:$B, 0))), "")
A40: 75 | B40: WOS_savedrecs_1_r000101 | D40: WoS | E40: 1 | F40: 2026-02-26_005404 | G40: C:\Users\Luís Pinto Coelho\Desktop\Dissertação\StudyScreening_Meta-Analysis\data\web_of_science\raw_data\savedrecs_1.xls | H40: 101 | I40: 2026-02-26 | J40: Goher, R; Alkharabsheh, HM; Seleiman, MF; Diatta, AA; Gitari, H; Wasonga, DO; Khan, GR; Akmal, M | K40: 2023 | L40: Impacts of heat shock on productivity and quality of Triticum aestivum L. at different growth stages | M40: The transitional phase of climate change is becoming a threat worldwide. Fluctuations in temperature are frequently observed in the life cycles of field crops. The current study was intended to evaluate heat stress (HS) at sensitive stages on four wheat cultivars' growth, grain yield, and quality traits during two consecutive seasons. The experiment included four spring wheat cultivars that were exposed to HS durations (i.e., 0, 48, 96 and 144 h) at booting and anthesis stages. Pots were kept in an open-air, and labeled pots were moved to the glasshouse at the respective growth stage. After HS treatments, pots were moved from the glasshouse to the original position in the open air. The results showed that the cultivars differed in yield and grain quality traits, but their collective mean effect was significantly expressed with HS and HS duration (HSd) on the measured traits. Spike length was significantly affected by HS at the anthesis in comparison to those obtained from the control. However, the increase in HSd did not cause a significant effect on spike length compared to other treatments. Spike weight was significantly decreased in plants exposed to HS at booting and anthesis as well as by increasing HSd. In addition, grain weight and numbers were decreased in plants exposed to HS at booting and anthesis stages with a similar pattern by increasing HSd. Moreover, a reduction in amylose content was observed in grains of plants exposed to HS at booting and anthesis stages or when plants as exposed to a longer period of HSd. Nonetheless, amylopectin, wet gluten (WG) and grain N (GN) showed an increase in plants exposed to HS at booting and anthesis stages and/or extending HSd. This study concludes that plants exposed to different HS treatments during the life cycle had lower values for spike length, grains weight, and grains number per spike including amylose content in comparison to those obtained from the control. The decrease was significantly noted in the yield and grain quality of wheat when plants were exposed to HS at the booting stage in comparison to those exposed to HS at anthesis. | N40: climate change; heat shock duration; grain quality; wheat yield | O40: NOTULAE BOTANICAE HORTI AGROBOTANICI CLUJ-NAPOCA | P40: 51 | Q40: 1 | T40: 13090 | U40: rabiagoher@aup.edu.pk; Drhibakh@bau.edu.jo; mseleiman@ksu.edu.sa; andre-amakobo.diatta@ugb.edu.sn; harun.gitari@ku.ac.ke; dwasonga@illinois.edu; gulrozkhan@aup.edu.pk; akmal@aup.edu.pk | V40: 10.15835/nbha51113090 | W40: https://doi.org/10.15835/nbha51113090 | X40: 1 | Y40: downloaded | Z40: 75__Impacts_of_heat_shock_on_productivity_and_quality_of_Triticum_aestivum_L._at_different_growth_stages.pdf | AA40: https://www.notulaebotanicae.ro/index.php/nbha/article/download/13090/9536 | AB40: pdf_files/75__Impacts_of_heat_shock_on_productivity_and_quality_of_Triticum_aestivum_L._at_different_growth_stages.pdf | AC40: 200 | AD40: 2026-03-15 11:26:19 | AE40: =IFERROR(IF(ISBLANK(INDEX(wos_screening_view_full_text!$O:$O, MATCH($A40, wos_screening_view_full_text!$B:$B, 0))), "", INDEX(wos_screening_view_full_text!$O:$O, MATCH($A40, wos_screening_view_full_text!$B:$B, 0))), "") | AF40: =IFERROR(IF(ISBLANK(INDEX(wos_screening_view_full_text!$P:$P, MATCH($A40, wos_screening_view_full_text!$B:$B, 0))), "", INDEX(wos_screening_view_full_text!$P:$P, MATCH($A40, wos_screening_view_full_text!$B:$B, 0))), "") | AG40: =IFERROR(IF(ISBLANK(INDEX(wos_screening_view_full_text!$Q:$Q, MATCH($A40, wos_screening_view_full_text!$B:$B, 0))), "", INDEX(wos_screening_view_full_text!$Q:$Q, MATCH($A40, wos_screening_view_full_text!$B:$B, 0))), "")
A41: 76 | B41: WOS_savedrecs_1_r000103 | D41: WoS | E41: 1 | F41: 2026-02-26_005404 | G41: C:\Users\Luís Pinto Coelho\Desktop\Dissertação\StudyScreening_Meta-Analysis\data\web_of_science\raw_data\savedrecs_1.xls | H41: 103 | I41: 2026-02-26 | J41: Thakur, V; Rane, J; Nankar, AN | K41: 2022 | L41: Comparative Analysis of Canopy Cooling in Wheat under High Temperature and Drought Stress | M41: The size and the weight of wheat grains vary across the length of each spike (Triticum aestivum L.). High temperature and water scarcity often reduce the single grain weight, and this reduction also varies across the spike length. Plants tend to cope with high temperature and drought stress through inherent mechanisms such ascanopy cooling through transpiration, which can contribute to yield stability. The effect of canopy cooling on the average grain weight at different positions in spike is still unknown. In this study, we planned to assess the role of canopy temperature, yield-related traits, and spike shape in final grain weight. For two years (2017-2018 and 2018-2019), fifteen diverse genotypes released for cultivation in different environmental conditions were grown in the field. They were examined for canopy temperature, spikelets spike(-1), grain number spike(-1), grain yield spike(-1), and grain weight of the spike's basal, median, and distal regions. The Pearson correlation coefficient (r) was obtained for all pair-wise combinations of traits under different treatments and spike shapes. The results indicated that cooler canopy is correlated to grain weight in normal spike shape at all three positions within the spike irrespective of stress. The advantage of the cooler canopy in improving grain-filling at basal, median, and distal regions was more conspicuous in the high temperature stress conditions compared to non-stressed and drought conditions. | N41: canopy temperature depression; basal; median and distal regions of spike; normal spike shape; high temperature; drought | O41: AGRONOMY-BASEL | P41: 12 | Q41: 4 | T41: 978 | U41: vidisha.thakur30@gmail.com; jagrane@hotmail.com; nankar@cpsbb.eu | V41: 10.3390/agronomy12040978 | W41: https://doi.org/10.3390/agronomy12040978 | X41: 0 | Y41: paywalled | Z41: 76__Comparative_Analysis_of_Canopy_Cooling_in_Wheat_under_High_Temperature_and_Drought_Stress.pdf | AA41: https://www.mdpi.com/2073-4395/12/4/978 | AC41: 403 | AD41: 2026-03-15 11:26:21 | AE41: =IFERROR(IF(ISBLANK(INDEX(wos_screening_view_full_text!$O:$O, MATCH($A41, wos_screening_view_full_text!$B:$B, 0))), "", INDEX(wos_screening_view_full_text!$O:$O, MATCH($A41, wos_screening_view_full_text!$B:$B, 0))), "") | AF41: =IFERROR(IF(ISBLANK(INDEX(wos_screening_view_full_text!$P:$P, MATCH($A41, wos_screening_view_full_text!$B:$B, 0))), "", INDEX(wos_screening_view_full_text!$P:$P, MATCH($A41, wos_screening_view_full_text!$B:$B, 0))), "") | AG41: =IFERROR(IF(ISBLANK(INDEX(wos_screening_view_full_text!$Q:$Q, MATCH($A41, wos_screening_view_full_text!$B:$B, 0))), "", INDEX(wos_screening_view_full_text!$Q:$Q, MATCH($A41, wos_screening_view_full_text!$B:$B, 0))), "")
A42: 78 | B42: WOS_savedrecs_1_r000108 | D42: WoS | E42: 1 | F42: 2026-02-26_005404 | G42: C:\Users\Luís Pinto Coelho\Desktop\Dissertação\StudyScreening_Meta-Analysis\data\web_of_science\raw_data\savedrecs_1.xls | H42: 108 | I42: 2026-02-26 | J42: Mahrookashani, A; Siebert, S; Hüging, H; Ewert, F | K42: 2017 | L42: Independent and combined effects of high temperature and drought stress around anthesis on wheat | M42: High temperature and drought stress are projected to reduce crop yields and threaten food security. While effects of heat and drought on crop growth and yield have been studied separately, little is known about the combined effect of these stressors. We studied detrimental effects of high temperature, drought stress and combined heat and drought stress around anthesis on yield and its components for three wheat cultivars originating from Germany and Iran. We found that effects of combined heat and drought on the studied physiological and yield traits were considerably stronger than those of the individual stress factors alone, but the magnitude of the effects varied for specific growth- and yield-related traits. Single grain weight was reduced under drought stress by 13%-27% and under combined heat and drought stress by 43%-83% but not by heat stress alone. Heat stress significantly decreased grain number by 14%-28%, grain yield by 16%-25% and straw yield by 15%-25%. Cultivar responses were similar for heat but different for drought and combined heat and drought treatments. We conclude that heat stress as imposed in this study is less detrimental than the effects of those other studied stresses on growth and yield traits. | N42: combined heat and drought stress; drought stress; high temperature; wheat | O42: JOURNAL OF AGRONOMY AND CROP SCIENCE | P42: 203 | Q42: 6 | R42: 453 | S42: 463 | U42: amahru@uni-bonn.de | V42: 10.1111/jac.12218 | W42: https://doi.org/10.1111/jac.12218 | X42: 0 | Y42: paywalled | Z42: 78__Independent_and_combined_effects_of_high_temperature_and_drought_stress_around_anthesis_on_wheat.pdf | AA42: https://onlinelibrary.wiley.com/doi/10.1111/jac.12218 | AC42: 403 | AD42: 2026-03-15 11:26:22 | AE42: =IFERROR(IF(ISBLANK(INDEX(wos_screening_view_full_text!$O:$O, MATCH($A42, wos_screening_view_full_text!$B:$B, 0))), "", INDEX(wos_screening_view_full_text!$O:$O, MATCH($A42, wos_screening_view_full_text!$B:$B, 0))), "") | AF42: =IFERROR(IF(ISBLANK(INDEX(wos_screening_view_full_text!$P:$P, MATCH($A42, wos_screening_view_full_text!$B:$B, 0))), "", INDEX(wos_screening_view_full_text!$P:$P, MATCH($A42, wos_screening_view_full_text!$B:$B, 0))), "") | AG42: =IFERROR(IF(ISBLANK(INDEX(wos_screening_view_full_text!$Q:$Q, MATCH($A42, wos_screening_view_full_text!$B:$B, 0))), "", INDEX(wos_screening_view_full_text!$Q:$Q, MATCH($A42, wos_screening_view_full_text!$B:$B, 0))), "")
A43: 80 | B43: WOS_savedrecs_1_r000110 | D43: WoS | E43: 1 | F43: 2026-02-26_005404 | G43: C:\Users\Luís Pinto Coelho\Desktop\Dissertação\StudyScreening_Meta-Analysis\data\web_of_science\raw_data\savedrecs_1.xls | H43: 110 | I43: 2026-02-26 | J43: Mamrutha, HM; Rinki, K; Venkatesh, K; Gopalareddy, K; Khan, H; Mishra, CN; Kumar, S; Kumar, Y; Singh, G; Singh, GP | K43: 2020 | L43: Impact of high night temperature stress on different growth stages of wheat | M43: Increasing temperature especially the High night temperature (HNT) is a major constriction for sustaining global food production under changing climate scenario. Recent climate change has resulted into events of abrupt night temperature rise either throughout the crop period or at specific growth stage. Historical temperature observations and model projections have predicted a more pronounced increase in night temperature [minimum temperature (T-min.)] compared to that of day temperatures [maximum temperature (T-max.)]. Hence, the present study was carried out to identify the most critical growth stage affected by HNT and their effects on physiological, growth and yield traits of wheat. A unique field-based movable temperature controlling system was designed to enhance the night temperature by 5 degrees C than ambient temperature. The three critical phenological stages of wheat i.e. at GS 15 (before tillering initiation), GS 45 (booting) and GS 75 (grain filling) of Zadok's scale were separately subjected to HNT treatment. The results reveals that GS 75 (grain filling) was the most sensitive stage affected by HNT, which has recorded remarkable reduction in grain yield (GY), Harvest Index (HI), Thousand grain weight (TGW) and grain weight per spike (GWPS) compared to control treatment. Pearson correlation analysis showed that breeders can choose lines with higher TGW, GWPS and grain number per spike (GNPS) for obtaining better GY under HNT conditions and vegetative/booting stage HNT in field condition may not attribute for any significant yield loss. | N43: Triticum aestivum L; High night temperature (HNT); Wheat; Heat stress; Physiological traits; Yield traits | O43: PLANT PHYSIOLOGY REPORTS | P43: 25 | Q43: 4 | R43: 707 | S43: 715 | U43: mamrutha.M@icar.gov.in | V43: 10.1007/s40502-020-00558-w | W43: https://doi.org/10.1007/s40502-020-00558-w | X43: 1 | Y43: downloaded | Z43: 80__Impact_of_high_night_temperature_stress_on_different_growth_stages_of_wheat.pdf | AA43: https://link.springer.com/content/pdf/10.1007/s40502-020-00558-w.pdf | AB43: pdf_files/80__Impact_of_high_night_temperature_stress_on_different_growth_stages_of_wheat.pdf | AC43: 200 | AD43: 2026-03-15 11:26:27 | AE43: =IFERROR(IF(ISBLANK(INDEX(wos_screening_view_full_text!$O:$O, MATCH($A43, wos_screening_view_full_text!$B:$B, 0))), "", INDEX(wos_screening_view_full_text!$O:$O, MATCH($A43, wos_screening_view_full_text!$B:$B, 0))), "") | AF43: =IFERROR(IF(ISBLANK(INDEX(wos_screening_view_full_text!$P:$P, MATCH($A43, wos_screening_view_full_text!$B:$B, 0))), "", INDEX(wos_screening_view_full_text!$P:$P, MATCH($A43, wos_screening_view_full_text!$B:$B, 0))), "") | AG43: =IFERROR(IF(ISBLANK(INDEX(wos_screening_view_full_text!$Q:$Q, MATCH($A43, wos_screening_view_full_text!$B:$B, 0))), "", INDEX(wos_screening_view_full_text!$Q:$Q, MATCH($A43, wos_screening_view_full_text!$B:$B, 0))), "")
A44: 81 | B44: WOS_savedrecs_1_r000111 | D44: WoS | E44: 1 | F44: 2026-02-26_005404 | G44: C:\Users\Luís Pinto Coelho\Desktop\Dissertação\StudyScreening_Meta-Analysis\data\web_of_science\raw_data\savedrecs_1.xls | H44: 111 | I44: 2026-02-26 | J44: Schittenhelm, S; Langkamp-Wedde, T; Kraft, M; Kottmann, L; Matschiner, K | K44: 2020 | L44: Effect of two-week heat stress during grain filling on stem reserves, senescence, and grain yield of European winter wheat cultivars | M44: To examine the extent to which heat stress during grain filling impacts on the development and yield of winter wheat (Triticum aestivum L.), a 3-year field experiment was conducted on a loess soil with high water holding capacity in the North German Plain. Thirty-two mostly European winter wheat cultivars were exposed to heat stress in a mobile foil tunnel with maximum air temperatures of 45.7, 45.4, and 47.2 degrees C in 2015, 2016, and 2017, respectively. The 14-day post-anthesis heat stress treatment caused an average 57.3% grain yield reduction compared to a close-by non-stressed control. The proportion of green crop area after the heat stress phase varied from 7% to 98% in 2016 and from 37% to 94% in 2017. The green crop area percentage did not significantly correlate with grain yield, indicating that the delayed senescence of stay-green phenotypes offers no yield advantage under terminal heat stress. The water soluble carbohydrate (WSC) concentration of the stems at crop maturity varied between 6 and 92 g/kg dry matter, showing that the genotypes differed in their efficiency at using the stem carbohydrate reserves for grain filling under heat stress. The stem WSC concentration correlated positively with the beginning of anthesis (r = 0.704; p < .001) but negatively with the grain yield (r = -0.431; p < .05). For heat tolerance breeding, the stem reserve strategy, i. e. the rapid and full exhaustion of the temporary carbohydrate storage therefore seems more promising than the stay-green strategy. | N44: chlorophyll degradation; grain weight; post-anthesis heat stress; stay-green; Triticum aestivum; wheat breeding | O44: JOURNAL OF AGRONOMY AND CROP SCIENCE | P44: 206 | Q44: 6 | R44: 722 | S44: 733 | U44: siegfried.schittenhelm@julius-kuehn.de | V44: 10.1111/jac.12410 | W44: https://doi.org/10.1111/jac.12410 | X44: 0 | Y44: paywalled | Z44: 81__Effect_of_two-week_heat_stress_during_grain_filling_on_stem_reserves,_senescence,_and_grain_yield_of_European_winter_wheat_cultivars.pdf | AA44: https://onlinelibrary.wiley.com/doi/10.1111/jac.12410 | AC44: 403 | AD44: 2026-03-15 11:26:28 | AE44: =IFERROR(IF(ISBLANK(INDEX(wos_screening_view_full_text!$O:$O, MATCH($A44, wos_screening_view_full_text!$B:$B, 0))), "", INDEX(wos_screening_view_full_text!$O:$O, MATCH($A44, wos_screening_view_full_text!$B:$B, 0))), "") | AF44: =IFERROR(IF(ISBLANK(INDEX(wos_screening_view_full_text!$P:$P, MATCH($A44, wos_screening_view_full_text!$B:$B, 0))), "", INDEX(wos_screening_view_full_text!$P:$P, MATCH($A44, wos_screening_view_full_text!$B:$B, 0))), "") | AG44: =IFERROR(IF(ISBLANK(INDEX(wos_screening_view_full_text!$Q:$Q, MATCH($A44, wos_screening_view_full_text!$B:$B, 0))), "", INDEX(wos_screening_view_full_text!$Q:$Q, MATCH($A44, wos_screening_view_full_text!$B:$B, 0))), "")
A45: 83 | B45: WOS_savedrecs_1_r000114 | D45: WoS | E45: 1 | F45: 2026-02-26_005404 | G45: C:\Users\Luís Pinto Coelho\Desktop\Dissertação\StudyScreening_Meta-Analysis\data\web_of_science\raw_data\savedrecs_1.xls | H45: 114 | I45: 2026-02-26 | J45: Liu, HP; Able, AJ; Able, JA | K45: 2021 | L45: Small RNA, Transcriptome and Degradome Analysis of the Transgenerational Heat Stress Response Network in Durum Wheat | M45: Heat stress is a major limiting factor of grain yield and quality in crops. Abiotic stresses have a transgenerational impact and the mechanistic basis is associated with epigenetic regulation. The current study presents the first systematic analysis of the transgenerational effects of post-anthesis heat stress in tetraploid wheat. Leaf physiological traits, harvest components and grain quality traits were characterized under the impact of parental and progeny heat stress. The parental heat stress treatment had a positive influence on the offspring for traits including chlorophyll content, grain weight, grain number and grain total starch content. Integrated sequencing analysis of the small RNAome, mRNA transcriptome and degradome provided the first description of the molecular networks mediating heat stress adaptation under transgenerational influence. The expression profile of 1771 microRNAs (733 being novel) and 66,559 genes was provided, with differentially expressed microRNAs and genes characterized subject to the progeny treatment, parental treatment and tissue-type factors. Gene Ontology and KEGG pathway analysis of stress responsive microRNAs-mRNA modules provided further information on their functional roles in biological processes such as hormone homeostasis, signal transduction and protein stabilization. Our results provide new insights on the molecular basis of transgenerational heat stress adaptation, which can be used for improving thermo-tolerance in breeding. | N45: heat stress; transgenerational stress memory; next-generation sequencing; microRNAs; cereal reproduction; crop improvement; tetraploid wheat | O45: INTERNATIONAL JOURNAL OF MOLECULAR SCIENCES | P45: 22 | Q45: 11 | T45: 5532 | U45: haipei.liu@adelaide.edu.au; amanda.able@adelaide.edu.au; jason.able@adelaide.edu.au | V45: 10.3390/ijms22115532 | W45: https://doi.org/10.3390/ijms22115532 | X45: 0 | Y45: paywalled | Z45: 83__Small_RNA,_Transcriptome_and_Degradome_Analysis_of_the_Transgenerational_Heat_Stress_Response_Network_in_Durum_Wheat.pdf | AA45: https://www.mdpi.com/1422-0067/22/11/5532 | AC45: 403 | AD45: 2026-03-15 11:26:30 | AE45: =IFERROR(IF(ISBLANK(INDEX(wos_screening_view_full_text!$O:$O, MATCH($A45, wos_screening_view_full_text!$B:$B, 0))), "", INDEX(wos_screening_view_full_text!$O:$O, MATCH($A45, wos_screening_view_full_text!$B:$B, 0))), "") | AF45: =IFERROR(IF(ISBLANK(INDEX(wos_screening_view_full_text!$P:$P, MATCH($A45, wos_screening_view_full_text!$B:$B, 0))), "", INDEX(wos_screening_view_full_text!$P:$P, MATCH($A45, wos_screening_view_full_text!$B:$B, 0))), "") | AG45: =IFERROR(IF(ISBLANK(INDEX(wos_screening_view_full_text!$Q:$Q, MATCH($A45, wos_screening_view_full_text!$B:$B, 0))), "", INDEX(wos_screening_view_full_text!$Q:$Q, MATCH($A45, wos_screening_view_full_text!$B:$B, 0))), "")
A46: 85 | B46: WOS_savedrecs_1_r000116 | D46: WoS | E46: 1 | F46: 2026-02-26_005404 | G46: C:\Users\Luís Pinto Coelho\Desktop\Dissertação\StudyScreening_Meta-Analysis\data\web_of_science\raw_data\savedrecs_1.xls | H46: 116 | I46: 2026-02-26 | J46: Pratap, A; Taylor, NL; Pal, M; Chinnusamy, V; Siddique, KHM | K46: 2025 | L46: Heat tolerance mechanisms in bread wheat: Insights from flag leaves and spike tissues | M46: Heat stress significantly limits global bread wheat (Triticum aestivum L.) productivity. This study investigated the mechanisms underlying heat tolerance by comparing physiological responses, yield components, and proteomic profiles in flag leaves and spike tissues of two heat-tolerant (RAJ3765-T, HD2932-T) and two susceptible (HD2329-S, HD2733-S) wheat genotypes under short-term (32 degrees C for 5 days) and long-term (32 degrees C until maturity) heat stress at ear peep (Zadoks' stage 51). Short-term heat stress significantly reduced grain yield (6.16-42.78 %), primarily by decreasing grain number per plant (27.79-57.73 %), while long-term heat stress reduced thousand grain weight (10.55-27.33 %). Tolerant genotypes (RAJ3765-T, HD2932-T) maintained higher grain yields by preserving photosynthesis, membrane stability (r = 0.88, p <= 0.05), pollen viability (r = 0.74, p <= 0.05) and chlorophyll content (r = 0.82, p <= 0.05) while preventing excessive reactive oxygen species (ROS) accumulation (r=-0.83, p <= 0.05). These genotypes also sustained higher above-ground biomass and harvest index under both the heat conditions, whereas grain protein content increased across all genotypes (8.91-15.47 %). Proteomic analysis identified 31 and 60 differentially abundant proteins in flag leaves and spikes, respectively. Key proteins associated with heat tolerance in flag leaves were involved in photosynthesis, amino acid metabolism, and chromatin organization, while those linked to susceptibility were related to carbohydrate metabolism, methylation, chromatin and cell wall organization, and solute transport. Disrupted redox homeostasis was a typical heat susceptibility response in both spikes and flag leaves. Co-expression analysis revealed protein networks associated with redox homeostasis and chlorophyll biosynthesis, which significantly correlated with grain yield, offering novel biomarkers to breeding heat-tolerant wheat varieties. | N46: Heat-responsive proteins; Photosynthetic efficiency; Reactive oxygen species (ROS) scavenging; Thermotolerance; Yield stability; Biomarkers, climate change | O46: PLANT STRESS | P46: 16 | T46: 100876 | U46: kadambot.siddique@uwa.edu.au | V46: 10.1016/j.stress.2025.100876 | W46: https://doi.org/10.1016/j.stress.2025.100876 | X46: 0 | Y46: manual_check | Z46: 85__Heat_tolerance_mechanisms_in_bread_wheat_Insights_from_flag_leaves_and_spike_tissues.pdf | AA46: https://linkinghub.elsevier.com/retrieve/pii/S2667064X25001447 | AC46: 200 | AD46: 2026-03-15 11:26:31 | AE46: =IFERROR(IF(ISBLANK(INDEX(wos_screening_view_full_text!$O:$O, MATCH($A46, wos_screening_view_full_text!$B:$B, 0))), "", INDEX(wos_screening_view_full_text!$O:$O, MATCH($A46, wos_screening_view_full_text!$B:$B, 0))), "") | AF46: =IFERROR(IF(ISBLANK(INDEX(wos_screening_view_full_text!$P:$P, MATCH($A46, wos_screening_view_full_text!$B:$B, 0))), "", INDEX(wos_screening_view_full_text!$P:$P, MATCH($A46, wos_screening_view_full_text!$B:$B, 0))), "") | AG46: =IFERROR(IF(ISBLANK(INDEX(wos_screening_view_full_text!$Q:$Q, MATCH($A46, wos_screening_view_full_text!$B:$B, 0))), "", INDEX(wos_screening_view_full_text!$Q:$Q, MATCH($A46, wos_screening_view_full_text!$B:$B, 0))), "")
A47: 88 | B47: WOS_savedrecs_1_r000120 | D47: WoS | E47: 1 | F47: 2026-02-26_005404 | G47: C:\Users\Luís Pinto Coelho\Desktop\Dissertação\StudyScreening_Meta-Analysis\data\web_of_science\raw_data\savedrecs_1.xls | H47: 120 | I47: 2026-02-26 | J47: Oliveira, CED; Andrade, AD; Zoz, A; Sobrinho, RL; Zoz, T | K47: 2020 | L47: Genetic divergence and path analysis in wheat cultivars under heat stress | M47: One of the biggest limitations for the wheat crop expansion to Brazilian tropical regions is the high temperature in the rainy season. This study aimed to select, based on genetic divergence and path analysis, cultivars that tolerate cultivation in the summer (heat stress). Nine wheat cultivars were sown, using a randomized block design with three replications, with plots consisting of 10 rows of 6 m and row spacing of 0.15 m. The highest grain yield and number of ears m(-2) were observed for the CD 150 cultivar and the largest 1,000-grain weight for CD 116. BRS 220, IPR 136, IPR 144 and BRS Pardela had the highest number of sterile spikelets. The highest number of grains per ear was observed for CD 150, CD 116, BRS Pardela, IPR 130 and IPR 85, showing direct effects on grain yield, evidenced by the path analysis. CD 116 and CD 150 were the most productive cultivars and can be considered as possible parents in wheat breeding programs. IPR 85, CD 116, CD 108 and CD 150 showed a greater tolerance to high temperatures. | N47: Triticum aestivum; genotypic correlations; high-temperature tolerance; wheat crop expansion | O47: PESQUISA AGROPECUARIA TROPICAL | P47: 50 | T47: e65493 | U47: carllos_eduard@hotmail.com; agner_freitas@hotmail.com; andre_zoz@hotmail.com; renato.lustosasobrinho@uantwerpen.be; zoz@uems.br | V47: 10.1590/1983-40632020v5065493 | W47: https://doi.org/10.1590/1983-40632020v5065493 | X47: 0 | Y47: manual_check | Z47: 88__Genetic_divergence_and_path_analysis_in_wheat_cultivars_under_heat_stress.pdf | AA47: https://www.scielo.br/j/pat/a/S3rKQ8KB3rdj3GQrdkKpg4q/?lang=en&amp;format=pdf | AC47: 200 | AD47: 2026-03-15 11:26:37 | AE47: =IFERROR(IF(ISBLANK(INDEX(wos_screening_view_full_text!$O:$O, MATCH($A47, wos_screening_view_full_text!$B:$B, 0))), "", INDEX(wos_screening_view_full_text!$O:$O, MATCH($A47, wos_screening_view_full_text!$B:$B, 0))), "") | AF47: =IFERROR(IF(ISBLANK(INDEX(wos_screening_view_full_text!$P:$P, MATCH($A47, wos_screening_view_full_text!$B:$B, 0))), "", INDEX(wos_screening_view_full_text!$P:$P, MATCH($A47, wos_screening_view_full_text!$B:$B, 0))), "") | AG47: =IFERROR(IF(ISBLANK(INDEX(wos_screening_view_full_text!$Q:$Q, MATCH($A47, wos_screening_view_full_text!$B:$B, 0))), "", INDEX(wos_screening_view_full_text!$Q:$Q, MATCH($A47, wos_screening_view_full_text!$B:$B, 0))), "")
A48: 89 | B48: WOS_savedrecs_1_r000121 | D48: WoS | E48: 1 | F48: 2026-02-26_005404 | G48: C:\Users\Luís Pinto Coelho\Desktop\Dissertação\StudyScreening_Meta-Analysis\data\web_of_science\raw_data\savedrecs_1.xls | H48: 121 | I48: 2026-02-26 | J48: Tahir, ISA; Nakata, N | K48: 2005 | L48: Remobilization of nitrogen and carbohydrate from stems of bread wheat in response to heat stress during grain filling | M48: When wheat (Triticum aestivum L.) is grown under heat-stress conditions during grain filling, preanthesis stored total non-structural carbohydrates (TNC) and nitrogen (N) could serve as alternative source of assimilates. This study was performed to evaluate wheat genotypes for their ability to accumulate and remobilize TNC and N stored in their stem to support grain filling under heat stress. Eighteen genotypes were used for N remobilization study while nine of them were used for TNC remobilization study. They were grown in pots and placed in a vinyl house with the maximum temperature kept below 30 degrees C. Five days after anthesis (5DAA), half of the pots were taken to phytotrons where temperature was gradually increased and the maximum was set at 38 degrees C. Grain yield and grain weight decreased by about 35 % under heat stress. Significant differences were found among genotypes in percentage reduction in grain yield, grain weight, grain filling duration and harvest index because of heat stress. The N and TNC concentrations of the stem at 5DAA were significantly different among genotypes. Heat stress significantly reduced the N remobilization efficiency of most of genotypes. However, heat stress significantly increased TNC remobilization efficiency and significant variation were observed among genotypes. N remobilization efficiency across treatments significantly correlated with grain yield, grain weight, harvest index and grain filling duration. TNC at 5DAA negatively correlated with N at 5DAA and harvest index, but the TNC remobilization efficiency under heat stress positively correlated with mainstem grain yield, grain weight and harvest index. The rate of chlorophyll loss from flag leaf positively correlated with N and TNC remobilization efficiencies under heat stress suggesting a link between leaf senescence and remobilization efficiency. The results indicate that heat stress negatively affected grain yield, its components and N remobilization while it increased TNC remobilization because of the increasing demand for resources. | N48: bread wheat; grain filling; heat stress; nitrogen; remobilization; total nonstructural carbohydrates | O48: JOURNAL OF AGRONOMY AND CROP SCIENCE | P48: 191 | Q48: 2 | R48: 106 | S48: 115 | U48: nnakata@muses.tottori-u.ac.jp | V48: 10.1111/j.1439-037x.2004.00127.x | W48: https://doi.org/10.1111/j.1439-037x.2004.00127.x | X48: 0 | Y48: paywalled | Z48: 89__Remobilization_of_nitrogen_and_carbohydrate_from_stems_of_bread_wheat_in_response_to_heat_stress_during_grain_filling.pdf | AA48: https://onlinelibrary.wiley.com/doi/10.1111/j.1439-037X.2004.00127.x | AC48: 403 | AD48: 2026-03-15 11:26:38 | AE48: =IFERROR(IF(ISBLANK(INDEX(wos_screening_view_full_text!$O:$O, MATCH($A48, wos_screening_view_full_text!$B:$B, 0))), "", INDEX(wos_screening_view_full_text!$O:$O, MATCH($A48, wos_screening_view_full_text!$B:$B, 0))), "") | AF48: =IFERROR(IF(ISBLANK(INDEX(wos_screening_view_full_text!$P:$P, MATCH($A48, wos_screening_view_full_text!$B:$B, 0))), "", INDEX(wos_screening_view_full_text!$P:$P, MATCH($A48, wos_screening_view_full_text!$B:$B, 0))), "") | AG48: =IFERROR(IF(ISBLANK(INDEX(wos_screening_view_full_text!$Q:$Q, MATCH($A48, wos_screening_view_full_text!$B:$B, 0))), "", INDEX(wos_screening_view_full_text!$Q:$Q, MATCH($A48, wos_screening_view_full_text!$B:$B, 0))), "")
A49: 91 | B49: WOS_savedrecs_1_r000124 | D49: WoS | E49: 1 | F49: 2026-02-26_005404 | G49: C:\Users\Luís Pinto Coelho\Desktop\Dissertação\StudyScreening_Meta-Analysis\data\web_of_science\raw_data\savedrecs_1.xls | H49: 124 | I49: 2026-02-26 | J49: Khan, SU; Din, JU; Qayyum, A; Jan, NE; Jenks, MA | K49: 2015 | L49: Heat tolerance indicators in Pakistani wheat (Triticum aestivum L.) genotypes | M49: The effect of high temperature stress on six wheat cultivars exposed to 35-40 degrees C for 3 h each day for five consecutive days was examined. High temperature significantly affected total proline, soluble protein content, membrane stability index (MSI), yield, and various yield components, and had a direct effect on growth and other physiological attributes of wheat at anthesis and the milky seed stages. The wheat cultivar AS-2002 achieved better osmotic adjustment by accumulating more leaf proline. Higher MSI was also observed in AS-2002, as well as Inqalab-91. The anthesis growth stage was found to be more sensitive to heat stress than seed development at the milky stage. Overall heat stress reduced yield 75% at anthesis and 40% at the milky stage. AS-2002 performed better on the basis of yield and yield components. Seed weight per spike was highest in AS-2002, and lowest in SH-2002. The cumulative response of AS-2002 was better on the basis of physiological and yield attributes. In addition to yield, plant breeders should also include proline and MSI as selection parameter in the breeding program for development of heat tolerant wheat cultivars. Most of the evaluated wheat cultivars/lines were developed for cultivation in the rainfed areas of Pakistan. | N49: anthesis; grain yield; heat stress; membrane stability index; milky seed stage; proline; soluble proteins; Triticum aestivum L.; wheat | O49: ACTA BOTANICA CROATICA | P49: 74 | Q49: 1 | R49: 109 | S49: 121 | U49: aqayyum@uoh.edu.pk | V49: 10.1515/botcro-2015-0002 | W49: https://doi.org/10.1515/botcro-2015-0002 | X49: 0 | Y49: not_found | Z49: 91__Heat_tolerance_indicators_in_Pakistani_wheat_(Triticum_aestivum_L.)_genotypes.pdf | AA49: https://reference-global.com:443/journals/botcro/74/1/article-p109 | AC49: 404 | AD49: 2026-03-15 11:26:41 | AE49: =IFERROR(IF(ISBLANK(INDEX(wos_screening_view_full_text!$O:$O, MATCH($A49, wos_screening_view_full_text!$B:$B, 0))), "", INDEX(wos_screening_view_full_text!$O:$O, MATCH($A49, wos_screening_view_full_text!$B:$B, 0))), "") | AF49: =IFERROR(IF(ISBLANK(INDEX(wos_screening_view_full_text!$P:$P, MATCH($A49, wos_screening_view_full_text!$B:$B, 0))), "", INDEX(wos_screening_view_full_text!$P:$P, MATCH($A49, wos_screening_view_full_text!$B:$B, 0))), "") | AG49: =IFERROR(IF(ISBLANK(INDEX(wos_screening_view_full_text!$Q:$Q, MATCH($A49, wos_screening_view_full_text!$B:$B, 0))), "", INDEX(wos_screening_view_full_text!$Q:$Q, MATCH($A49, wos_screening_view_full_text!$B:$B, 0))), "")
A50: 93 | B50: WOS_savedrecs_1_r000126 | D50: WoS | E50: 1 | F50: 2026-02-26_005404 | G50: C:\Users\Luís Pinto Coelho\Desktop\Dissertação\StudyScreening_Meta-Analysis\data\web_of_science\raw_data\savedrecs_1.xls | H50: 126 | I50: 2026-02-26 | J50: Shahid, M; Saleem, MF; Anjum, SA; Shahid, M; Afzal, I | K50: 2017 | L50: BIOCHEMICAL MARKERS ASSISTED SCREENING OF PAKISTANI WHEAT (Triticum aestivum L.) CULTIVARS FOR TERMINAL HEAT STRESS TOLERANCE | M50: Heat stress is an important abiotic constraint limiting crop productivity. An experiment was conducted to elucidate the impacts of heat induced biochemical transformations on morphological attributes of Pakistani wheat genotypes. Experiment was laid out in randomized complete block design (RCBD) with the split plot arrangement during the winter season 2014-15. Main plot treatments were comprised of H-0 (No heat imposition) and H-1 [(Heat imposition from spike emergence to grain filling initiation (Feekes Scale = 10.50 to 11.00)]. Subplots treatments were comprised of eleven wheat genotypes (Punjab-2011, AARI-2011, Galaxy-2013, Millat-2011, Aas-2011, Fareed-2006, Chakwal-50, Mairaj-2008, Pakistan-2013, NIBGE-NIAB-1 and Kohistan-97). Under heat over control, lesser decrease in chlorophyll contents and enhancement in antioxidant activities were depicted by Aas-2011, Chakwal-50, and Mairaj-2008. Higher chlorophyll degradation and diminishment in antioxidant activities under heat stress over control was observed for all other cultivars. Comparatively lower grain filling rate, higher duration, number of grains per spike and grain yield was observed for cultivars Aas-2011, Chakwal-50, Mairaj-2008 and Punjab-2011 under heat stress over control. Conclusively, based on biochemical response and morphological markers genotypes Aas-2011, Chakwal-50, and Mairaj-2008 manifested heat tolerance. Genotypes Fareed-2006 and Punjab-2011 manifested medium heat tolerance. Whereas, genotypes AARI-2011, Galaxy-2013, Millat-2011, Pakistan-2013, NIBGE-NIAB-1 and Kohistan-97 depicted susceptibility to terminal heat stress. | N50: Antioxidant defense system; grain yield; morphogenesis; stay green; thermotolerance | O50: PAKISTAN JOURNAL OF AGRICULTURAL SCIENCES | P50: 54 | Q50: 4 | R50: 837 | S50: 845 | U50: mfsuaf@yahoo.com | V50: 10.21162/pakjas/17.6040 | W50: https://doi.org/10.21162/pakjas/17.6040 | X50: 0 | Y50: not_found | Z50: 93__BIOCHEMICAL_MARKERS_ASSISTED_SCREENING_OF_PAKISTANI_WHEAT_(Triticum_aestivum_L.)_CULTIVARS_FOR_TERMINAL_HEAT_STRESS_TOLERANCE.pdf | AA50: https://pakjas.com.pk/download.php?fileName=2771.pdf | AC50: 404 | AD50: 2026-03-15 11:26:43 | AE50: =IFERROR(IF(ISBLANK(INDEX(wos_screening_view_full_text!$O:$O, MATCH($A50, wos_screening_view_full_text!$B:$B, 0))), "", INDEX(wos_screening_view_full_text!$O:$O, MATCH($A50, wos_screening_view_full_text!$B:$B, 0))), "") | AF50: =IFERROR(IF(ISBLANK(INDEX(wos_screening_view_full_text!$P:$P, MATCH($A50, wos_screening_view_full_text!$B:$B, 0))), "", INDEX(wos_screening_view_full_text!$P:$P, MATCH($A50, wos_screening_view_full_text!$B:$B, 0))), "") | AG50: =IFERROR(IF(ISBLANK(INDEX(wos_screening_view_full_text!$Q:$Q, MATCH($A50, wos_screening_view_full_text!$B:$B, 0))), "", INDEX(wos_screening_view_full_text!$Q:$Q, MATCH($A50, wos_screening_view_full_text!$B:$B, 0))), "")
A51: 95 | B51: WOS_savedrecs_1_r000128 | D51: WoS | E51: 1 | F51: 2026-02-26_005404 | G51: C:\Users\Luís Pinto Coelho\Desktop\Dissertação\StudyScreening_Meta-Analysis\data\web_of_science\raw_data\savedrecs_1.xls | H51: 128 | I51: 2026-02-26 | J51: Singh, A; Shukla, PK; Prasad, SS; Singh, S; Mishra, P; Rajeshwar, JR; Ramesh, GB; Ramteke, PW; Buddiga, J; Chester, JRE | K51: 2025 | L51: Differential effects of high-temperature stress on the morphophysiological traits of different Wheat (Triticum aestivum L.) genotypes | M51: High-temperature stress (HTS) is one of the significant constraints in crop production under climate change. The temperature rises from 32 degrees C during the wheat reproductive and grain-filling stage, leading to yield penalties. In the present investigation, ten different wheat genotypes were evaluated at three different times of the same cropping year to assess the effect of HTS on developmental patterns and yield. The physiological characterization assessed chlorophyll content (CC) and cell membrane stability (CMS). However, the Canopy temperature depression (CTD) was measured at the three development stages, pre-anthesis, anthesis and post-anthesis, under HTS conditions to identify promising genotypes for developing new breeding lines. Simultaneously the morphological characterization viz. days to 50 % heading (HD), (SW), grain number per spike (GN/S), grain weight (GW), test grain weight (TGW) and grain yield per plot (GY/P) were analyzed to correlate the yield under HTS. Statistical analysis was done using a factorial ANOVA in all the genotypes and K910-30 showed better responses with CC, CMS and TGW values under HTS conditions. Simultaneously, the assessment of morphological traits revealed that the K910-30 genotype performed better than other genotypes. The results of the present investigation will be helpful in future studies dealing with improved hightemperature stress tolerance in wheat. They might be beneficial for identifying wheat genotypes that can withstand high-temperature stress. | N51: abiotic stress; crop improvement; dryland cropping; genetic variability | O51: PLANT SCIENCE TODAY | P51: 12 | Q51: 3 | T51: 6103 | U51: robertedwinchester@kluniversity.in | V51: 10.14719/pst.6103 | W51: https://doi.org/10.14719/pst.6103 | X51: 1 | Y51: downloaded | Z51: 95__Differential_effects_of_high-temperature_stress_on_the_morphophysiological_traits_of_different_Wheat_(Triticum_aestivum_L.)_genotypes.pdf | AA51: https://horizonepublishing.com/journals/index.php/PST/article/download/6103/8769 | AB51: pdf_files/95__Differential_effects_of_high-temperature_stress_on_the_morphophysiological_traits_of_different_Wheat_(Triticum_aestivum_L.)_genotypes.pdf | AC51: 200 | AD51: 2026-03-15 11:26:49 | AE51: =IFERROR(IF(ISBLANK(INDEX(wos_screening_view_full_text!$O:$O, MATCH($A51, wos_screening_view_full_text!$B:$B, 0))), "", INDEX(wos_screening_view_full_text!$O:$O, MATCH($A51, wos_screening_view_full_text!$B:$B, 0))), "") | AF51: =IFERROR(IF(ISBLANK(INDEX(wos_screening_view_full_text!$P:$P, MATCH($A51, wos_screening_view_full_text!$B:$B, 0))), "", INDEX(wos_screening_view_full_text!$P:$P, MATCH($A51, wos_screening_view_full_text!$B:$B, 0))), "") | AG51: =IFERROR(IF(ISBLANK(INDEX(wos_screening_view_full_text!$Q:$Q, MATCH($A51, wos_screening_view_full_text!$B:$B, 0))), "", INDEX(wos_screening_view_full_text!$Q:$Q, MATCH($A51, wos_screening_view_full_text!$B:$B, 0))), "")
A52: 97 | B52: WOS_savedrecs_1_r000130 | D52: WoS | E52: 1 | F52: 2026-02-26_005404 | G52: C:\Users\Luís Pinto Coelho\Desktop\Dissertação\StudyScreening_Meta-Analysis\data\web_of_science\raw_data\savedrecs_1.xls | H52: 130 | I52: 2026-02-26 | J52: Dias, AS; Lidon, FC | K52: 2009 | L52: Evaluation of Grain Filling Rate and Duration in Bread and Durum Wheat, under Heat Stress after Anthesis | M52: Bread and durum wheat genotypes were submitted to heat stress during the grain filling period, and relationships between grain weight and accumulated time from anthesis until maturity, using days after anthesis and growing degree days, were described by cubic polynomials. Maximum grain weight and the duration and rate of grain filling were estimated from the fitted curves. It was found that bread and durum wheat exposure to high temperatures significantly decreased grain weight and hastens physiological maturity (shortening the grain filling period). High temperatures significantly affected the rate (on a growing degree day basis) and duration (on Julian day units) of grain filling. The grain filling rate, on a thermal time basis, was positively associated with the final grain weight and the estimated maximum grain weight. The duration of grain filling does not appear to be a limiting factor for genotype grain weight stability, being mainly fixed by temperature. Grain weight of the controlled plants was positively correlated with the final and maximum grain weight of heat stressed plants. It was concluded that a high grain filling rate and a high potential grain weight are major traits that can be useful to improve heat tolerance of Triticum under Mediterranean environments. | N52: grain filling rate and duration; grain weight; high temperatures; Triticum aestivum L; Triticum turgidum ssp; durum | O52: JOURNAL OF AGRONOMY AND CROP SCIENCE | P52: 195 | Q52: 2 | R52: 137 | S52: 147 | U52: anasofia.almeida@gmail.com | V52: 10.1111/j.1439-037x.2008.00347.x | W52: https://doi.org/10.1111/j.1439-037x.2008.00347.x | X52: 0 | Y52: paywalled | Z52: 97__Evaluation_of_Grain_Filling_Rate_and_Duration_in_Bread_and_Durum_Wheat,_under_Heat_Stress_after_Anthesis.pdf | AA52: https://onlinelibrary.wiley.com/doi/10.1111/j.1439-037X.2008.00347.x | AC52: 403 | AD52: 2026-03-15 11:26:50 | AE52: =IFERROR(IF(ISBLANK(INDEX(wos_screening_view_full_text!$O:$O, MATCH($A52, wos_screening_view_full_text!$B:$B, 0))), "", INDEX(wos_screening_view_full_text!$O:$O, MATCH($A52, wos_screening_view_full_text!$B:$B, 0))), "") | AF52: =IFERROR(IF(ISBLANK(INDEX(wos_screening_view_full_text!$P:$P, MATCH($A52, wos_screening_view_full_text!$B:$B, 0))), "", INDEX(wos_screening_view_full_text!$P:$P, MATCH($A52, wos_screening_view_full_text!$B:$B, 0))), "") | AG52: =IFERROR(IF(ISBLANK(INDEX(wos_screening_view_full_text!$Q:$Q, MATCH($A52, wos_screening_view_full_text!$B:$B, 0))), "", INDEX(wos_screening_view_full_text!$Q:$Q, MATCH($A52, wos_screening_view_full_text!$B:$B, 0))), "")
A53: 98 | B53: WOS_savedrecs_1_r000131 | D53: WoS | E53: 1 | F53: 2026-02-26_005404 | G53: C:\Users\Luís Pinto Coelho\Desktop\Dissertação\StudyScreening_Meta-Analysis\data\web_of_science\raw_data\savedrecs_1.xls | H53: 131 | I53: 2026-02-26 | J53: Wollenweber, B; Porter, JR; Schellberg, J | K53: 2003 | L53: Lack of interaction between extreme high-temperature events at vegetative and reproductive growth stages in wheat | M53: Increased climatic variability and more frequent episodes of extreme conditions may result in crops being exposed to more than one extreme temperature event in a single growing season and could decrease crop yields to the same extent as changes in mean temperature. The developmental stage of the crop exposed to increased temperatures will determine the severity of possible damage experienced by the plant. It is not known whether or not the damaging effects of heat episodes occurring at different phenological stages are additive. In the present study, the interaction of high-temperature events applied at the stages of double ridges and anthesis in Triticum aestivum (L.) cv. Chablis was investigated. Biomass accumulation of control plants and that of plants experiencing high temperatures during the double-ridge stage were similar and were reduced by 40 % when plants were subjected to a heat event at anthesis. Grain number on the main and side tillers declined by 41 %, and individual grain weight declined by 45 % with heat stress applied at the double-ridge stage and anthesis or at anthesis alone. The harvest index was reduced from 0.53 to 0.33. Nitrogen contents in leaves were reduced by 10 % at the double-ridge stage and by 25 % at anthesis. The maximum rates of CO2 assimilation increased with heat stress at the double-ridge stage and higher rates were maintained throughout the growing season. The results clearly indicate that an extreme heat event at the double-ridge stage does not affect subsequent growth or the response of wheat to heat stress at anthesis. | N53: anthesis; double ridges; extreme temperature events; grain yield | O53: JOURNAL OF AGRONOMY AND CROP SCIENCE | P53: 189 | Q53: 3 | R53: 142 | S53: 150 | V53: 10.1046/j.1439-037x.2003.00025.x | W53: https://doi.org/10.1046/j.1439-037x.2003.00025.x | X53: 0 | Y53: paywalled | Z53: 98__Lack_of_interaction_between_extreme_high-temperature_events_at_vegetative_and_reproductive_growth_stages_in_wheat.pdf | AA53: https://onlinelibrary.wiley.com/doi/10.1046/j.1439-037X.2003.00025.x | AC53: 403 | AD53: 2026-03-15 11:26:52 | AE53: =IFERROR(IF(ISBLANK(INDEX(wos_screening_view_full_text!$O:$O, MATCH($A53, wos_screening_view_full_text!$B:$B, 0))), "", INDEX(wos_screening_view_full_text!$O:$O, MATCH($A53, wos_screening_view_full_text!$B:$B, 0))), "") | AF53: =IFERROR(IF(ISBLANK(INDEX(wos_screening_view_full_text!$P:$P, MATCH($A53, wos_screening_view_full_text!$B:$B, 0))), "", INDEX(wos_screening_view_full_text!$P:$P, MATCH($A53, wos_screening_view_full_text!$B:$B, 0))), "") | AG53: =IFERROR(IF(ISBLANK(INDEX(wos_screening_view_full_text!$Q:$Q, MATCH($A53, wos_screening_view_full_text!$B:$B, 0))), "", INDEX(wos_screening_view_full_text!$Q:$Q, MATCH($A53, wos_screening_view_full_text!$B:$B, 0))), "")
A54: 101 | B54: WOS_savedrecs_1_r000137 | D54: WoS | E54: 1 | F54: 2026-02-26_005404 | G54: C:\Users\Luís Pinto Coelho\Desktop\Dissertação\StudyScreening_Meta-Analysis\data\web_of_science\raw_data\savedrecs_1.xls | H54: 137 | I54: 2026-02-26 | J54: Hütsch, BW; Jahn, D; Schubert, S | K54: 2019 | L54: Grain yield of wheat (Triticum aestivum L.) under long-term heat stress is sink-limited with stronger inhibition of kernel setting than grain filling | M54: The aim of the study was to investigate source-sink relations of wheat under continuous heat stress and to identify bottle necks of yield formation. A pot experiment was conducted in two climatic chambers exposing wheat plants (Triticum aestivum L. cv. Thasos) either to day/night temperatures of 20/20 degrees C (control conditions) or of 30/25 degrees C (heat stress) during the whole vegetation period in the absence of plant water deficit. Plants were harvested at four phenological stages: three-node stage (DC 33), start of flowering (DC 61), grain filling (DC 75) and maturity (DC 94). Heat stress shortened the development phases of the plants and caused a significant decrease in total above-ground biomass between 19% and 41%. At grain filling and at maturity, the reductions in total shoot biomass mainly resulted from grain yield depressions by 77% and 58%, respectively. The ear number per plant was significantly higher under heat stress in comparison with the control, at maturity it was more than doubled. On the contrary, under heat stress, the kernel number per ear was strongly decreased by 83% and 75% during grain filling and at maturity, respectively. The decrease in individual kernel weight was 23% at maturity. Thus, the heat-stressed plants were able to strongly increase the number of ear-bearing tillers which were able to set only a small number of kernels, yet these kernels showed good grain filling. The harvest index (HI) of heat-stressed plants was significantly reduced by 36% (control: HI = 50.1% +/- 0.4, heat: HI = 32.2% +/- 0.9***). The plants in the stress treatment adapted to the adverse conditions by less biomass production which presumably allowed a higher transpiration without an increase in total water consumption. Nevertheless, under heat stress, the water use efficiency (WUEgrain) was strongly decreased by 62% as a result of a small grain yield. In ears and grains, the sucrose, glucose and fructose concentrations were not significantly different between control and heat stress at start of flowering and during grain filling. Thus, the supply of assimilates was not restricted (no source limitation). Sink capacity was reduced by heat stress, as lesser and smaller kernels were produced than in the control. Concerning sink activity, the sink-limiting step during kernel set is probably the active transport of hexoses across the plasma membrane into the developing kernels, which could also affect grain filling. This needs to be investigated in more detail in further studies. | N54: assimilate partitioning; phenological stages; sugar concentrations; tillering; water consumption | O54: JOURNAL OF AGRONOMY AND CROP SCIENCE | P54: 205 | Q54: 1 | R54: 22 | S54: 32 | U54: Birgit.W.Huetsch@ernaehrung.uni-giessen.de | V54: 10.1111/jac.12298 | W54: https://doi.org/10.1111/jac.12298 | X54: 0 | Y54: paywalled | Z54: 101__Grain_yield_of_wheat_(Triticum_aestivum_L.)_under_long-term_heat_stress_is_sink-limited_with_stronger_inhibition_of_kernel_setting_than_grai.pdf | AA54: https://onlinelibrary.wiley.com/doi/10.1111/jac.12298 | AC54: 403 | AD54: 2026-03-15 11:26:53 | AE54: =IFERROR(IF(ISBLANK(INDEX(wos_screening_view_full_text!$O:$O, MATCH($A54, wos_screening_view_full_text!$B:$B, 0))), "", INDEX(wos_screening_view_full_text!$O:$O, MATCH($A54, wos_screening_view_full_text!$B:$B, 0))), "") | AF54: =IFERROR(IF(ISBLANK(INDEX(wos_screening_view_full_text!$P:$P, MATCH($A54, wos_screening_view_full_text!$B:$B, 0))), "", INDEX(wos_screening_view_full_text!$P:$P, MATCH($A54, wos_screening_view_full_text!$B:$B, 0))), "") | AG54: =IFERROR(IF(ISBLANK(INDEX(wos_screening_view_full_text!$Q:$Q, MATCH($A54, wos_screening_view_full_text!$B:$B, 0))), "", INDEX(wos_screening_view_full_text!$Q:$Q, MATCH($A54, wos_screening_view_full_text!$B:$B, 0))), "")
A55: 103 | B55: WOS_savedrecs_1_r000139 | D55: WoS | E55: 1 | F55: 2026-02-26_005404 | G55: C:\Users\Luís Pinto Coelho\Desktop\Dissertação\StudyScreening_Meta-Analysis\data\web_of_science\raw_data\savedrecs_1.xls | H55: 139 | I55: 2026-02-26 | J55: Sarwar, M; Saleem, MF; Anwar, A; Ahmad, H; Ali, B; Shahid, M; Hashem, A; Kumar, A; Abd-Allah, EF | K55: 2025 | L55: Exogenous Zinc Alleviates Post-Anthesis Heat Stress by Improving the Defense Mechanism and Leaf Physiology of Bread Wheat | M55: Background: Heat waves following anthesis significantly affect leaf physiology and grain yield of bread wheat in most parts of the world. Purpose: The aim of this study was to measure the impact of heat damage on wheat leaf physiology and grain yield, as well as to develop a technique to recover from heat induced damage by applying zinc (Zn), which plays a role in leaf physiology, plant defense, enzyme activation and membrane stability under abiotic stresses. Methods: Wheat genotypes, Anaj-17 (relatively heat susceptible) and Ujala-16 (relatively heat tolerant), were grown in pots and subjected to heat stress for seven days under polythene sheets one and two-weeks after anthesis (Zodak 69 and 71). Before the imposition of heat stress, wheat plants were sprayed with 0.2% Zn as ZnSO4. The experiment was conducted in completely randomized design with split factorial arrangements. Results: Averaged over the second week after anthesis of 2019 and the first week after anthesis of 2020, the seven days of heat stress reduced the grain numbers per spike, individual grain weight, 1000 grain weight, flag leaf senescence, net photosynthetic rate and stomatal conductance by 32%, 22%, 33%, 32%, 29% and 28%, respectively, while relative cell injury was increased by 38% compared to control (ambient) plants. More heat damage was observed in Anaj-17 over the Ujala-16. Foliar application of Zn at high temperatures resulted in higher heat tolerance in the Ujala-16 over the Anaj-17. Application of Zn increased grain weight, grain numbers and antioxidants by 18%, 14% and 100% while reduced the flag leaf senescence by 20% averaged across the high temperature regimes of both study years over the control treatment. Conclusions: Further studies are needed under field conditions to generalize the findings that wheat crops would. | N55: Beneficial management practices; Triticum aestivum L.; Early and medium stages of post-anthesis; Foliar zinc; High temperature stress; Grain filling | O55: JOURNAL OF SOIL SCIENCE AND PLANT NUTRITION | P55: 25 | Q55: 3 | R55: 6029 | S55: 6044 | U55: mfsuaf@yahoo.com | V55: 10.1007/s42729-025-02516-7 | W55: https://doi.org/10.1007/s42729-025-02516-7 | X55: 1 | Y55: downloaded | Z55: 103__Exogenous_Zinc_Alleviates_Post-Anthesis_Heat_Stress_by_Improving_the_Defense_Mechanism_and_Leaf_Physiology_of_Bread_Wheat.pdf | AA55: https://link.springer.com/content/pdf/10.1007/s42729-025-02516-7.pdf | AB55: pdf_files/103__Exogenous_Zinc_Alleviates_Post-Anthesis_Heat_Stress_by_Improving_the_Defense_Mechanism_and_Leaf_Physiology_of_Bread_Wheat.pdf | AC55: 200 | AD55: 2026-03-15 11:26:57 | AE55: =IFERROR(IF(ISBLANK(INDEX(wos_screening_view_full_text!$O:$O, MATCH($A55, wos_screening_view_full_text!$B:$B, 0))), "", INDEX(wos_screening_view_full_text!$O:$O, MATCH($A55, wos_screening_view_full_text!$B:$B, 0))), "") | AF55: =IFERROR(IF(ISBLANK(INDEX(wos_screening_view_full_text!$P:$P, MATCH($A55, wos_screening_view_full_text!$B:$B, 0))), "", INDEX(wos_screening_view_full_text!$P:$P, MATCH($A55, wos_screening_view_full_text!$B:$B, 0))), "") | AG55: =IFERROR(IF(ISBLANK(INDEX(wos_screening_view_full_text!$Q:$Q, MATCH($A55, wos_screening_view_full_text!$B:$B, 0))), "", INDEX(wos_screening_view_full_text!$Q:$Q, MATCH($A55, wos_screening_view_full_text!$B:$B, 0))), "")
A56: 104 | B56: WOS_savedrecs_1_r000140 | D56: WoS | E56: 1 | F56: 2026-02-26_005404 | G56: C:\Users\Luís Pinto Coelho\Desktop\Dissertação\StudyScreening_Meta-Analysis\data\web_of_science\raw_data\savedrecs_1.xls | H56: 140 | I56: 2026-02-26 | J56: Li, YB; Tao, FL; Hao, YF; Tong, JY; Xiao, YG; He, ZH; Reynolds, M | K56: 2023 | L56: Traits and the associated loci in wheat favoring extreme high temperature tolerance | M56: Extreme temperature, especially heat stress, is increasingly limiting wheat production, resulting in a large yield loss worldwide. Identifying the cultivars, traits and molecular mechanisms conferring extreme high temperature tolerance is essential for comprehending crop resilience to extreme climates and breeding climate-resilient cultivars. Here, we identified 23 extreme high temperature-tolerant cultivars (11.0%) out of 209 wheat culti-vars based on mass field experiments. In an extreme high temperature year, wheat grain yield was significantly reduced by 27.1% among all the genotypes. We found that radiation use efficiency, plant height, thousand-grain weight, flag leaf width, accumulated thermal time to flowering, net photosynthetic rate and SPAD at flowering and grain filling rate could be the traits associated with extreme high temperature tolerance. These traits were indicative of yield in two years differing in temperature, exhibiting a high heritability. Additionally, 203 loci associated with these traits were identified. The results indicated that the interval 755.97-767.82 Mb on chro-mosome 2 A was linked to flag leaf area, grain yield, accumulated thermal time to flowering and maturity, leaf dry weight at flowering and spike dry weight at flowering, resulting in a cumulative genetic effect on yield. Our findings identify wheat cultivars, traits and associated loci for extreme high temperature tolerance selection, facilitating marker-assisted breeding of cultivars under a changing climate. | N56: Heat stress; Intraspecific variation; Photosynthetic traits; Triticum aestivum L; Marker-traits associations; Adaptation | O56: EUROPEAN JOURNAL OF AGRONOMY | P56: 145 | T56: 126776 | U56: taofl@igsnrr.ac.cn; zhhecaas@163.com | V56: 10.1016/j.eja.2023.126776 | W56: https://doi.org/10.1016/j.eja.2023.126776 | X56: 0 | Y56: manual_check | Z56: 104__Traits_and_the_associated_loci_in_wheat_favoring_extreme_high_temperature_tolerance.pdf | AA56: https://linkinghub.elsevier.com/retrieve/pii/S1161030123000448 | AC56: 200 | AD56: 2026-03-15 11:26:59 | AE56: =IFERROR(IF(ISBLANK(INDEX(wos_screening_view_full_text!$O:$O, MATCH($A56, wos_screening_view_full_text!$B:$B, 0))), "", INDEX(wos_screening_view_full_text!$O:$O, MATCH($A56, wos_screening_view_full_text!$B:$B, 0))), "") | AF56: =IFERROR(IF(ISBLANK(INDEX(wos_screening_view_full_text!$P:$P, MATCH($A56, wos_screening_view_full_text!$B:$B, 0))), "", INDEX(wos_screening_view_full_text!$P:$P, MATCH($A56, wos_screening_view_full_text!$B:$B, 0))), "") | AG56: =IFERROR(IF(ISBLANK(INDEX(wos_screening_view_full_text!$Q:$Q, MATCH($A56, wos_screening_view_full_text!$B:$B, 0))), "", INDEX(wos_screening_view_full_text!$Q:$Q, MATCH($A56, wos_screening_view_full_text!$B:$B, 0))), "")
A57: 105 | B57: WOS_savedrecs_1_r000141 | D57: WoS | E57: 1 | F57: 2026-02-26_005404 | G57: C:\Users\Luís Pinto Coelho\Desktop\Dissertação\StudyScreening_Meta-Analysis\data\web_of_science\raw_data\savedrecs_1.xls | H57: 141 | I57: 2026-02-26 | J57: Thomelin, P; Bonneau, J; Brien, C; Suchecki, R; Baumann, U; Kalambettu, P; Langridge, P; Tricker, P; Fleury, D | K57: 2021 | L57: The wheat Seven in absentia gene is associated with increases in biomass and yield in hot climates | M57: Wheat (Triticum aestivum L.) productivity is severely reduced by high temperatures. Breeding of heat-tolerant cultivars can be achieved by identifying genes controlling physiological and agronomical traits when high temperatures occur and using these to select superior genotypes, but no gene underlying genetic variation for heat tolerance has previously been described. We advanced the positional cloning of qYDH.3BL, a quantitative trait locus (QTL) on bread wheat chromosome 3B associated with increased yield in hot and dry climates. The delimited genomic region contained 12 putative genes and a sequence variant in the promoter region of one gene, Seven in absentia, TaSINA. This was associated with the QTL's effects on early vigour, root growth, plant biomass, and yield components in two distinct wheat populations grown under various growth conditions. Near isogenic lines carrying the positive allele at qYDH.3BL underexpressed TaSINA and had increased vigour and water use efficiency early in development, as well as increased biomass, grain number, and grain weight following heat stress. A survey of worldwide distribution indicated that the positive allele became widespread from the 1950s through the CIMMYT wheat breeding programme but, to date, has been selected only in breeding programmes in Mexico and Australia. | N57: Cereal; drought; E3 ligase; grain; heat stress; positional cloning; Triticum aestivum | O57: JOURNAL OF EXPERIMENTAL BOTANY | P57: 72 | Q57: 10 | R57: 3774 | S57: 3791 | U57: delphine.fleury@adelaide.edu.au | V57: 10.1093/jxb/erab044 | W57: https://doi.org/10.1093/jxb/erab044 | X57: 0 | Y57: paywalled | Z57: 105__The_wheat_Seven_in_absentia_gene_is_associated_with_increases_in_biomass_and_yield_in_hot_climates.pdf | AA57: https://academic.oup.com/jxb/article/72/10/3774/6128899 | AC57: 403 | AD57: 2026-03-15 11:27:00 | AE57: =IFERROR(IF(ISBLANK(INDEX(wos_screening_view_full_text!$O:$O, MATCH($A57, wos_screening_view_full_text!$B:$B, 0))), "", INDEX(wos_screening_view_full_text!$O:$O, MATCH($A57, wos_screening_view_full_text!$B:$B, 0))), "") | AF57: =IFERROR(IF(ISBLANK(INDEX(wos_screening_view_full_text!$P:$P, MATCH($A57, wos_screening_view_full_text!$B:$B, 0))), "", INDEX(wos_screening_view_full_text!$P:$P, MATCH($A57, wos_screening_view_full_text!$B:$B, 0))), "") | AG57: =IFERROR(IF(ISBLANK(INDEX(wos_screening_view_full_text!$Q:$Q, MATCH($A57, wos_screening_view_full_text!$B:$B, 0))), "", INDEX(wos_screening_view_full_text!$Q:$Q, MATCH($A57, wos_screening_view_full_text!$B:$B, 0))), "")
A58: 106 | B58: WOS_savedrecs_1_r000142 | D58: WoS | E58: 1 | F58: 2026-02-26_005404 | G58: C:\Users\Luís Pinto Coelho\Desktop\Dissertação\StudyScreening_Meta-Analysis\data\web_of_science\raw_data\savedrecs_1.xls | H58: 142 | I58: 2026-02-26 | J58: Shirdelmoghanloo, H; Cozzolino, D; Lohraseb, I; Collins, NC | K58: 2016 | L58: Truncation of grain filling in wheat (Triticum aestivum) triggered by brief heat stress during early grain filling: association with senescence responses and reductions in stem reserves | M58: Short heat waves during grain filling can reduce grain size and consequently yield in wheat (Triticum aestivum L.). Grain weight responses to heat represent the net outcome of reduced photosynthesis, increased mobilisation of stem reserves (water-soluble carbohydrates, WSC) and accelerated senescence in the grain. To compare their relative roles in grain weight responses under heat, these characteristics were monitored in nine wheat genotypes subjected to a brief heat stress at early grain filling (37 degrees C maximum for 3 days at 10 days after anthesis). Compared with the five tolerant varieties, the four susceptible varieties showed greater heat-triggered reductions in final grain weight, grain filling duration, flag leaf chla and chlb content, stem WSC and PSII functionality (F-v/F-m). Despite the potential for reductions in sugar supply to the developing grains, there was little effect of heat on grain filling rate, suggesting that grain size effects of heat may have instead been driven by premature senescence in the grain. Extreme senescence responses potentially masked stem WSC contributions to grain weight stability. Based on these findings, limiting heat-triggered senescence in the grain may provide an appropriate focus for improving heat tolerance in wheat. | N58: grain weight; photosynthesis; stay-green; temperature; water-soluble carbohydrate | O58: FUNCTIONAL PLANT BIOLOGY | P58: 43 | Q58: 10 | R58: 919 | S58: 930 | U58: nick.collins@acpfg.com.au | V58: 10.1071/fp15384 | W58: https://doi.org/10.1071/fp15384 | X58: 0 | Y58: paywalled | Z58: 106__Truncation_of_grain_filling_in_wheat_(Triticum_aestivum)_triggered_by_brief_heat_stress_during_early_grain_filling_association_with_senescen.pdf | AA58: https://connectsci.au/fp/article/43/10/919/54873/Truncation-of-grain-filling-in-wheat-Triticum | AC58: 403 | AD58: 2026-03-15 11:27:02 | AE58: =IFERROR(IF(ISBLANK(INDEX(wos_screening_view_full_text!$O:$O, MATCH($A58, wos_screening_view_full_text!$B:$B, 0))), "", INDEX(wos_screening_view_full_text!$O:$O, MATCH($A58, wos_screening_view_full_text!$B:$B, 0))), "") | AF58: =IFERROR(IF(ISBLANK(INDEX(wos_screening_view_full_text!$P:$P, MATCH($A58, wos_screening_view_full_text!$B:$B, 0))), "", INDEX(wos_screening_view_full_text!$P:$P, MATCH($A58, wos_screening_view_full_text!$B:$B, 0))), "") | AG58: =IFERROR(IF(ISBLANK(INDEX(wos_screening_view_full_text!$Q:$Q, MATCH($A58, wos_screening_view_full_text!$B:$B, 0))), "", INDEX(wos_screening_view_full_text!$Q:$Q, MATCH($A58, wos_screening_view_full_text!$B:$B, 0))), "")
A59: 109 | B59: WOS_savedrecs_1_r000146 | D59: WoS | E59: 1 | F59: 2026-02-26_005404 | G59: C:\Users\Luís Pinto Coelho\Desktop\Dissertação\StudyScreening_Meta-Analysis\data\web_of_science\raw_data\savedrecs_1.xls | H59: 146 | I59: 2026-02-26 | J59: Samita; Kumar, M; Singh, V; Yadav, S; Yadav, S; Kavita; Kumar, D; Choudhary, RR | K59: 2022 | L59: Assessment of genetic variability in bread Wheat (Triticum aestivum) under heat stress | M59: The present study was carried out during rabi 2017-18, at wheat research farm, Department of genetics and plant breeding, CCS Haryana Agricultural University, Hisar, Haryana to assess the genetic diversity of 64 genotypesof bread wheat (Triticum aestivum L.) under late sown conditions based on the moipho-physiological traits. Analysis of variance depicted significant differences for all morpho-physiological traits under heat stress. Mean sum of squares due to genotypes were found significant for all the traits, indicating the presence of sufficient genetic variability among the genotypes. High estimates of phenotypic coefficient of variation (PCV), genotypic coefficient of variation (GCV) and high heritability coupled with high genetic advance were observed for traits, viz. spike weight, relative stress injury, chlorophyll stability index and GGR28 indicating additive gene action in expression of the traits and simple selection will be effective for the improvement of these traits. Correlation coefficient analysis revealed that increased grain yield under heat stress conditions was significantly contributed by spike weight (0.699), spike length (0.646), harvest index (0.616), spikelets per spike (0.445), number of productive tillers (0.393), grains per spike (0.390), 1000-grain weight (0.364), biological yield (0.360), GGR14 (0.332) and chlorophyll stability index (0.330). Among the traits studied, biological yield per plot (0.8421) and harvest index (0.9686) recorded for highest positive direct effect on grain yield in late sown conditions. The grain yield is indirectly contributed by spike length, spike weight, spikelets per spike, CSI, GGR14 through harvest index and number of productive tillers per meter, spike weight, thousand grain weight, GGR14 through biological yield. | N59: Diversity; Grain yield; Heat stress; Wheat | O59: INDIAN JOURNAL OF AGRICULTURAL SCIENCES | P59: 92 | Q59: 4 | R59: 511 | S59: 515 | U59: samitacoa@gmail.com | V59: 10.56093/ijas.v92i4.124005 | W59: https://doi.org/10.56093/ijas.v92i4.124005 | X59: 1 | Y59: downloaded | Z59: 109__Assessment_of_genetic_variability_in_bread_Wheat_(Triticum_aestivum)_under_heat_stress.pdf | AA59: https://epubs.icar.org.in/index.php/IJAgS/article/download/124005/46901 | AB59: pdf_files/109__Assessment_of_genetic_variability_in_bread_Wheat_(Triticum_aestivum)_under_heat_stress.pdf | AC59: 200 | AD59: 2026-03-15 11:27:13 | AE59: =IFERROR(IF(ISBLANK(INDEX(wos_screening_view_full_text!$O:$O, MATCH($A59, wos_screening_view_full_text!$B:$B, 0))), "", INDEX(wos_screening_view_full_text!$O:$O, MATCH($A59, wos_screening_view_full_text!$B:$B, 0))), "") | AF59: =IFERROR(IF(ISBLANK(INDEX(wos_screening_view_full_text!$P:$P, MATCH($A59, wos_screening_view_full_text!$B:$B, 0))), "", INDEX(wos_screening_view_full_text!$P:$P, MATCH($A59, wos_screening_view_full_text!$B:$B, 0))), "") | AG59: =IFERROR(IF(ISBLANK(INDEX(wos_screening_view_full_text!$Q:$Q, MATCH($A59, wos_screening_view_full_text!$B:$B, 0))), "", INDEX(wos_screening_view_full_text!$Q:$Q, MATCH($A59, wos_screening_view_full_text!$B:$B, 0))), "")
A60: 111 | B60: WOS_savedrecs_1_r000149 | D60: WoS | E60: 1 | F60: 2026-02-26_005404 | G60: C:\Users\Luís Pinto Coelho\Desktop\Dissertação\StudyScreening_Meta-Analysis\data\web_of_science\raw_data\savedrecs_1.xls | H60: 149 | I60: 2026-02-26 | J60: Goyal, A; Munjal, R; Rani, B; Swami, P; Kumari, A | K60: 2023 | L60: Correlation between physiological and yield attributes in bread wheat genotypes for high temperature tolerance | M60: Aim: The aim of the present study was to observe the role of heat stress in the correlation of physiological and yield attributes in bread wheat genotypes.Methodology: (PBW781, RWP-2018-30, PBW821, RWP-2018-31, WH1239, RWP-2018-26, and RWP-2018-32) along with three check varities namely DBW14, WH730, and RAJ3765 were grown under timely sown (TS) and late sown (LS) conditions in the field research area of Wheat Section, CCS HAU, Hisar (2018-19). For generating heat stress, delay in sowing (4 weeks) was done in late sown from timely sown. These wheat lines were assessed for several physiological and yield attributes under both conditions and one genotype was found to be heat-tolerant under late sown condition. Seven wheat genotypesResults: PBW821 was classified as thermo-tolerant due to maximum grain yield, higher normalized difference vegetation index, photosynthetic rate, chlorophyll content, and lower canopy temperature compared to other varieties under late sown conditions. Interpretation: resistant wheat genotype would be a valuable resource for developing high-yielding cultivars Identification of a heat -under high-temperature conditions, and these findings might also be used in breeding programs. | N60: Grain yield; Heat tolerance; Physiological traits; Triticum aestivum | O60: JOURNAL OF ENVIRONMENTAL BIOLOGY | P60: 44 | Q60: 5 | R60: 665 | S60: 675 | U60: anitahsr@gmail.com | V60: 10.22438/jeb/44/5/mrn-4096 | W60: https://doi.org/10.22438/jeb/44/5/mrn-4096 | X60: 1 | Y60: downloaded | Z60: 111__Correlation_between_physiological_and_yield_attributes_in_bread_wheat_genotypes_for_high_temperature_tolerance.pdf | AA60: http://jeb.co.in./journal_issues/202309_sep23/paper_03.pdf | AB60: pdf_files/111__Correlation_between_physiological_and_yield_attributes_in_bread_wheat_genotypes_for_high_temperature_tolerance.pdf | AC60: 200 | AD60: 2026-03-15 11:27:16 | AE60: =IFERROR(IF(ISBLANK(INDEX(wos_screening_view_full_text!$O:$O, MATCH($A60, wos_screening_view_full_text!$B:$B, 0))), "", INDEX(wos_screening_view_full_text!$O:$O, MATCH($A60, wos_screening_view_full_text!$B:$B, 0))), "") | AF60: =IFERROR(IF(ISBLANK(INDEX(wos_screening_view_full_text!$P:$P, MATCH($A60, wos_screening_view_full_text!$B:$B, 0))), "", INDEX(wos_screening_view_full_text!$P:$P, MATCH($A60, wos_screening_view_full_text!$B:$B, 0))), "") | AG60: =IFERROR(IF(ISBLANK(INDEX(wos_screening_view_full_text!$Q:$Q, MATCH($A60, wos_screening_view_full_text!$B:$B, 0))), "", INDEX(wos_screening_view_full_text!$Q:$Q, MATCH($A60, wos_screening_view_full_text!$B:$B, 0))), "")
